Workbook

Sheet Locations
A1: Location Profile | AZ1: =TODAY() -> 46266 | BA1: Food Cost - Inventory Routines and Mobile App Setup | BL1: Last Revised - 03/24/26 4:33 PM
A2: Location Name | B2: Owner/Operator | C2: OperatorEmail | D2: OperatorEmail2 | E2: Organization | F2: Supervisor | G2: Effective Date | H2: SupEmail | I2: GM | J2: GMEmail | K2: Email Domain | L2: Users | M2: MDP Email | N2: MDP Password | O2: LocNameForDisplay | P2: Address | Q2: Inventory D/W/M Setup Verified | R2: eProduction Settings Updated and Verified | S2: eProduction Verified Date | T2: Weekly Inventory Count Day | U2: FOB Risk Profile | V2: FOB Driver | W2: Controls Risk Profile | X2: Controls Driver | Y2: Primary Counting Manager | Z2: Mobile Inventory App Training Occurred | AA2: Mobile App Training Scheduled | AB2: Martin Brower Delivery Day 1 | AC2: Martin Brower Delivery Day 2 | AD2: Martin Brower Delivery Day 3 | AE2: Store Settings Updated for Inventory | AF2: Scheduling Manager | AG2: Schedule Workshop | AH2: FLH Verified | AI2: Availability Update | AJ2: Skill Levels Updated | AK2: 1st Schedule Week | BA2: Location | BB2: Supervisor | BC2: GM | BD2: Counting Manager | BE2: Time Needed | BF2: Date Scheduled | BG2: Start Time | BH2: RGR Date | BI2: Count Day | BJ2: FOB Risk | BK2: Validity | BL2: Status | BM2: Store Settings Updated for Inventory
A3: 3708 | B3: Ryan Thorley | C3: =LEFT(Table1[[#This Row],[Owner/Operator]], SEARCH(" ", Table1[[#This Row],[Owner/Operator]]) - 1) & "@" & Table1[[#This Row],[Email Domain]] -> Ryan@mcdok.com | E3: MCDOK | F3: Robert Spencer | H3: =LEFT(Table1[[#This Row],[Supervisor]], SEARCH(" ", Table1[[#This Row],[Supervisor]]) - 1) & "@" & Table1[[#This Row],[Email Domain]] -> Robert@mcdok.com | I3: Cinthya Armedariz | J3: =LEFT(Table1[[#This Row],[GM]], SEARCH(" ", Table1[[#This Row],[GM]]) - 1) & "@" & Table1[[#This Row],[Email Domain]] -> Cinthya@mcdok.com | K3: mcdok.com | L3: 461 | M3: ="mcdok.mdp+"&Table1[[#This Row],[Location Name]]&"@gmail.com" -> mcdok.mdp+3708@gmail.com | N3: ="Mcdok.mdp"&Table1[[#This Row],[Location Name]] -> Mcdok.mdp3708 | O3: 3708 - ARDMORE-BROADWAY | P3: 1001 W Broadway, Ardmore, OK, 73401, USA | Q3: Yes | R3: No | T3: Tuesday | U3: =_xlfn.XLOOKUP(Table1[[#This Row],[Location Name]],'Risk Profiles'!$A$18:$A$37,'Risk Profiles'!$B$18:$B$37) -> Medium | V3: =_xlfn.XLOOKUP(Table1[[#This Row],[Location Name]],'Risk Profiles'!$A$18:$A$37,'Risk Profiles'!$C$18:$C$37) -> Within Normal range | W3: =_xlfn.XLOOKUP(Table1[[#This Row],[Location Name]],'Risk Profiles'!$A$18:$A$37,'Risk Profiles'!$D$18:$D$37) -> High | X3: =_xlfn.XLOOKUP(Table1[[#This Row],[Location Name]],'Risk Profiles'!$A$18:$A$37,'Risk Profiles'!$E$18:$E$37) -> T-Red After (0.29%), Cash O/S (0.04%), Overrings (0.58%) | Y3: Cinthya | Z3: Yes | AA3: =_xlfn.XLOOKUP(A3,Table3[Location],Table3[Date Scheduled]) -> 46133 | AB3: Wednesday | AC3: Sunday | AE3: 46128 | AF3: Siara | AG3: 46268 | AH3: Yes | AI3: Yes | AJ3: Yes | AK3: =IFERROR(INDEX('Scheduling Setup'!$L:$L,MATCH($A3,'Scheduling Setup'!$A:$A,0)),"") -> 46274 | BA3: 6972 | BB3: =_xlfn.XLOOKUP($BA3,$A$3:$A$32,$F$3:$F$32) -> Robert Spencer | BC3: =_xlfn.XLOOKUP($BA3,$A$3:$A$32,$I$3:$I$32) -> Nick Rice | BD3: =IF(_xlfn.XLOOKUP($BA3,$A$3:$A$32,$Y$3:$Y$32)="","",_xlfn.XLOOKUP($BA3,$A$3:$A$32,$Y$3:$Y$32)) -> Beth | BF3: 46065 | BH3: =_xlfn.XLOOKUP(Table3[[#This Row],[Location]],Table4[STORE '#],Table4[DATE RGR]) -> 46063 | BI3: =_xlfn.XLOOKUP(Table3[[#This Row],[Location]],Table1[Location Name],Table1[Weekly Inventory Count Day]) -> Thursday | BJ3: =_xlfn.XLOOKUP(Table3[[#This Row],[Location]],Table1[Location Name],Table1[FOB Risk Profile]) -> Medium | BM3: 46128
A4: 5183 | B4: Gary Mornhinweg | C4: =LEFT(Table1[[#This Row],[Owner/Operator]], SEARCH(" ", Table1[[#This Row],[Owner/Operator]]) - 1) & "@" & Table1[[#This Row],[Email Domain]] -> Gary@mcdok.com | E4: MCDOK | F4: Krystiana Langford | H4: =LEFT(Table1[[#This Row],[Supervisor]], SEARCH(" ", Table1[[#This Row],[Supervisor]]) - 1) & "@" & Table1[[#This Row],[Email Domain]] -> Krystiana@mcdok.com | I4: Mukarram Norman | J4: =LEFT(Table1[[#This Row],[GM]], SEARCH(" ", Table1[[#This Row],[GM]]) - 1) & "@" & Table1[[#This Row],[Email Domain]] -> Mukarram@mcdok.com | K4: mcdok.com | L4: 465 | M4: ="mcdok.mdp+"&Table1[[#This Row],[Location Name]]&"@gmail.com" -> mcdok.mdp+5183@gmail.com | N4: ="Mcdok.mdp"&Table1[[#This Row],[Location Name]] -> Mcdok.mdp5183 | O4: 5183 - CHICKASHA-SO 4TH | P4: 2027 S 4th St, Chickasha, OK, 73018, USA | Q4: Yes | R4: No | T4: Thursday | U4: =_xlfn.XLOOKUP(Table1[[#This Row],[Location Name]],'Risk Profiles'!$A$18:$A$37,'Risk Profiles'!$B$18:$B$37) -> Medium | V4: =_xlfn.XLOOKUP(Table1[[#This Row],[Location Name]],'Risk Profiles'!$A$18:$A$37,'Risk Profiles'!$C$18:$C$37) -> Stat Var (1.80%) | W4: =_xlfn.XLOOKUP(Table1[[#This Row],[Location Name]],'Risk Profiles'!$A$18:$A$37,'Risk Profiles'!$D$18:$D$37) -> Medium | X4: =_xlfn.XLOOKUP(Table1[[#This Row],[Location Name]],'Risk Profiles'!$A$18:$A$37,'Risk Profiles'!$E$18:$E$37) -> Cash O/S (0.04%), Discounts (6.57%) | Y4: Mukarram | Z4: Yes | AA4: =_xlfn.XLOOKUP(A4,Table3[Location],Table3[Date Scheduled]) -> 46163 | AB4: Tuesday | AC4: Friday | AE4: 46128 | AF4: Pam | AG4: 46247 | AH4: Yes | AI4: Yes | AJ4: Yes | AK4: =IFERROR(INDEX('Scheduling Setup'!$L:$L,MATCH($A4,'Scheduling Setup'!$A:$A,0)),"") -> 46260 | BA4: 24471 | BB4: =_xlfn.XLOOKUP($BA4,$A$3:$A$32,$F$3:$F$32) -> Robert Spencer | BC4: =_xlfn.XLOOKUP($BA4,$A$3:$A$32,$I$3:$I$32) -> Mystykal Abbey | BD4: =IF(_xlfn.XLOOKUP($BA4,$A$3:$A$32,$Y$3:$Y$32)="","",_xlfn.XLOOKUP($BA4,$A$3:$A$32,$Y$3:$Y$32)) -> Mystikal | BF4: 46086 | BH4: =_xlfn.XLOOKUP(Table3[[#This Row],[Location]],Table4[STORE '#],Table4[DATE RGR]) -> 46309 | BI4: =_xlfn.XLOOKUP(Table3[[#This Row],[Location]],Table1[Location Name],Table1[Weekly Inventory Count Day]) -> Thursday | BJ4: =_xlfn.XLOOKUP(Table3[[#This Row],[Location]],Table1[Location Name],Table1[FOB Risk Profile]) -> High | BM4: 46128
A5: 5985 | B5: Rick/Kathy Thorley | C5: rick@mcdok.com | D5: kathy@mcdok.com | E5: MCDOK | F5: Ashley Podroza | H5: =LEFT(Table1[[#This Row],[Supervisor]], SEARCH(" ", Table1[[#This Row],[Supervisor]]) - 1) & "@" & Table1[[#This Row],[Email Domain]] -> Ashley@mcdok.com | I5: Stacey Hyatt | J5: =LEFT(Table1[[#This Row],[GM]], SEARCH(" ", Table1[[#This Row],[GM]]) - 1) & "@" & Table1[[#This Row],[Email Domain]] -> Stacey@mcdok.com | K5: mcdok.com | L5: 490 | M5: ="mcdok.mdp+"&Table1[[#This Row],[Location Name]]&"@gmail.com" -> mcdok.mdp+5985@gmail.com | N5: ="Mcdok.mdp"&Table1[[#This Row],[Location Name]] -> Mcdok.mdp5985 | O5: 5985 - DURANT-US HWY 704/22 | P5: 2227 W Main St, Durant, OK, 74701, USA | Q5: Yes | R5: No | T5: Tuesday | U5: =_xlfn.XLOOKUP(Table1[[#This Row],[Location Name]],'Risk Profiles'!$A$18:$A$37,'Risk Profiles'!$B$18:$B$37) -> Low | V5: =_xlfn.XLOOKUP(Table1[[#This Row],[Location Name]],'Risk Profiles'!$A$18:$A$37,'Risk Profiles'!$C$18:$C$37) -> Within Normal range | W5: =_xlfn.XLOOKUP(Table1[[#This Row],[Location Name]],'Risk Profiles'!$A$18:$A$37,'Risk Profiles'!$D$18:$D$37) -> Low | X5: =_xlfn.XLOOKUP(Table1[[#This Row],[Location Name]],'Risk Profiles'!$A$18:$A$37,'Risk Profiles'!$E$18:$E$37) -> Within Normal range | Y5: Scauti/Chas | Z5: Yes | AA5: =_xlfn.XLOOKUP(A5,Table3[Location],Table3[Date Scheduled]) -> 46116 | AB5: Tuesday | AC5: Friday | AD5: Sunday | AE5: 46128 | AF5: Chasity | AG5: 46251 | AH5: Yes | AI5: Yes | AJ5: Yes | AK5: =IFERROR(INDEX('Scheduling Setup'!$L:$L,MATCH($A5,'Scheduling Setup'!$A:$A,0)),"") -> 46260 | BA5: 43380 | BB5: =_xlfn.XLOOKUP($BA5,$A$3:$A$32,$F$3:$F$32) -> Ashley Podroza | BC5: =_xlfn.XLOOKUP($BA5,$A$3:$A$32,$I$3:$I$32) -> Zukarr Eaves | BD5: =IF(_xlfn.XLOOKUP($BA5,$A$3:$A$32,$Y$3:$Y$32)="","",_xlfn.XLOOKUP($BA5,$A$3:$A$32,$Y$3:$Y$32)) -> Zukaar | BF5: 46088 | BH5: =_xlfn.XLOOKUP(Table3[[#This Row],[Location]],Table4[STORE '#],Table4[DATE RGR]) -> 46225 | BI5: =_xlfn.XLOOKUP(Table3[[#This Row],[Location]],Table1[Location Name],Table1[Weekly Inventory Count Day]) -> Saturday | BJ5: =_xlfn.XLOOKUP(Table3[[#This Row],[Location]],Table1[Location Name],Table1[FOB Risk Profile]) -> Medium | BM5: 46128
A6: 6972 | B6: Ryan Thorley | C6: =LEFT(Table1[[#This Row],[Owner/Operator]], SEARCH(" ", Table1[[#This Row],[Owner/Operator]]) - 1) & "@" & Table1[[#This Row],[Email Domain]] -> Ryan@mcdok.com | E6: MCDOK | F6: Robert Spencer | H6: =LEFT(Table1[[#This Row],[Supervisor]], SEARCH(" ", Table1[[#This Row],[Supervisor]]) - 1) & "@" & Table1[[#This Row],[Email Domain]] -> Robert@mcdok.com | I6: Nick Rice | J6: =LEFT(Table1[[#This Row],[GM]], SEARCH(" ", Table1[[#This Row],[GM]]) - 1) & "@" & Table1[[#This Row],[Email Domain]] -> Nick@mcdok.com | K6: mcdok.com | L6: 503 | M6: ="mcdok.mdp+"&Table1[[#This Row],[Location Name]]&"@gmail.com" -> mcdok.mdp+6972@gmail.com | N6: ="Mcdok.mdp"&Table1[[#This Row],[Location Name]] -> Mcdok.mdp6972 | O6: 6972 - ADA-COUNTRY CLUB | P6: 818 N Country Club Rd, Ada, OK, 74820, USA | Q6: Yes | R6: No | T6: Thursday | U6: =_xlfn.XLOOKUP(Table1[[#This Row],[Location Name]],'Risk Profiles'!$A$18:$A$37,'Risk Profiles'!$B$18:$B$37) -> Medium | V6: =_xlfn.XLOOKUP(Table1[[#This Row],[Location Name]],'Risk Profiles'!$A$18:$A$37,'Risk Profiles'!$C$18:$C$37) -> Within Normal Range | W6: =_xlfn.XLOOKUP(Table1[[#This Row],[Location Name]],'Risk Profiles'!$A$18:$A$37,'Risk Profiles'!$D$18:$D$37) -> Medium | X6: =_xlfn.XLOOKUP(Table1[[#This Row],[Location Name]],'Risk Profiles'!$A$18:$A$37,'Risk Profiles'!$E$18:$E$37) -> POS Overrings (0.38%)/Excessively High T-Reds | Y6: Beth | Z6: Yes | AA6: =_xlfn.XLOOKUP(A6,Table3[Location],Table3[Date Scheduled]) -> 46065 | AB6: Tuesday | AC6: Friday | AE6: 46128 | AF6: Bobbi | AG6: 46261 | AH6: Yes | AI6: Yes | AJ6: Yes | AK6: =IFERROR(INDEX('Scheduling Setup'!$L:$L,MATCH($A6,'Scheduling Setup'!$A:$A,0)),"") -> 46267 | BA6: 35064 | BB6: =_xlfn.XLOOKUP($BA6,$A$3:$A$32,$F$3:$F$32) -> Steven Vaughn | BC6: =_xlfn.XLOOKUP($BA6,$A$3:$A$32,$I$3:$I$32) -> Lynsey Yahola | BD6: =IF(_xlfn.XLOOKUP($BA6,$A$3:$A$32,$Y$3:$Y$32)="","",_xlfn.XLOOKUP($BA6,$A$3:$A$32,$Y$3:$Y$32)) -> Lynsey | BF6: 46092 | BH6: =_xlfn.XLOOKUP(Table3[[#This Row],[Location]],Table4[STORE '#],Table4[DATE RGR]) -> 46211 | BI6: =_xlfn.XLOOKUP(Table3[[#This Row],[Location]],Table1[Location Name],Table1[Weekly Inventory Count Day]) -> Wednesday | BJ6: =_xlfn.XLOOKUP(Table3[[#This Row],[Location]],Table1[Location Name],Table1[FOB Risk Profile]) -> High | BM6: 46128
A7: 10422 | B7: Rick/Kathy Thorley | C7: rick@mcdok.com | D7: kathy@mcdok.com | E7: MCDOK | F7: Ashley Podroza | H7: =LEFT(Table1[[#This Row],[Supervisor]], SEARCH(" ", Table1[[#This Row],[Supervisor]]) - 1) & "@" & Table1[[#This Row],[Email Domain]] -> Ashley@mcdok.com | I7: Ashleyh Hegwer | J7: =LEFT(Table1[[#This Row],[GM]], SEARCH(" ", Table1[[#This Row],[GM]]) - 1) & "@" & Table1[[#This Row],[Email Domain]] -> Ashleyh@mcdok.com | K7: mcdok.com | L7: 471 | M7: ="mcdok.mdp+"&Table1[[#This Row],[Location Name]]&"@gmail.com" -> mcdok.mdp+10422@gmail.com | N7: ="Mcdok.mdp"&Table1[[#This Row],[Location Name]] -> Mcdok.mdp10422 | O7: 10422 - ATOKA, OK-MISSISSIPPI | P7: 1100 S Mississippi Ave, Atoka, OK, 74525, USA | Q7: Yes | R7: No | T7: Saturday | U7: =_xlfn.XLOOKUP(Table1[[#This Row],[Location Name]],'Risk Profiles'!$A$18:$A$37,'Risk Profiles'!$B$18:$B$37) -> High | V7: =_xlfn.XLOOKUP(Table1[[#This Row],[Location Name]],'Risk Profiles'!$A$18:$A$37,'Risk Profiles'!$C$18:$C$37) -> High Stat Var (2.16%)/Coordinated Register Theft | W7: =_xlfn.XLOOKUP(Table1[[#This Row],[Location Name]],'Risk Profiles'!$A$18:$A$37,'Risk Profiles'!$D$18:$D$37) -> High | X7: =_xlfn.XLOOKUP(Table1[[#This Row],[Location Name]],'Risk Profiles'!$A$18:$A$37,'Risk Profiles'!$E$18:$E$37) -> POS Overrings (0.47%) | Y7: Ashley | Z7: Yes | AA7: =_xlfn.XLOOKUP(A7,Table3[Location],Table3[Date Scheduled]) -> 46095 | AB7: Wednesday | AC7: Sunday | AE7: 46128 | AF7: Peggy May | AG7: 46240 | AH7: Yes | AI7: Yes | AJ7: Yes | AK7: =IFERROR(INDEX('Scheduling Setup'!$L:$L,MATCH($A7,'Scheduling Setup'!$A:$A,0)),"") -> 46246 | BA7: 10422 | BB7: =_xlfn.XLOOKUP($BA7,$A$3:$A$32,$F$3:$F$32) -> Ashley Podroza | BC7: =_xlfn.XLOOKUP($BA7,$A$3:$A$32,$I$3:$I$32) -> Ashleyh Hegwer | BD7: =IF(_xlfn.XLOOKUP($BA7,$A$3:$A$32,$Y$3:$Y$32)="","",_xlfn.XLOOKUP($BA7,$A$3:$A$32,$Y$3:$Y$32)) -> Ashley | BF7: 46095 | BH7: =_xlfn.XLOOKUP(Table3[[#This Row],[Location]],Table4[STORE '#],Table4[DATE RGR]) -> 46051 | BI7: =_xlfn.XLOOKUP(Table3[[#This Row],[Location]],Table1[Location Name],Table1[Weekly Inventory Count Day]) -> Saturday | BJ7: =_xlfn.XLOOKUP(Table3[[#This Row],[Location]],Table1[Location Name],Table1[FOB Risk Profile]) -> High | BM7: 46128
A8: 10915 | B8: Ryan Thorley | C8: =LEFT(Table1[[#This Row],[Owner/Operator]], SEARCH(" ", Table1[[#This Row],[Owner/Operator]]) - 1) & "@" & Table1[[#This Row],[Email Domain]] -> Ryan@mcdok.com | E8: MCDOK | F8: Steven Vaughn | H8: =LEFT(Table1[[#This Row],[Supervisor]], SEARCH(" ", Table1[[#This Row],[Supervisor]]) - 1) & "@" & Table1[[#This Row],[Email Domain]] -> Steven@mcdok.com | I8: Caleb Nunnelley | J8: =LEFT(Table1[[#This Row],[GM]], SEARCH(" ", Table1[[#This Row],[GM]]) - 1) & "@" & Table1[[#This Row],[Email Domain]] -> Caleb@mcdok.com | K8: mcdok.com | L8: 458 | M8: ="mcdok.mdp+"&Table1[[#This Row],[Location Name]]&"@gmail.com" -> mcdok.mdp+10915@gmail.com | N8: ="Mcdok.mdp"&Table1[[#This Row],[Location Name]] -> Mcdok.mdp10915 | O8: 10915 - SEMINOLE, OK-MILT PHILLIPS | P8: 1423 Milt Phillips, Seminole, OK, 74868, USA | Q8: Yes | R8: No | T8: Wednesday | U8: =_xlfn.XLOOKUP(Table1[[#This Row],[Location Name]],'Risk Profiles'!$A$18:$A$37,'Risk Profiles'!$B$18:$B$37) -> Medium | V8: =_xlfn.XLOOKUP(Table1[[#This Row],[Location Name]],'Risk Profiles'!$A$18:$A$37,'Risk Profiles'!$C$18:$C$37) -> High Waste (1.06%) | W8: =_xlfn.XLOOKUP(Table1[[#This Row],[Location Name]],'Risk Profiles'!$A$18:$A$37,'Risk Profiles'!$D$18:$D$37) -> High | X8: =_xlfn.XLOOKUP(Table1[[#This Row],[Location Name]],'Risk Profiles'!$A$18:$A$37,'Risk Profiles'!$E$18:$E$37) -> T-Red After (0.45%), Discounts (6.55%) | Y8: Caitlin | Z8: Yes | AA8: =_xlfn.XLOOKUP(A8,Table3[Location],Table3[Date Scheduled]) -> 46148 | AB8: Thursday | AC8: Monday | AE8: 46129 | AF8: Tasha | AG8: 46252 | AH8: Yes | AI8: Yes | AJ8: Yes | AK8: =IFERROR(INDEX('Scheduling Setup'!$L:$L,MATCH($A8,'Scheduling Setup'!$A:$A,0)),"") -> 46260 | BA8: 29760 | BB8: =_xlfn.XLOOKUP($BA8,$A$3:$A$32,$F$3:$F$32) -> Krystiana Langford | BC8: =_xlfn.XLOOKUP($BA8,$A$3:$A$32,$I$3:$I$32) -> Heather Danforth | BD8: =IF(_xlfn.XLOOKUP($BA8,$A$3:$A$32,$Y$3:$Y$32)="","",_xlfn.XLOOKUP($BA8,$A$3:$A$32,$Y$3:$Y$32)) -> Magi | BF8: 46100 | BH8: =_xlfn.XLOOKUP(Table3[[#This Row],[Location]],Table4[STORE '#],Table4[DATE RGR]) -> 46323 | BI8: =_xlfn.XLOOKUP(Table3[[#This Row],[Location]],Table1[Location Name],Table1[Weekly Inventory Count Day]) -> Thursday | BJ8: =_xlfn.XLOOKUP(Table3[[#This Row],[Location]],Table1[Location Name],Table1[FOB Risk Profile]) -> Low | BM8: 46129
A9: 11657 | B9: Gary Mornhinweg | C9: =LEFT(Table1[[#This Row],[Owner/Operator]], SEARCH(" ", Table1[[#This Row],[Owner/Operator]]) - 1) & "@" & Table1[[#This Row],[Email Domain]] -> Gary@mcdok.com | E9: MCDOK | F9: Amanda Estrada | H9: =LEFT(Table1[[#This Row],[Supervisor]], SEARCH(" ", Table1[[#This Row],[Supervisor]]) - 1) & "@" & Table1[[#This Row],[Email Domain]] -> Amanda@mcdok.com | I9: Jessie Hiatt | J9: =LEFT(Table1[[#This Row],[GM]], SEARCH(" ", Table1[[#This Row],[GM]]) - 1) & "@" & Table1[[#This Row],[Email Domain]] -> Jessie@mcdok.com | K9: mcdok.com | L9: 440 | M9: ="mcdok.mdp+"&Table1[[#This Row],[Location Name]]&"@gmail.com" -> mcdok.mdp+11657@gmail.com | N9: ="Mcdok.mdp"&Table1[[#This Row],[Location Name]] -> Mcdok.mdp11657 | O9: 11657 - PURCELL | P9: 2211 S 9th Ave, Purcell, OK, 73080, USA | Q9: Yes | R9: No | T9: Thursday | U9: =_xlfn.XLOOKUP(Table1[[#This Row],[Location Name]],'Risk Profiles'!$A$18:$A$37,'Risk Profiles'!$B$18:$B$37) -> Medium | V9: =_xlfn.XLOOKUP(Table1[[#This Row],[Location Name]],'Risk Profiles'!$A$18:$A$37,'Risk Profiles'!$C$18:$C$37) -> High Waste (1.29%) | W9: =_xlfn.XLOOKUP(Table1[[#This Row],[Location Name]],'Risk Profiles'!$A$18:$A$37,'Risk Profiles'!$D$18:$D$37) -> Medium | X9: =_xlfn.XLOOKUP(Table1[[#This Row],[Location Name]],'Risk Profiles'!$A$18:$A$37,'Risk Profiles'!$E$18:$E$37) -> Within Normal range | Y9: Norma | Z9: Yes | AA9: =_xlfn.XLOOKUP(A9,Table3[Location],Table3[Date Scheduled]) -> 46149 | AB9: Tuesday | AC9: Friday | AE9: 46129 | AF9: Olivia | AG9: 46260 | AH9: Yes | AI9: Yes | AJ9: Yes | AK9: =IFERROR(INDEX('Scheduling Setup'!$L:$L,MATCH($A9,'Scheduling Setup'!$A:$A,0)),"") -> 46267 | BA9: 5985 | BB9: =_xlfn.XLOOKUP($BA9,$A$3:$A$32,$F$3:$F$32) -> Ashley Podroza | BC9: =_xlfn.XLOOKUP($BA9,$A$3:$A$32,$I$3:$I$32) -> Stacey Hyatt | BD9: =IF(_xlfn.XLOOKUP($BA9,$A$3:$A$32,$Y$3:$Y$32)="","",_xlfn.XLOOKUP($BA9,$A$3:$A$32,$Y$3:$Y$32)) -> Scauti/Chas | BE9: 4-6 Hours | BF9: 46116 | BG9: 0.33333333 | BH9: =_xlfn.XLOOKUP(Table3[[#This Row],[Location]],Table4[STORE '#],Table4[DATE RGR]) -> 46092 | BI9: =_xlfn.XLOOKUP(Table3[[#This Row],[Location]],Table1[Location Name],Table1[Weekly Inventory Count Day]) -> Tuesday | BJ9: =_xlfn.XLOOKUP(Table3[[#This Row],[Location]],Table1[Location Name],Table1[FOB Risk Profile]) -> Low | BK9: Earliest available date | BL9: Unchanged | BM9: 46129
A10: 13113 | B10: Rick/Kathy Thorley | C10: rick@mcdok.com | D10: kathy@mcdok.com | E10: MCDOK | F10: Ashley Podroza | H10: =LEFT(Table1[[#This Row],[Supervisor]], SEARCH(" ", Table1[[#This Row],[Supervisor]]) - 1) & "@" & Table1[[#This Row],[Email Domain]] -> Ashley@mcdok.com | I10: Chris Abbey | J10: =LEFT(Table1[[#This Row],[GM]], SEARCH(" ", Table1[[#This Row],[GM]]) - 1) & "@" & Table1[[#This Row],[Email Domain]] -> Chris@mcdok.com | K10: mcdok.com | L10: 454 | M10: ="mcdok.mdp+"&Table1[[#This Row],[Location Name]]&"@gmail.com" -> mcdok.mdp+13113@gmail.com | N10: ="Mcdok.mdp"&Table1[[#This Row],[Location Name]] -> Mcdok.mdp13113 | O10: 13113 - MADILL, HWY. 70 | P10: 511 S 1st St, Madill, OK, 73446, USA | Q10: Yes | R10: No | T10: Tuesday | U10: =_xlfn.XLOOKUP(Table1[[#This Row],[Location Name]],'Risk Profiles'!$A$18:$A$37,'Risk Profiles'!$B$18:$B$37) -> High | V10: =_xlfn.XLOOKUP(Table1[[#This Row],[Location Name]],'Risk Profiles'!$A$18:$A$37,'Risk Profiles'!$C$18:$C$37) -> High FOB% (5.58%), High Stat Var (2.40%) | W10: =_xlfn.XLOOKUP(Table1[[#This Row],[Location Name]],'Risk Profiles'!$A$18:$A$37,'Risk Profiles'!$D$18:$D$37) -> Medium | X10: =_xlfn.XLOOKUP(Table1[[#This Row],[Location Name]],'Risk Profiles'!$A$18:$A$37,'Risk Profiles'!$E$18:$E$37) -> POS Overrings (0.47%) | Y10: Josh | Z10: Yes | AA10: =_xlfn.XLOOKUP(A10,Table3[Location],Table3[Date Scheduled]) -> 46126 | AB10: Wednesday | AC10: Sunday | AE10: 46129 | AF10: Colton Standeraur | AG10: 46260 | AH10: Yes | AI10: Yes | AJ10: Yes | AK10: =IFERROR(INDEX('Scheduling Setup'!$L:$L,MATCH($A10,'Scheduling Setup'!$A:$A,0)),"") -> 46274 | BA10: 32525 | BB10: =_xlfn.XLOOKUP($BA10,$A$3:$A$32,$F$3:$F$32) -> Robert Spencer | BC10: =_xlfn.XLOOKUP($BA10,$A$3:$A$32,$I$3:$I$32) -> Aliyah Richardson | BD10: =IF(_xlfn.XLOOKUP($BA10,$A$3:$A$32,$Y$3:$Y$32)="","",_xlfn.XLOOKUP($BA10,$A$3:$A$32,$Y$3:$Y$32)) -> Priscilla | BE10: 4-6 Hours | BF10: 46121 | BG10: 0.33333333 | BH10: =_xlfn.XLOOKUP(Table3[[#This Row],[Location]],Table4[STORE '#],Table4[DATE RGR]) -> 46337 | BI10: =_xlfn.XLOOKUP(Table3[[#This Row],[Location]],Table1[Location Name],Table1[Weekly Inventory Count Day]) -> Thursday | BJ10: =_xlfn.XLOOKUP(Table3[[#This Row],[Location]],Table1[Location Name],Table1[FOB Risk Profile]) -> High | BK10: Earliest available date | BL10: Unchanged | BM10: 46129
A11: 18213 | B11: Gary Mornhinweg | C11: =LEFT(Table1[[#This Row],[Owner/Operator]], SEARCH(" ", Table1[[#This Row],[Owner/Operator]]) - 1) & "@" & Table1[[#This Row],[Email Domain]] -> Gary@mcdok.com | E11: MCDOK | F11: Krystiana Langford | H11: =LEFT(Table1[[#This Row],[Supervisor]], SEARCH(" ", Table1[[#This Row],[Supervisor]]) - 1) & "@" & Table1[[#This Row],[Email Domain]] -> Krystiana@mcdok.com | I11: Cora Bahling | J11: =LEFT(Table1[[#This Row],[GM]], SEARCH(" ", Table1[[#This Row],[GM]]) - 1) & "@" & Table1[[#This Row],[Email Domain]] -> Cora@mcdok.com | K11: mcdok.com | L11: 435 | M11: ="mcdok.mdp+"&Table1[[#This Row],[Location Name]]&"@gmail.com" -> mcdok.mdp+18213@gmail.com | N11: ="Mcdok.mdp"&Table1[[#This Row],[Location Name]] -> Mcdok.mdp18213 | O11: 18213 - LINDSAY, OK-WAL*MART | P11: 407 Linwood Plz, Lindsay, OK, 73052, USA | Q11: Yes | R11: No | T11: Thursday | U11: =_xlfn.XLOOKUP(Table1[[#This Row],[Location Name]],'Risk Profiles'!$A$18:$A$37,'Risk Profiles'!$B$18:$B$37) -> Medium | V11: =_xlfn.XLOOKUP(Table1[[#This Row],[Location Name]],'Risk Profiles'!$A$18:$A$37,'Risk Profiles'!$C$18:$C$37) -> High Waste (1.16%) | W11: =_xlfn.XLOOKUP(Table1[[#This Row],[Location Name]],'Risk Profiles'!$A$18:$A$37,'Risk Profiles'!$D$18:$D$37) -> Medium | X11: =_xlfn.XLOOKUP(Table1[[#This Row],[Location Name]],'Risk Profiles'!$A$18:$A$37,'Risk Profiles'!$E$18:$E$37) -> Within Normal range | Y11: Crystal | Z11: Yes | AA11: =_xlfn.XLOOKUP(A11,Table3[Location],Table3[Date Scheduled]) -> 46177 | AB11: Tuesday | AC11: Friday | AE11: 46129 | AF11: Brad | AG11: 46247 | AH11: Yes | AI11: Yes | AJ11: Yes | AK11: =IFERROR(INDEX('Scheduling Setup'!$L:$L,MATCH($A11,'Scheduling Setup'!$A:$A,0)),"") -> 46253 | BA11: 20475 | BB11: =_xlfn.XLOOKUP($BA11,$A$3:$A$32,$F$3:$F$32) -> Amanda Estrada | BC11: =_xlfn.XLOOKUP($BA11,$A$3:$A$32,$I$3:$I$32) -> Derek McGirt | BD11: =IF(_xlfn.XLOOKUP($BA11,$A$3:$A$32,$Y$3:$Y$32)="","",_xlfn.XLOOKUP($BA11,$A$3:$A$32,$Y$3:$Y$32)) -> Susanna | BE11: 4-6 Hours | BF11: 46122 | BG11: 0.33333333 | BH11: =_xlfn.XLOOKUP(Table3[[#This Row],[Location]],Table4[STORE '#],Table4[DATE RGR]) -> 46107 | BI11: =_xlfn.XLOOKUP(Table3[[#This Row],[Location]],Table1[Location Name],Table1[Weekly Inventory Count Day]) -> Thursday | BJ11: =_xlfn.XLOOKUP(Table3[[#This Row],[Location]],Table1[Location Name],Table1[FOB Risk Profile]) -> Low | BK11: Earliest available date | BL11: Unchanged | BM11: 46129
A12: 20475 | B12: Gary Mornhinweg | C12: =LEFT(Table1[[#This Row],[Owner/Operator]], SEARCH(" ", Table1[[#This Row],[Owner/Operator]]) - 1) & "@" & Table1[[#This Row],[Email Domain]] -> Gary@mcdok.com | E12: MCDOK | F12: Amanda Estrada | H12: =LEFT(Table1[[#This Row],[Supervisor]], SEARCH(" ", Table1[[#This Row],[Supervisor]]) - 1) & "@" & Table1[[#This Row],[Email Domain]] -> Amanda@mcdok.com | I12: Derek McGirt | J12: =LEFT(Table1[[#This Row],[GM]], SEARCH(" ", Table1[[#This Row],[GM]]) - 1) & "@" & Table1[[#This Row],[Email Domain]] -> Derek@mcdok.com | K12: mcdok.com | L12: 451 | M12: ="mcdok.mdp+"&Table1[[#This Row],[Location Name]]&"@gmail.com" -> mcdok.mdp+20475@gmail.com | N12: ="Mcdok.mdp"&Table1[[#This Row],[Location Name]] -> Mcdok.mdp20475 | O12: 20475 - OKC-I-240/SOONER | P12: 7800 S Sooner Rd, Oklahoma City, OK, 73135, USA | Q12: Yes | R12: No | T12: Thursday | U12: =_xlfn.XLOOKUP(Table1[[#This Row],[Location Name]],'Risk Profiles'!$A$18:$A$37,'Risk Profiles'!$B$18:$B$37) -> Low | V12: =_xlfn.XLOOKUP(Table1[[#This Row],[Location Name]],'Risk Profiles'!$A$18:$A$37,'Risk Profiles'!$C$18:$C$37) -> Within Normal range | W12: =_xlfn.XLOOKUP(Table1[[#This Row],[Location Name]],'Risk Profiles'!$A$18:$A$37,'Risk Profiles'!$D$18:$D$37) -> Medium | X12: =_xlfn.XLOOKUP(Table1[[#This Row],[Location Name]],'Risk Profiles'!$A$18:$A$37,'Risk Profiles'!$E$18:$E$37) -> T-Red After (0.38%), Discounts (7.40%) | Y12: Susanna | Z12: Yes | AA12: =_xlfn.XLOOKUP(A12,Table3[Location],Table3[Date Scheduled]) -> 46122 | AB12: Tuesday | AC12: Friday | AE12: 46129 | AF12: Rebecca | AG12: 46239 | AH12: Yes | AI12: Yes | AJ12: Yes | AK12: =IFERROR(INDEX('Scheduling Setup'!$L:$L,MATCH($A12,'Scheduling Setup'!$A:$A,0)),"") -> 46246 | BA12: 13113 | BB12: =_xlfn.XLOOKUP($BA12,$A$3:$A$32,$F$3:$F$32) -> Ashley Podroza | BC12: =_xlfn.XLOOKUP($BA12,$A$3:$A$32,$I$3:$I$32) -> Chris Abbey | BD12: =IF(_xlfn.XLOOKUP($BA12,$A$3:$A$32,$Y$3:$Y$32)="","",_xlfn.XLOOKUP($BA12,$A$3:$A$32,$Y$3:$Y$32)) -> Josh | BE12: 4-6 Hours | BF12: 46126 | BG12: 0.33333333 | BH12: =_xlfn.XLOOKUP(Table3[[#This Row],[Location]],Table4[STORE '#],Table4[DATE RGR]) -> 46183 | BI12: =_xlfn.XLOOKUP(Table3[[#This Row],[Location]],Table1[Location Name],Table1[Weekly Inventory Count Day]) -> Tuesday | BJ12: =_xlfn.XLOOKUP(Table3[[#This Row],[Location]],Table1[Location Name],Table1[FOB Risk Profile]) -> High | BK12: Earliest available date | BL12: Unchanged | BM12: 46129
A13: 24471 | B13: Ryan Thorley | C13: =LEFT(Table1[[#This Row],[Owner/Operator]], SEARCH(" ", Table1[[#This Row],[Owner/Operator]]) - 1) & "@" & Table1[[#This Row],[Email Domain]] -> Ryan@mcdok.com | E13: MCDOK | F13: Robert Spencer | H13: =LEFT(Table1[[#This Row],[Supervisor]], SEARCH(" ", Table1[[#This Row],[Supervisor]]) - 1) & "@" & Table1[[#This Row],[Email Domain]] -> Robert@mcdok.com | I13: Mystykal Abbey | J13: =LEFT(Table1[[#This Row],[GM]], SEARCH(" ", Table1[[#This Row],[GM]]) - 1) & "@" & Table1[[#This Row],[Email Domain]] -> Mystykal@mcdok.com | K13: mcdok.com | L13: 459 | M13: ="mcdok.mdp+"&Table1[[#This Row],[Location Name]]&"@gmail.com" -> mcdok.mdp+24471@gmail.com | N13: ="Mcdok.mdp"&Table1[[#This Row],[Location Name]] -> Mcdok.mdp24471 | O13: 24471 - ARDMORE, OK-NEC COOPER/12TH | P13: 1202 Cooper Dr, Ardmore, OK, 73401, USA | Q13: Yes | R13: No | T13: Thursday | U13: =_xlfn.XLOOKUP(Table1[[#This Row],[Location Name]],'Risk Profiles'!$A$18:$A$37,'Risk Profiles'!$B$18:$B$37) -> High | V13: =_xlfn.XLOOKUP(Table1[[#This Row],[Location Name]],'Risk Profiles'!$A$18:$A$37,'Risk Profiles'!$C$18:$C$37) -> High FOB% (5.55%), High Stat Var (2.04%) | W13: =_xlfn.XLOOKUP(Table1[[#This Row],[Location Name]],'Risk Profiles'!$A$18:$A$37,'Risk Profiles'!$D$18:$D$37) -> Medium | X13: =_xlfn.XLOOKUP(Table1[[#This Row],[Location Name]],'Risk Profiles'!$A$18:$A$37,'Risk Profiles'!$E$18:$E$37) -> Within Normal range | Y13: Mystikal | Z13: Yes | AA13: =_xlfn.XLOOKUP(A13,Table3[Location],Table3[Date Scheduled]) -> 46086 | AB13: Wednesday | AC13: Sunday | AE13: 46129 | AF13: Rasheda | AG13: 46268 | AH13: Yes | AI13: Yes | AJ13: Yes | AK13: =IFERROR(INDEX('Scheduling Setup'!$L:$L,MATCH($A13,'Scheduling Setup'!$A:$A,0)),"") -> 46274 | BA13: 3708 | BB13: =_xlfn.XLOOKUP($BA13,$A$3:$A$32,$F$3:$F$32) -> Robert Spencer | BC13: =_xlfn.XLOOKUP($BA13,$A$3:$A$32,$I$3:$I$32) -> Cinthya Armedariz | BD13: =IF(_xlfn.XLOOKUP($BA13,$A$3:$A$32,$Y$3:$Y$32)="","",_xlfn.XLOOKUP($BA13,$A$3:$A$32,$Y$3:$Y$32)) -> Cinthya | BE13: 4-6 Hours | BF13: 46133 | BG13: 0.33333333 | BH13: =_xlfn.XLOOKUP(Table3[[#This Row],[Location]],Table4[STORE '#],Table4[DATE RGR]) -> 46260 | BI13: =_xlfn.XLOOKUP(Table3[[#This Row],[Location]],Table1[Location Name],Table1[Weekly Inventory Count Day]) -> Tuesday | BJ13: =_xlfn.XLOOKUP(Table3[[#This Row],[Location]],Table1[Location Name],Table1[FOB Risk Profile]) -> Medium | BK13: Earliest available date | BL13: Unchanged | BM13: 46129
A14: 29760 | B14: Ryan Thorley | C14: =LEFT(Table1[[#This Row],[Owner/Operator]], SEARCH(" ", Table1[[#This Row],[Owner/Operator]]) - 1) & "@" & Table1[[#This Row],[Email Domain]] -> Ryan@mcdok.com | E14: MCDOK | F14: Krystiana Langford | H14: =LEFT(Table1[[#This Row],[Supervisor]], SEARCH(" ", Table1[[#This Row],[Supervisor]]) - 1) & "@" & Table1[[#This Row],[Email Domain]] -> Krystiana@mcdok.com | I14: Heather Danforth | J14: =LEFT(Table1[[#This Row],[GM]], SEARCH(" ", Table1[[#This Row],[GM]]) - 1) & "@" & Table1[[#This Row],[Email Domain]] -> Heather@mcdok.com | K14: mcdok.com | L14: 483 | M14: ="mcdok.mdp+"&Table1[[#This Row],[Location Name]]&"@gmail.com" -> mcdok.mdp+29760@gmail.com | N14: ="Mcdok.mdp"&Table1[[#This Row],[Location Name]] -> Mcdok.mdp29760 | O14: 29760 - DUNCAN, OK-HWY 81 (RELO) | P14: 1817 N Highway 81, Duncan, OK, 73533, USA | Q14: Yes | R14: No | T14: Thursday | U14: =_xlfn.XLOOKUP(Table1[[#This Row],[Location Name]],'Risk Profiles'!$A$18:$A$37,'Risk Profiles'!$B$18:$B$37) -> Low | V14: =_xlfn.XLOOKUP(Table1[[#This Row],[Location Name]],'Risk Profiles'!$A$18:$A$37,'Risk Profiles'!$C$18:$C$37) -> Within Normal range | W14: =_xlfn.XLOOKUP(Table1[[#This Row],[Location Name]],'Risk Profiles'!$A$18:$A$37,'Risk Profiles'!$D$18:$D$37) -> Low | X14: =_xlfn.XLOOKUP(Table1[[#This Row],[Location Name]],'Risk Profiles'!$A$18:$A$37,'Risk Profiles'!$E$18:$E$37) -> Within Normal range | Y14: Magi | Z14: Yes | AA14: =_xlfn.XLOOKUP(A14,Table3[Location],Table3[Date Scheduled]) -> 46100 | AB14: Tuesday | AC14: Friday | AE14: 46129 | AF14: Stephanie | AG14: 46267 | AH14: Yes | AI14: Yes | AJ14: Yes | AK14: =IFERROR(INDEX('Scheduling Setup'!$L:$L,MATCH($A14,'Scheduling Setup'!$A:$A,0)),"") -> 46267 | BA14: 33222 | BB14: =_xlfn.XLOOKUP($BA14,$A$3:$A$32,$F$3:$F$32) -> Krystiana Langford | BC14: =_xlfn.XLOOKUP($BA14,$A$3:$A$32,$I$3:$I$32) -> Carol Escusa | BD14: =IF(_xlfn.XLOOKUP($BA14,$A$3:$A$32,$Y$3:$Y$32)="","",_xlfn.XLOOKUP($BA14,$A$3:$A$32,$Y$3:$Y$32)) -> Darryl | BE14: 4-6 Hours | BF14: 46135 | BG14: 0.33333333 | BH14: =_xlfn.XLOOKUP(Table3[[#This Row],[Location]],Table4[STORE '#],Table4[DATE RGR]) -> 46169 | BI14: =_xlfn.XLOOKUP(Table3[[#This Row],[Location]],Table1[Location Name],Table1[Weekly Inventory Count Day]) -> Thursday | BJ14: =_xlfn.XLOOKUP(Table3[[#This Row],[Location]],Table1[Location Name],Table1[FOB Risk Profile]) -> High | BK14: Earliest available date | BL14: Changed Fdrom 04/02/26 | BM14: 46129
A15: 31357 | B15: Ryan Thorley | C15: =LEFT(Table1[[#This Row],[Owner/Operator]], SEARCH(" ", Table1[[#This Row],[Owner/Operator]]) - 1) & "@" & Table1[[#This Row],[Email Domain]] -> Ryan@mcdok.com | E15: MCDOK | F15: Amanda Estrada | H15: =LEFT(Table1[[#This Row],[Supervisor]], SEARCH(" ", Table1[[#This Row],[Supervisor]]) - 1) & "@" & Table1[[#This Row],[Email Domain]] -> Amanda@mcdok.com | I15: Brady Giambaresi | J15: =LEFT(Table1[[#This Row],[GM]], SEARCH(" ", Table1[[#This Row],[GM]]) - 1) & "@" & Table1[[#This Row],[Email Domain]] -> Brady@mcdok.com | K15: mcdok.com | L15: 443 | M15: ="mcdok.mdp+"&Table1[[#This Row],[Location Name]]&"@gmail.com" -> mcdok.mdp+31357@gmail.com | N15: ="Mcdok.mdp"&Table1[[#This Row],[Location Name]] -> Mcdok.mdp31357 | O15: 31357 - PAULS VALLEY RELO - BALLARD RD NO. | P15: 2635 W Grant Ave, Pauls Valley, OK, 73075, USA | Q15: Yes | R15: No | T15: Thursday | U15: =_xlfn.XLOOKUP(Table1[[#This Row],[Location Name]],'Risk Profiles'!$A$18:$A$37,'Risk Profiles'!$B$18:$B$37) -> Medium | V15: =_xlfn.XLOOKUP(Table1[[#This Row],[Location Name]],'Risk Profiles'!$A$18:$A$37,'Risk Profiles'!$C$18:$C$37) -> Within Normal range | W15: =_xlfn.XLOOKUP(Table1[[#This Row],[Location Name]],'Risk Profiles'!$A$18:$A$37,'Risk Profiles'!$D$18:$D$37) -> Medium | X15: =_xlfn.XLOOKUP(Table1[[#This Row],[Location Name]],'Risk Profiles'!$A$18:$A$37,'Risk Profiles'!$E$18:$E$37) -> Within Normal range | Y15: Angelo | Z15: Yes | AA15: =_xlfn.XLOOKUP(A15,Table3[Location],Table3[Date Scheduled]) -> 46156 | AB15: Tuesday | AC15: Friday | AE15: 46129 | AF15: Ashleigh | AG15: 46261 | AH15: Yes | AI15: Yes | AJ15: Yes | AK15: =IFERROR(INDEX('Scheduling Setup'!$L:$L,MATCH($A15,'Scheduling Setup'!$A:$A,0)),"") -> 46267 | BA15: 10915 | BB15: =_xlfn.XLOOKUP($BA15,$A$3:$A$32,$F$3:$F$32) -> Steven Vaughn | BC15: =_xlfn.XLOOKUP($BA15,$A$3:$A$32,$I$3:$I$32) -> Caleb Nunnelley | BD15: =IF(_xlfn.XLOOKUP($BA15,$A$3:$A$32,$Y$3:$Y$32)="","",_xlfn.XLOOKUP($BA15,$A$3:$A$32,$Y$3:$Y$32)) -> Caitlin | BE15: 4-6 Hours | BF15: 46148 | BG15: 0.33333333 | BH15: =_xlfn.XLOOKUP(Table3[[#This Row],[Location]],Table4[STORE '#],Table4[DATE RGR]) -> 46071 | BI15: =_xlfn.XLOOKUP(Table3[[#This Row],[Location]],Table1[Location Name],Table1[Weekly Inventory Count Day]) -> Wednesday | BJ15: =_xlfn.XLOOKUP(Table3[[#This Row],[Location]],Table1[Location Name],Table1[FOB Risk Profile]) -> Medium | BK15: Earliest available date | BL15: Unchanged | BM15: 46129
A16: 32525 | B16: Ryan Thorley | C16: =LEFT(Table1[[#This Row],[Owner/Operator]], SEARCH(" ", Table1[[#This Row],[Owner/Operator]]) - 1) & "@" & Table1[[#This Row],[Email Domain]] -> Ryan@mcdok.com | E16: MCDOK | F16: Robert Spencer | H16: =LEFT(Table1[[#This Row],[Supervisor]], SEARCH(" ", Table1[[#This Row],[Supervisor]]) - 1) & "@" & Table1[[#This Row],[Email Domain]] -> Robert@mcdok.com | I16: Aliyah Richardson | J16: =LEFT(Table1[[#This Row],[GM]], SEARCH(" ", Table1[[#This Row],[GM]]) - 1) & "@" & Table1[[#This Row],[Email Domain]] -> Aliyah@mcdok.com | K16: mcdok.com | L16: 440 | M16: ="mcdok.mdp+"&Table1[[#This Row],[Location Name]]&"@gmail.com" -> mcdok.mdp+32525@gmail.com | N16: ="Mcdok.mdp"&Table1[[#This Row],[Location Name]] -> Mcdok.mdp32525 | O16: 32525 - SULPHUR, OK | P16: 2539 W Broadway Ave, Sulphur, OK, 73086, USA | Q16: Yes | R16: No | T16: Thursday | U16: =_xlfn.XLOOKUP(Table1[[#This Row],[Location Name]],'Risk Profiles'!$A$18:$A$37,'Risk Profiles'!$B$18:$B$37) -> High | V16: =_xlfn.XLOOKUP(Table1[[#This Row],[Location Name]],'Risk Profiles'!$A$18:$A$37,'Risk Profiles'!$C$18:$C$37) -> High FOB% (5.27%), High Waste (1.51%) | W16: =_xlfn.XLOOKUP(Table1[[#This Row],[Location Name]],'Risk Profiles'!$A$18:$A$37,'Risk Profiles'!$D$18:$D$37) -> Low | X16: =_xlfn.XLOOKUP(Table1[[#This Row],[Location Name]],'Risk Profiles'!$A$18:$A$37,'Risk Profiles'!$E$18:$E$37) -> Within Normal range | Y16: Priscilla | Z16: Yes | AA16: =_xlfn.XLOOKUP(A16,Table3[Location],Table3[Date Scheduled]) -> 46121 | AB16: Tuesday | AC16: Friday | AE16: 46129 | AF16: Sarah | AG16: 46251 | AH16: Yes | AI16: Yes | AJ16: Yes | AK16: =IFERROR(INDEX('Scheduling Setup'!$L:$L,MATCH($A16,'Scheduling Setup'!$A:$A,0)),"") -> 46267 | BA16: 11657 | BB16: =_xlfn.XLOOKUP($BA16,$A$3:$A$32,$F$3:$F$32) -> Amanda Estrada | BC16: =_xlfn.XLOOKUP($BA16,$A$3:$A$32,$I$3:$I$32) -> Jessie Hiatt | BD16: =IF(_xlfn.XLOOKUP($BA16,$A$3:$A$32,$Y$3:$Y$32)="","",_xlfn.XLOOKUP($BA16,$A$3:$A$32,$Y$3:$Y$32)) -> Norma | BE16: 4-6 Hours | BF16: 46149 | BG16: 0.33333333 | BH16: =_xlfn.XLOOKUP(Table3[[#This Row],[Location]],Table4[STORE '#],Table4[DATE RGR]) -> 46134 | BI16: =_xlfn.XLOOKUP(Table3[[#This Row],[Location]],Table1[Location Name],Table1[Weekly Inventory Count Day]) -> Thursday | BJ16: =_xlfn.XLOOKUP(Table3[[#This Row],[Location]],Table1[Location Name],Table1[FOB Risk Profile]) -> Medium | BK16: Earliest available date | BL16: Changed from 06/04/26 | BM16: 46129
A17: 33109 | B17: Rick/Kathy Thorley | C17: rick@mcdok.com | D17: kathy@mcdok.com | E17: MCDOK | F17: Ashley Podroza | H17: =LEFT(Table1[[#This Row],[Supervisor]], SEARCH(" ", Table1[[#This Row],[Supervisor]]) - 1) & "@" & Table1[[#This Row],[Email Domain]] -> Ashley@mcdok.com | I17: Rey Araiz | J17: =LEFT(Table1[[#This Row],[GM]], SEARCH(" ", Table1[[#This Row],[GM]]) - 1) & "@" & Table1[[#This Row],[Email Domain]] -> Rey@mcdok.com | K17: mcdok.com | L17: 427 | M17: ="mcdok.mdp+"&Table1[[#This Row],[Location Name]]&"@gmail.com" -> mcdok.mdp+33109@gmail.com | N17: ="Mcdok.mdp"&Table1[[#This Row],[Location Name]] -> Mcdok.mdp33109 | O17: 33109 - MARIETTA, OK | P17: 1303 Memorial Dr, Marietta, OK, 73448, USA | Q17: Yes | R17: No | T17: Tuesday | U17: =_xlfn.XLOOKUP(Table1[[#This Row],[Location Name]],'Risk Profiles'!$A$18:$A$37,'Risk Profiles'!$B$18:$B$37) -> Low | V17: =_xlfn.XLOOKUP(Table1[[#This Row],[Location Name]],'Risk Profiles'!$A$18:$A$37,'Risk Profiles'!$C$18:$C$37) -> Within Normal range | W17: =_xlfn.XLOOKUP(Table1[[#This Row],[Location Name]],'Risk Profiles'!$A$18:$A$37,'Risk Profiles'!$D$18:$D$37) -> Low | X17: =_xlfn.XLOOKUP(Table1[[#This Row],[Location Name]],'Risk Profiles'!$A$18:$A$37,'Risk Profiles'!$E$18:$E$37) -> Within Normal range | Y17: Gisselle | Z17: Yes | AA17: =_xlfn.XLOOKUP(A17,Table3[Location],Table3[Date Scheduled]) -> 46170 | AB17: Wednesday | AC17: Sunday | AE17: 46129 | AF17: Angie | AG17: 46252 | AH17: Yes | AI17: Yes | AJ17: Yes | AK17: =IFERROR(INDEX('Scheduling Setup'!$L:$L,MATCH($A17,'Scheduling Setup'!$A:$A,0)),"") -> 46260 | BA17: 31357 | BB17: =_xlfn.XLOOKUP($BA17,$A$3:$A$32,$F$3:$F$32) -> Amanda Estrada | BC17: =_xlfn.XLOOKUP($BA17,$A$3:$A$32,$I$3:$I$32) -> Brady Giambaresi | BD17: =IF(_xlfn.XLOOKUP($BA17,$A$3:$A$32,$Y$3:$Y$32)="","",_xlfn.XLOOKUP($BA17,$A$3:$A$32,$Y$3:$Y$32)) -> Angelo | BE17: 4-6 Hours | BF17: 46156 | BG17: 0.33333333 | BH17: =_xlfn.XLOOKUP(Table3[[#This Row],[Location]],Table4[STORE '#],Table4[DATE RGR]) -> 46197 | BI17: =_xlfn.XLOOKUP(Table3[[#This Row],[Location]],Table1[Location Name],Table1[Weekly Inventory Count Day]) -> Thursday | BJ17: =_xlfn.XLOOKUP(Table3[[#This Row],[Location]],Table1[Location Name],Table1[FOB Risk Profile]) -> Medium | BK17: Earliest available date | BL17: Unchanged | BM17: 46129
A18: 33222 | B18: Ryan Thorley | C18: =LEFT(Table1[[#This Row],[Owner/Operator]], SEARCH(" ", Table1[[#This Row],[Owner/Operator]]) - 1) & "@" & Table1[[#This Row],[Email Domain]] -> Ryan@mcdok.com | E18: MCDOK | F18: Krystiana Langford | H18: =LEFT(Table1[[#This Row],[Supervisor]], SEARCH(" ", Table1[[#This Row],[Supervisor]]) - 1) & "@" & Table1[[#This Row],[Email Domain]] -> Krystiana@mcdok.com | I18: Carol Escusa | J18: =LEFT(Table1[[#This Row],[GM]], SEARCH(" ", Table1[[#This Row],[GM]]) - 1) & "@" & Table1[[#This Row],[Email Domain]] -> Carol@mcdok.com | K18: mcdok.com | L18: 440 | M18: ="mcdok.mdp+"&Table1[[#This Row],[Location Name]]&"@gmail.com" -> mcdok.mdp+33222@gmail.com | N18: ="Mcdok.mdp"&Table1[[#This Row],[Location Name]] -> Mcdok.mdp33222 | O18: 33222 - ELGIN, OK - STO | P18: 7738 US Highway 277, Elgin, OK, 73538, USA | Q18: Yes | R18: Yes | S18: 46082 | T18: Thursday | U18: =_xlfn.XLOOKUP(Table1[[#This Row],[Location Name]],'Risk Profiles'!$A$18:$A$37,'Risk Profiles'!$B$18:$B$37) -> High | V18: =_xlfn.XLOOKUP(Table1[[#This Row],[Location Name]],'Risk Profiles'!$A$18:$A$37,'Risk Profiles'!$C$18:$C$37) -> Bulk Theft/Untracked Waste | W18: =_xlfn.XLOOKUP(Table1[[#This Row],[Location Name]],'Risk Profiles'!$A$18:$A$37,'Risk Profiles'!$D$18:$D$37) -> Low | X18: =_xlfn.XLOOKUP(Table1[[#This Row],[Location Name]],'Risk Profiles'!$A$18:$A$37,'Risk Profiles'!$E$18:$E$37) -> Within Normal range | Y18: Darryl | Z18: Yes | AA18: =_xlfn.XLOOKUP(A18,Table3[Location],Table3[Date Scheduled]) -> 46135 | AB18: Tuesday | AC18: Friday | AE18: 46129 | AF18: Stephanie | AG18: 46267 | AH18: Yes | AI18: Yes | AJ18: Yes | AK18: =IFERROR(INDEX('Scheduling Setup'!$L:$L,MATCH($A18,'Scheduling Setup'!$A:$A,0)),"") -> 46274 | BA18: 33704 | BB18: =_xlfn.XLOOKUP($BA18,$A$3:$A$32,$F$3:$F$32) -> Steven Vaughn | BC18: =_xlfn.XLOOKUP($BA18,$A$3:$A$32,$I$3:$I$32) -> Candy Barksdale | BD18: =IF(_xlfn.XLOOKUP($BA18,$A$3:$A$32,$Y$3:$Y$32)="","",_xlfn.XLOOKUP($BA18,$A$3:$A$32,$Y$3:$Y$32)) -> Marlena | BE18: 4-6 Hours | BF18: 46157 | BG18: 0.33333333 | BH18: =_xlfn.XLOOKUP(Table3[[#This Row],[Location]],Table4[STORE '#],Table4[DATE RGR]) -> 46127 | BI18: =_xlfn.XLOOKUP(Table3[[#This Row],[Location]],Table1[Location Name],Table1[Weekly Inventory Count Day]) -> Friday | BJ18: =_xlfn.XLOOKUP(Table3[[#This Row],[Location]],Table1[Location Name],Table1[FOB Risk Profile]) -> Medium | BK18: Earliest available date | BL18: Unchanged | BM18: 46129
A19: 33704 | B19: Gary Mornhinweg | C19: =LEFT(Table1[[#This Row],[Owner/Operator]], SEARCH(" ", Table1[[#This Row],[Owner/Operator]]) - 1) & "@" & Table1[[#This Row],[Email Domain]] -> Gary@mcdok.com | E19: MCDOK | F19: Steven Vaughn | H19: =LEFT(Table1[[#This Row],[Supervisor]], SEARCH(" ", Table1[[#This Row],[Supervisor]]) - 1) & "@" & Table1[[#This Row],[Email Domain]] -> Steven@mcdok.com | I19: Candy Barksdale | J19: =LEFT(Table1[[#This Row],[GM]], SEARCH(" ", Table1[[#This Row],[GM]]) - 1) & "@" & Table1[[#This Row],[Email Domain]] -> Candy@mcdok.com | K19: mcdok.com | L19: 448 | M19: ="mcdok.mdp+"&Table1[[#This Row],[Location Name]]&"@gmail.com" -> mcdok.mdp+33704@gmail.com | N19: ="Mcdok.mdp"&Table1[[#This Row],[Location Name]] -> Mcdok.mdp33704 | O19: 33704 - TECUMSEH, OK | P19: 1210 Gordon Cooper Dr, Tecumseh, OK, 74873, USA | Q19: Yes | R19: No | T19: Friday | U19: =_xlfn.XLOOKUP(Table1[[#This Row],[Location Name]],'Risk Profiles'!$A$18:$A$37,'Risk Profiles'!$B$18:$B$37) -> Medium | V19: =_xlfn.XLOOKUP(Table1[[#This Row],[Location Name]],'Risk Profiles'!$A$18:$A$37,'Risk Profiles'!$C$18:$C$37) -> Within Normal range | W19: =_xlfn.XLOOKUP(Table1[[#This Row],[Location Name]],'Risk Profiles'!$A$18:$A$37,'Risk Profiles'!$D$18:$D$37) -> Medium | X19: =_xlfn.XLOOKUP(Table1[[#This Row],[Location Name]],'Risk Profiles'!$A$18:$A$37,'Risk Profiles'!$E$18:$E$37) -> High Discounts (7.10%) | Y19: Marlena | Z19: Yes | AA19: =_xlfn.XLOOKUP(A19,Table3[Location],Table3[Date Scheduled]) -> 46157 | AB19: Monday | AC19: Thursday | AE19: 46129 | AF19: Bella | AG19: 46246 | AH19: Yes | AI19: Yes | AJ19: Yes | AK19: =IFERROR(INDEX('Scheduling Setup'!$L:$L,MATCH($A19,'Scheduling Setup'!$A:$A,0)),"") -> 46253 | BA19: 34222 | BB19: =_xlfn.XLOOKUP($BA19,$A$3:$A$32,$F$3:$F$32) -> Steven Vaughn | BC19: =_xlfn.XLOOKUP($BA19,$A$3:$A$32,$I$3:$I$32) -> Hunter McKee | BD19: =IF(_xlfn.XLOOKUP($BA19,$A$3:$A$32,$Y$3:$Y$32)="","",_xlfn.XLOOKUP($BA19,$A$3:$A$32,$Y$3:$Y$32)) -> Kaylee | BE19: 4-6 Hours | BF19: 46162 | BG19: 0.375 | BH19: =_xlfn.XLOOKUP(Table3[[#This Row],[Location]],Table4[STORE '#],Table4[DATE RGR]) -> 46155 | BI19: =_xlfn.XLOOKUP(Table3[[#This Row],[Location]],Table1[Location Name],Table1[Weekly Inventory Count Day]) -> Monday | BJ19: =_xlfn.XLOOKUP(Table3[[#This Row],[Location]],Table1[Location Name],Table1[FOB Risk Profile]) -> Low | BK19: Earliest available date | BL19: Unchanged | BM19: 46129
A20: 34222 | B20: Gary Mornhinweg | C20: =LEFT(Table1[[#This Row],[Owner/Operator]], SEARCH(" ", Table1[[#This Row],[Owner/Operator]]) - 1) & "@" & Table1[[#This Row],[Email Domain]] -> Gary@mcdok.com | E20: MCDOK | F20: Steven Vaughn | H20: =LEFT(Table1[[#This Row],[Supervisor]], SEARCH(" ", Table1[[#This Row],[Supervisor]]) - 1) & "@" & Table1[[#This Row],[Email Domain]] -> Steven@mcdok.com | I20: Hunter McKee | J20: =LEFT(Table1[[#This Row],[GM]], SEARCH(" ", Table1[[#This Row],[GM]]) - 1) & "@" & Table1[[#This Row],[Email Domain]] -> Hunter@mcdok.com | K20: mcdok.com | L20: 449 | M20: ="mcdok.mdp+"&Table1[[#This Row],[Location Name]]&"@gmail.com" -> mcdok.mdp+34222@gmail.com | N20: ="Mcdok.mdp"&Table1[[#This Row],[Location Name]] -> Mcdok.mdp34222 | O20: 34222 - HARRAH, OK | P20: 3115 S Harrah Rd, Harrah, OK, 73045, USA | Q20: Yes | R20: No | T20: Monday | U20: =_xlfn.XLOOKUP(Table1[[#This Row],[Location Name]],'Risk Profiles'!$A$18:$A$37,'Risk Profiles'!$B$18:$B$37) -> Low | V20: =_xlfn.XLOOKUP(Table1[[#This Row],[Location Name]],'Risk Profiles'!$A$18:$A$37,'Risk Profiles'!$C$18:$C$37) -> Within Normal range | W20: =_xlfn.XLOOKUP(Table1[[#This Row],[Location Name]],'Risk Profiles'!$A$18:$A$37,'Risk Profiles'!$D$18:$D$37) -> Medium | X20: =_xlfn.XLOOKUP(Table1[[#This Row],[Location Name]],'Risk Profiles'!$A$18:$A$37,'Risk Profiles'!$E$18:$E$37) -> High Discounts (6.58%) | Y20: Kaylee | Z20: Yes | AA20: =_xlfn.XLOOKUP(A20,Table3[Location],Table3[Date Scheduled]) -> 46162 | AB20: Monday | AC20: Thursday | AE20: 46129 | AF20: Lezli | AG20: 46239 | AH20: Yes | AI20: Yes | AJ20: Yes | AK20: =IFERROR(INDEX('Scheduling Setup'!$L:$L,MATCH($A20,'Scheduling Setup'!$A:$A,0)),"") -> 46246 | BA20: 5183 | BB20: =_xlfn.XLOOKUP($BA20,$A$3:$A$32,$F$3:$F$32) -> Krystiana Langford | BC20: =_xlfn.XLOOKUP($BA20,$A$3:$A$32,$I$3:$I$32) -> Mukarram Norman | BD20: =IF(_xlfn.XLOOKUP($BA20,$A$3:$A$32,$Y$3:$Y$32)="","",_xlfn.XLOOKUP($BA20,$A$3:$A$32,$Y$3:$Y$32)) -> Mukarram | BE20: 4-6 Hours | BF20: 46163 | BG20: 0.33333333 | BH20: =_xlfn.XLOOKUP(Table3[[#This Row],[Location]],Table4[STORE '#],Table4[DATE RGR]) -> 46281 | BI20: =_xlfn.XLOOKUP(Table3[[#This Row],[Location]],Table1[Location Name],Table1[Weekly Inventory Count Day]) -> Thursday | BJ20: =_xlfn.XLOOKUP(Table3[[#This Row],[Location]],Table1[Location Name],Table1[FOB Risk Profile]) -> Medium | BK20: Earliest available date | BL20: Changed from 04/23/26 | BM20: 46129
A21: 35064 | B21: Rick/Kathy Thorley | C21: rick@mcdok.com | D21: kathy@mcdok.com | E21: MCDOK | F21: Steven Vaughn | H21: =LEFT(Table1[[#This Row],[Supervisor]], SEARCH(" ", Table1[[#This Row],[Supervisor]]) - 1) & "@" & Table1[[#This Row],[Email Domain]] -> Steven@mcdok.com | I21: Lynsey Yahola | J21: =LEFT(Table1[[#This Row],[GM]], SEARCH(" ", Table1[[#This Row],[GM]]) - 1) & "@" & Table1[[#This Row],[Email Domain]] -> Lynsey@mcdok.com | K21: mcdok.com | L21: 452 | M21: ="mcdok.mdp+"&Table1[[#This Row],[Location Name]]&"@gmail.com" -> mcdok.mdp+35064@gmail.com | N21: ="Mcdok.mdp"&Table1[[#This Row],[Location Name]] -> Mcdok.mdp35064 | O21: 35064 - HOLDENVILLE, OK | P21: 424 E Highway St, Holdenville, OK, 74848, USA | Q21: Yes | R21: Yes | S21: 46106 | T21: Wednesday | U21: =_xlfn.XLOOKUP(Table1[[#This Row],[Location Name]],'Risk Profiles'!$A$18:$A$37,'Risk Profiles'!$B$18:$B$37) -> High | V21: =_xlfn.XLOOKUP(Table1[[#This Row],[Location Name]],'Risk Profiles'!$A$18:$A$37,'Risk Profiles'!$C$18:$C$37) -> High FOB% (6.12%), Stat Var (2.73%), Waste (1.40%) | W21: =_xlfn.XLOOKUP(Table1[[#This Row],[Location Name]],'Risk Profiles'!$A$18:$A$37,'Risk Profiles'!$D$18:$D$37) -> HIgh | X21: =_xlfn.XLOOKUP(Table1[[#This Row],[Location Name]],'Risk Profiles'!$A$18:$A$37,'Risk Profiles'!$E$18:$E$37) -> T-Red After (0.42%), Cash O/S (0.05%) | Y21: Lynsey | Z21: Yes | AA21: =_xlfn.XLOOKUP(A21,Table3[Location],Table3[Date Scheduled]) -> 46092 | AB21: Monday | AC21: Thursday | AE21: 46129 | AF21: Kevonte | AG21: 46246 | AH21: Yes | AI21: Yes | AJ21: Yes | AK21: =IFERROR(INDEX('Scheduling Setup'!$L:$L,MATCH($A21,'Scheduling Setup'!$A:$A,0)),"") -> 46253 | BA21: 33109 | BB21: =_xlfn.XLOOKUP($BA21,$A$3:$A$32,$F$3:$F$32) -> Ashley Podroza | BC21: =_xlfn.XLOOKUP($BA21,$A$3:$A$32,$I$3:$I$32) -> Rey Araiz | BD21: =IF(_xlfn.XLOOKUP($BA21,$A$3:$A$32,$Y$3:$Y$32)="","",_xlfn.XLOOKUP($BA21,$A$3:$A$32,$Y$3:$Y$32)) -> Gisselle | BE21: 4-6 Hours | BF21: 46170 | BG21: 0.33333333 | BH21: =_xlfn.XLOOKUP(Table3[[#This Row],[Location]],Table4[STORE '#],Table4[DATE RGR]) -> 46295 | BI21: =_xlfn.XLOOKUP(Table3[[#This Row],[Location]],Table1[Location Name],Table1[Weekly Inventory Count Day]) -> Tuesday | BJ21: =_xlfn.XLOOKUP(Table3[[#This Row],[Location]],Table1[Location Name],Table1[FOB Risk Profile]) -> Low | BK21: Earliest available date | BL21: Changed from 05/21/26 | BM21: 46129
A22: 43380 | B22: Ryan Thorley | C22: rick@mcdok.com | D22: kathy@mcdok.com | E22: MCDOK | F22: Ashley Podroza | H22: =LEFT(Table1[[#This Row],[Supervisor]], SEARCH(" ", Table1[[#This Row],[Supervisor]]) - 1) & "@" & Table1[[#This Row],[Email Domain]] -> Ashley@mcdok.com | I22: Zukarr Eaves | J22: =LEFT(Table1[[#This Row],[GM]], SEARCH(" ", Table1[[#This Row],[GM]]) - 1) & "@" & Table1[[#This Row],[Email Domain]] -> Zukarr@mcdok.com | K22: mcdok.com | L22: 249 | M22: ="mcdok.mdp+"&Table1[[#This Row],[Location Name]]&"@gmail.com" -> mcdok.mdp+43380@gmail.com | N22: ="Mcdok.mdp"&Table1[[#This Row],[Location Name]] -> Mcdok.mdp43380 | O22: 43380 - MAIN AND REFUGE-TISHOMINGO, OK | P22: 1309 E Main St, Tishomingo, OK, 73460, USA | Q22: Yes | R22: No | T22: Saturday | U22: =_xlfn.XLOOKUP(Table1[[#This Row],[Location Name]],'Risk Profiles'!$A$18:$A$37,'Risk Profiles'!$B$18:$B$37) -> Medium | V22: =_xlfn.XLOOKUP(Table1[[#This Row],[Location Name]],'Risk Profiles'!$A$18:$A$37,'Risk Profiles'!$C$18:$C$37) -> Within Normal range | W22: =_xlfn.XLOOKUP(Table1[[#This Row],[Location Name]],'Risk Profiles'!$A$18:$A$37,'Risk Profiles'!$D$18:$D$37) -> Medium | X22: =_xlfn.XLOOKUP(Table1[[#This Row],[Location Name]],'Risk Profiles'!$A$18:$A$37,'Risk Profiles'!$E$18:$E$37) -> T-Red After (0.38%), Cash O/S (0.05%), Overrings (0.38%) | Y22: Zukaar | Z22: Yes | AA22: =_xlfn.XLOOKUP(A22,Table3[Location],Table3[Date Scheduled]) -> 46088 | AB22: Tuesday | AC22: Friday | AE22: 46129 | AF22: Sabrina Turner | AG22: 46240 | AH22: Yes | AI22: Yes | AJ22: Yes | AK22: =IFERROR(INDEX('Scheduling Setup'!$L:$L,MATCH($A22,'Scheduling Setup'!$A:$A,0)),"") -> 46246 | BA22: 18213 | BB22: =_xlfn.XLOOKUP($BA22,$A$3:$A$32,$F$3:$F$32) -> Krystiana Langford | BC22: =_xlfn.XLOOKUP($BA22,$A$3:$A$32,$I$3:$I$32) -> Cora Bahling | BD22: =IF(_xlfn.XLOOKUP($BA22,$A$3:$A$32,$Y$3:$Y$32)="","",_xlfn.XLOOKUP($BA22,$A$3:$A$32,$Y$3:$Y$32)) -> Crystal | BE22: 4-6 Hours | BF22: 46177 | BG22: 0.33333333 | BH22: =_xlfn.XLOOKUP(Table3[[#This Row],[Location]],Table4[STORE '#],Table4[DATE RGR]) -> 46338 | BI22: =_xlfn.XLOOKUP(Table3[[#This Row],[Location]],Table1[Location Name],Table1[Weekly Inventory Count Day]) -> Thursday | BJ22: =_xlfn.XLOOKUP(Table3[[#This Row],[Location]],Table1[Location Name],Table1[FOB Risk Profile]) -> Medium | BK22: Earliest available date | BL22: Changed from 05/07/26 | BM22: 46129
A23: 6178 | B23: Jacob Thorley | C23: =LEFT(Table1[[#This Row],[Owner/Operator]], SEARCH(" ", Table1[[#This Row],[Owner/Operator]]) - 1) & "@" & Table1[[#This Row],[Email Domain]] -> Jacob@emeraldarches.com | E23: Emerald Arches | F23: Mary Ratliff | G23: 46225 | H23: =LEFT(Table1[[#This Row],[Supervisor]], SEARCH(" ", Table1[[#This Row],[Supervisor]]) - 1) & "@" & Table1[[#This Row],[Email Domain]] -> Mary@emeraldarches.com | I23: Janet Jeter | J23: =LEFT(Table1[[#This Row],[GM]], SEARCH(" ", Table1[[#This Row],[GM]]) - 1) & "@" & Table1[[#This Row],[Email Domain]] -> Janet@emeraldarches.com | K23: emeraldarches.com | L23: 472 | M23: ="mcdok.mdp+"&Table1[[#This Row],[Location Name]]&"@gmail.com" -> mcdok.mdp+6178@gmail.com | N23: ="Mcdok.mdp"&Table1[[#This Row],[Location Name]] -> Mcdok.mdp6178 | O23: 6178 - CHIPLEY-ST.RD.77 | P23: 1291 Main St, Chipley, FL, 32428, USA | U23: =_xlfn.XLOOKUP(Table1[[#This Row],[Location Name]],'Risk Profiles'!$A$18:$A$37,'Risk Profiles'!$B$18:$B$37) -> #N/A | V23: =_xlfn.XLOOKUP(Table1[[#This Row],[Location Name]],'Risk Profiles'!$A$18:$A$37,'Risk Profiles'!$C$18:$C$37) -> #N/A | W23: =_xlfn.XLOOKUP(Table1[[#This Row],[Location Name]],'Risk Profiles'!$A$18:$A$37,'Risk Profiles'!$D$18:$D$37) -> #N/A | X23: =_xlfn.XLOOKUP(Table1[[#This Row],[Location Name]],'Risk Profiles'!$A$18:$A$37,'Risk Profiles'!$E$18:$E$37) -> #N/A | AA23: =_xlfn.XLOOKUP(A23,Table3[Location],Table3[Date Scheduled]) -> #N/A | AK23: =IFERROR(INDEX('Scheduling Setup'!$L:$L,MATCH($A23,'Scheduling Setup'!$A:$A,0)),"")
A24: 6838 | B24: Jacob Thorley | C24: =LEFT(Table1[[#This Row],[Owner/Operator]], SEARCH(" ", Table1[[#This Row],[Owner/Operator]]) - 1) & "@" & Table1[[#This Row],[Email Domain]] -> Jacob@emeraldarches.com | E24: Emerald Arches | F24: Mary Ratliff | G24: 46225 | H24: =LEFT(Table1[[#This Row],[Supervisor]], SEARCH(" ", Table1[[#This Row],[Supervisor]]) - 1) & "@" & Table1[[#This Row],[Email Domain]] -> Mary@emeraldarches.com | I24: Stephanie Harris | J24: =LEFT(Table1[[#This Row],[GM]], SEARCH(" ", Table1[[#This Row],[GM]]) - 1) & "@" & Table1[[#This Row],[Email Domain]] -> Stephanie@emeraldarches.com | K24: emeraldarches.com | L24: 490 | M24: ="mcdok.mdp+"&Table1[[#This Row],[Location Name]]&"@gmail.com" -> mcdok.mdp+6838@gmail.com | N24: ="Mcdok.mdp"&Table1[[#This Row],[Location Name]] -> Mcdok.mdp6838 | O24: 6838 - DEFUNIAK SPRINGS | P24: 2370 US Highway 331 S, Defuniak Springs, FL, 32435, USA | U24: =_xlfn.XLOOKUP(Table1[[#This Row],[Location Name]],'Risk Profiles'!$A$18:$A$37,'Risk Profiles'!$B$18:$B$37) -> #N/A | V24: =_xlfn.XLOOKUP(Table1[[#This Row],[Location Name]],'Risk Profiles'!$A$18:$A$37,'Risk Profiles'!$C$18:$C$37) -> #N/A | W24: =_xlfn.XLOOKUP(Table1[[#This Row],[Location Name]],'Risk Profiles'!$A$18:$A$37,'Risk Profiles'!$D$18:$D$37) -> #N/A | X24: =_xlfn.XLOOKUP(Table1[[#This Row],[Location Name]],'Risk Profiles'!$A$18:$A$37,'Risk Profiles'!$E$18:$E$37) -> #N/A | AA24: =_xlfn.XLOOKUP(A24,Table3[Location],Table3[Date Scheduled]) -> #N/A | AK24: =IFERROR(INDEX('Scheduling Setup'!$L:$L,MATCH($A24,'Scheduling Setup'!$A:$A,0)),"")
A25: 10034 | B25: Ryan Thorley | C25: =LEFT(Table1[[#This Row],[Owner/Operator]], SEARCH(" ", Table1[[#This Row],[Owner/Operator]]) - 1) & "@" & Table1[[#This Row],[Email Domain]] -> Ryan@emeraldarches.com | E25: Emerald Arches | F25: Mary Ratliff | G25: 46225 | H25: =LEFT(Table1[[#This Row],[Supervisor]], SEARCH(" ", Table1[[#This Row],[Supervisor]]) - 1) & "@" & Table1[[#This Row],[Email Domain]] -> Mary@emeraldarches.com | I25: Harlee Yates | J25: =LEFT(Table1[[#This Row],[GM]], SEARCH(" ", Table1[[#This Row],[GM]]) - 1) & "@" & Table1[[#This Row],[Email Domain]] -> Harlee@emeraldarches.com | K25: emeraldarches.com | L25: 483 | M25: ="mcdok.mdp+"&Table1[[#This Row],[Location Name]]&"@gmail.com" -> mcdok.mdp+10034@gmail.com | N25: ="Mcdok.mdp"&Table1[[#This Row],[Location Name]] -> Mcdok.mdp10034 | O25: 10034 - BONIFAY | P25: 2010 S Waukesha St, Bonifay, FL, 32425, USA | U25: =_xlfn.XLOOKUP(Table1[[#This Row],[Location Name]],'Risk Profiles'!$A$18:$A$37,'Risk Profiles'!$B$18:$B$37) -> #N/A | V25: =_xlfn.XLOOKUP(Table1[[#This Row],[Location Name]],'Risk Profiles'!$A$18:$A$37,'Risk Profiles'!$C$18:$C$37) -> #N/A | W25: =_xlfn.XLOOKUP(Table1[[#This Row],[Location Name]],'Risk Profiles'!$A$18:$A$37,'Risk Profiles'!$D$18:$D$37) -> #N/A | X25: =_xlfn.XLOOKUP(Table1[[#This Row],[Location Name]],'Risk Profiles'!$A$18:$A$37,'Risk Profiles'!$E$18:$E$37) -> #N/A | AA25: =_xlfn.XLOOKUP(A25,Table3[Location],Table3[Date Scheduled]) -> #N/A | AK25: =IFERROR(INDEX('Scheduling Setup'!$L:$L,MATCH($A25,'Scheduling Setup'!$A:$A,0)),"")
A26: 35242 | B26: Jacob Thorley | C26: =LEFT(Table1[[#This Row],[Owner/Operator]], SEARCH(" ", Table1[[#This Row],[Owner/Operator]]) - 1) & "@" & Table1[[#This Row],[Email Domain]] -> Jacob@emeraldarches.com | E26: Emerald Arches | F26: Brad Denley | H26: =LEFT(Table1[[#This Row],[Supervisor]], SEARCH(" ", Table1[[#This Row],[Supervisor]]) - 1) & "@" & Table1[[#This Row],[Email Domain]] -> Brad@emeraldarches.com | I26: Michele Nixon | J26: =LEFT(Table1[[#This Row],[GM]], SEARCH(" ", Table1[[#This Row],[GM]]) - 1) & "@" & Table1[[#This Row],[Email Domain]] -> Michele@emeraldarches.com | K26: emeraldarches.com | L26: 469 | M26: ="mcdok.mdp+"&Table1[[#This Row],[Location Name]]&"@gmail.com" -> mcdok.mdp+35242@gmail.com | N26: ="Mcdok.mdp"&Table1[[#This Row],[Location Name]] -> Mcdok.mdp35242 | O26: 35242 - COTTONDALE | P26: 2510 Highway 231, Cottondale, FL, 32431, USA | U26: =_xlfn.XLOOKUP(Table1[[#This Row],[Location Name]],'Risk Profiles'!$A$18:$A$37,'Risk Profiles'!$B$18:$B$37) -> #N/A | V26: =_xlfn.XLOOKUP(Table1[[#This Row],[Location Name]],'Risk Profiles'!$A$18:$A$37,'Risk Profiles'!$C$18:$C$37) -> #N/A | W26: =_xlfn.XLOOKUP(Table1[[#This Row],[Location Name]],'Risk Profiles'!$A$18:$A$37,'Risk Profiles'!$D$18:$D$37) -> #N/A | X26: =_xlfn.XLOOKUP(Table1[[#This Row],[Location Name]],'Risk Profiles'!$A$18:$A$37,'Risk Profiles'!$E$18:$E$37) -> #N/A | AA26: =_xlfn.XLOOKUP(A26,Table3[Location],Table3[Date Scheduled]) -> #N/A | AK26: =IFERROR(INDEX('Scheduling Setup'!$L:$L,MATCH($A26,'Scheduling Setup'!$A:$A,0)),"")
A27: 37566 | B27: Ryan Thorley | C27: =LEFT(Table1[[#This Row],[Owner/Operator]], SEARCH(" ", Table1[[#This Row],[Owner/Operator]]) - 1) & "@" & Table1[[#This Row],[Email Domain]] -> Ryan@emeraldarches.com | E27: Emerald Arches | F27: Mary Ratliff | G27: 46225 | H27: =LEFT(Table1[[#This Row],[Supervisor]], SEARCH(" ", Table1[[#This Row],[Supervisor]]) - 1) & "@" & Table1[[#This Row],[Email Domain]] -> Mary@emeraldarches.com | I27: Debra Herndon | J27: =LEFT(Table1[[#This Row],[GM]], SEARCH(" ", Table1[[#This Row],[GM]]) - 1) & "@" & Table1[[#This Row],[Email Domain]] -> Debra@emeraldarches.com | K27: emeraldarches.com | L27: 484 | M27: ="mcdok.mdp+"&Table1[[#This Row],[Location Name]]&"@gmail.com" -> mcdok.mdp+37566@gmail.com | N27: ="Mcdok.mdp"&Table1[[#This Row],[Location Name]] -> Mcdok.mdp37566 | O27: 37566 - MOSSY HEAD | P27: 17750 State Highway 285 Dr S, Defuniak Springs, FL, 32435, USA | U27: =_xlfn.XLOOKUP(Table1[[#This Row],[Location Name]],'Risk Profiles'!$A$18:$A$37,'Risk Profiles'!$B$18:$B$37) -> #N/A | V27: =_xlfn.XLOOKUP(Table1[[#This Row],[Location Name]],'Risk Profiles'!$A$18:$A$37,'Risk Profiles'!$C$18:$C$37) -> #N/A | W27: =_xlfn.XLOOKUP(Table1[[#This Row],[Location Name]],'Risk Profiles'!$A$18:$A$37,'Risk Profiles'!$D$18:$D$37) -> #N/A | X27: =_xlfn.XLOOKUP(Table1[[#This Row],[Location Name]],'Risk Profiles'!$A$18:$A$37,'Risk Profiles'!$E$18:$E$37) -> #N/A | AA27: =_xlfn.XLOOKUP(A27,Table3[Location],Table3[Date Scheduled]) -> #N/A | AK27: =IFERROR(INDEX('Scheduling Setup'!$L:$L,MATCH($A27,'Scheduling Setup'!$A:$A,0)),"")
A28: 38609 | B28: Jacob Thorley | C28: =LEFT(Table1[[#This Row],[Owner/Operator]], SEARCH(" ", Table1[[#This Row],[Owner/Operator]]) - 1) & "@" & Table1[[#This Row],[Email Domain]] -> Jacob@emeraldarches.com | E28: Emerald Arches | F28: Brad Denley | H28: =LEFT(Table1[[#This Row],[Supervisor]], SEARCH(" ", Table1[[#This Row],[Supervisor]]) - 1) & "@" & Table1[[#This Row],[Email Domain]] -> Brad@emeraldarches.com | I28: Christina Bencokzy | J28: =LEFT(Table1[[#This Row],[GM]], SEARCH(" ", Table1[[#This Row],[GM]]) - 1) & "@" & Table1[[#This Row],[Email Domain]] -> Christina@emeraldarches.com | K28: emeraldarches.com | L28: 467 | M28: ="mcdok.mdp+"&Table1[[#This Row],[Location Name]]&"@gmail.com" -> mcdok.mdp+38609@gmail.com | N28: ="Mcdok.mdp"&Table1[[#This Row],[Location Name]] -> Mcdok.mdp38609 | O28: 38609 - FREEPORT | P28: 16392 US Highway 331 S, Freeport, FL, 32439, USA | U28: =_xlfn.XLOOKUP(Table1[[#This Row],[Location Name]],'Risk Profiles'!$A$18:$A$37,'Risk Profiles'!$B$18:$B$37) -> #N/A | V28: =_xlfn.XLOOKUP(Table1[[#This Row],[Location Name]],'Risk Profiles'!$A$18:$A$37,'Risk Profiles'!$C$18:$C$37) -> #N/A | W28: =_xlfn.XLOOKUP(Table1[[#This Row],[Location Name]],'Risk Profiles'!$A$18:$A$37,'Risk Profiles'!$D$18:$D$37) -> #N/A | X28: =_xlfn.XLOOKUP(Table1[[#This Row],[Location Name]],'Risk Profiles'!$A$18:$A$37,'Risk Profiles'!$E$18:$E$37) -> #N/A | AA28: =_xlfn.XLOOKUP(A28,Table3[Location],Table3[Date Scheduled]) -> #N/A | AK28: =IFERROR(INDEX('Scheduling Setup'!$L:$L,MATCH($A28,'Scheduling Setup'!$A:$A,0)),"")
A29: 43701 | B29: Ryan Thorley | C29: =LEFT(Table1[[#This Row],[Owner/Operator]], SEARCH(" ", Table1[[#This Row],[Owner/Operator]]) - 1) & "@" & Table1[[#This Row],[Email Domain]] -> Ryan@emeraldarches.com | E29: Emerald Arches | F29: Brad Denley | H29: =LEFT(Table1[[#This Row],[Supervisor]], SEARCH(" ", Table1[[#This Row],[Supervisor]]) - 1) & "@" & Table1[[#This Row],[Email Domain]] -> Brad@emeraldarches.com | I29: Shannon Hardin | J29: =LEFT(Table1[[#This Row],[GM]], SEARCH(" ", Table1[[#This Row],[GM]]) - 1) & "@" & Table1[[#This Row],[Email Domain]] -> Shannon@emeraldarches.com | K29: emeraldarches.com | L29: 1523 | M29: ="mcdok.mdp+"&Table1[[#This Row],[Location Name]]&"@gmail.com" -> mcdok.mdp+43701@gmail.com | N29: ="Mcdok.mdp"&Table1[[#This Row],[Location Name]] -> Mcdok.mdp43701 | O29: 43701 - HWY 81 AND I-10-PONCE DE LEON, FL | P29: 2920 FL-81, Ponce de Leon, FL, 32455, USA | U29: =_xlfn.XLOOKUP(Table1[[#This Row],[Location Name]],'Risk Profiles'!$A$18:$A$37,'Risk Profiles'!$B$18:$B$37) -> #N/A | V29: =_xlfn.XLOOKUP(Table1[[#This Row],[Location Name]],'Risk Profiles'!$A$18:$A$37,'Risk Profiles'!$C$18:$C$37) -> #N/A | W29: =_xlfn.XLOOKUP(Table1[[#This Row],[Location Name]],'Risk Profiles'!$A$18:$A$37,'Risk Profiles'!$D$18:$D$37) -> #N/A | X29: =_xlfn.XLOOKUP(Table1[[#This Row],[Location Name]],'Risk Profiles'!$A$18:$A$37,'Risk Profiles'!$E$18:$E$37) -> #N/A | AA29: =_xlfn.XLOOKUP(A29,Table3[Location],Table3[Date Scheduled]) -> #N/A | AK29: =IFERROR(INDEX('Scheduling Setup'!$L:$L,MATCH($A29,'Scheduling Setup'!$A:$A,0)),"")
A30: Above Store | B30: Molly Mcgill | C30: =LEFT(Table1[[#This Row],[Owner/Operator]], SEARCH(" ", Table1[[#This Row],[Owner/Operator]]) - 1) & "@" & Table1[[#This Row],[Email Domain]] -> Molly@mcdok.com | E30: MCDOK | K30: mcdok.com | U30: =_xlfn.XLOOKUP(Table1[[#This Row],[Location Name]],'Risk Profiles'!$A$18:$A$37,'Risk Profiles'!$B$18:$B$37) -> #N/A | V30: =_xlfn.XLOOKUP(Table1[[#This Row],[Location Name]],'Risk Profiles'!$A$18:$A$37,'Risk Profiles'!$C$18:$C$37) -> #N/A | W30: =_xlfn.XLOOKUP(Table1[[#This Row],[Location Name]],'Risk Profiles'!$A$18:$A$37,'Risk Profiles'!$D$18:$D$37) -> #N/A | X30: =_xlfn.XLOOKUP(Table1[[#This Row],[Location Name]],'Risk Profiles'!$A$18:$A$37,'Risk Profiles'!$E$18:$E$37) -> #N/A | AA30: =_xlfn.XLOOKUP(A30,Table3[Location],Table3[Date Scheduled]) -> #N/A | AK30: =IFERROR(INDEX('Scheduling Setup'!$L:$L,MATCH($A30,'Scheduling Setup'!$A:$A,0)),"")
A31: Above Store | B31: Hugh Bonner | C31: =LEFT(Table1[[#This Row],[Owner/Operator]], SEARCH(" ", Table1[[#This Row],[Owner/Operator]]) - 1) & "@" & Table1[[#This Row],[Email Domain]] -> Hugh@mcdok.com | E31: MCDOK | K31: mcdok.com | U31: =_xlfn.XLOOKUP(Table1[[#This Row],[Location Name]],'Risk Profiles'!$A$18:$A$37,'Risk Profiles'!$B$18:$B$37) -> #N/A | V31: =_xlfn.XLOOKUP(Table1[[#This Row],[Location Name]],'Risk Profiles'!$A$18:$A$37,'Risk Profiles'!$C$18:$C$37) -> #N/A | W31: =_xlfn.XLOOKUP(Table1[[#This Row],[Location Name]],'Risk Profiles'!$A$18:$A$37,'Risk Profiles'!$D$18:$D$37) -> #N/A | X31: =_xlfn.XLOOKUP(Table1[[#This Row],[Location Name]],'Risk Profiles'!$A$18:$A$37,'Risk Profiles'!$E$18:$E$37) -> #N/A | AA31: =_xlfn.XLOOKUP(A31,Table3[Location],Table3[Date Scheduled]) -> #N/A | AK31: =IFERROR(INDEX('Scheduling Setup'!$L:$L,MATCH($A31,'Scheduling Setup'!$A:$A,0)),"")
A32: Above Store | B32: Fletcher Reaves | C32: =LEFT(Table1[[#This Row],[Owner/Operator]], SEARCH(" ", Table1[[#This Row],[Owner/Operator]]) - 1) & "@" & Table1[[#This Row],[Email Domain]] -> Fletcher@mcdok.com | E32: MCDOK | K32: mcdok.com | U32: =_xlfn.XLOOKUP(Table1[[#This Row],[Location Name]],'Risk Profiles'!$A$18:$A$37,'Risk Profiles'!$B$18:$B$37) -> #N/A | V32: =_xlfn.XLOOKUP(Table1[[#This Row],[Location Name]],'Risk Profiles'!$A$18:$A$37,'Risk Profiles'!$C$18:$C$37) -> #N/A | W32: =_xlfn.XLOOKUP(Table1[[#This Row],[Location Name]],'Risk Profiles'!$A$18:$A$37,'Risk Profiles'!$D$18:$D$37) -> #N/A | X32: =_xlfn.XLOOKUP(Table1[[#This Row],[Location Name]],'Risk Profiles'!$A$18:$A$37,'Risk Profiles'!$E$18:$E$37) -> #N/A | AA32: =_xlfn.XLOOKUP(A32,Table3[Location],Table3[Date Scheduled]) -> #N/A | AK32: =IFERROR(INDEX('Scheduling Setup'!$L:$L,MATCH($A32,'Scheduling Setup'!$A:$A,0)),"")
A34: =_xlfn.TEXTJOIN(",", TRUE, A3:A29) -> 3708,5183,5985,6972,10422,10915,11657,13113,18213,20475,24471,29760,31357,32525,33109,33222,33704,34222,35064,43380,6178,6838,10034,35242,37566,38609,43701 | AK34: =IFERROR(INDEX('Scheduling Setup'!$L:$L,MATCH($A34,'Scheduling Setup'!$A:$A,0)),"")
C35: angelo@mcdok.com
A37: 3.7085184e+128
A38: 6178 | F38: Janet | H38: Jeter | I38: Primary | J38: 641 | L38: GENERAL MANAGER | AK38: =IFERROR(INDEX('Scheduling Setup'!$L:$L,MATCH($A38,'Scheduling Setup'!$A:$A,0)),"")
A39: 6178 | F39: Brad | H39: Denley | I39: Primary | J39: 641 | L39: GENERAL MANAGER | AK39: =IFERROR(INDEX('Scheduling Setup'!$L:$L,MATCH($A39,'Scheduling Setup'!$A:$A,0)),"")
A40: 6178 | F40: Jennifer | H40: Denley | I40: Primary | J40: 641 | L40: GENERAL MANAGER | AK40: =IFERROR(INDEX('Scheduling Setup'!$L:$L,MATCH($A40,'Scheduling Setup'!$A:$A,0)),"")
A41: 6838 | F41: Mary | H41: Ratliff | I41: Primary | J41: 641 | L41: GENERAL MANAGER | AK41: =IFERROR(INDEX('Scheduling Setup'!$L:$L,MATCH($A41,'Scheduling Setup'!$A:$A,0)),"")
A42: 6838 | F42: Stephanie | H42: Harris | I42: Primary | J42: 641 | L42: GENERAL MANAGER | AK42: =IFERROR(INDEX('Scheduling Setup'!$L:$L,MATCH($A42,'Scheduling Setup'!$A:$A,0)),"")
A43: 10034 | F43: Harlee | H43: Yates | I43: Primary | J43: 641 | L43: GENERAL MANAGER | AK43: =IFERROR(INDEX('Scheduling Setup'!$L:$L,MATCH($A43,'Scheduling Setup'!$A:$A,0)),"")
A44: 35242 | F44: Michele | H44: Nixon | I44: Primary | J44: 641 | L44: GENERAL MANAGER | AK44: =IFERROR(INDEX('Scheduling Setup'!$L:$L,MATCH($A44,'Scheduling Setup'!$A:$A,0)),"")
A45: 37566 | F45: Debra | H45: Herndon | I45: Primary | J45: 641 | L45: GENERAL MANAGER | AK45: =IFERROR(INDEX('Scheduling Setup'!$L:$L,MATCH($A45,'Scheduling Setup'!$A:$A,0)),"")
A46: 38609 | F46: Christina | H46: Benkoczy | I46: Primary | J46: 641 | L46: GENERAL MANAGER | AK46: =IFERROR(INDEX('Scheduling Setup'!$L:$L,MATCH($A46,'Scheduling Setup'!$A:$A,0)),"")
A47: 38609 | F47: Russell | H47: Benkoczy | I47: Primary | J47: 641 | L47: GENERAL MANAGER | AK47: =IFERROR(INDEX('Scheduling Setup'!$L:$L,MATCH($A47,'Scheduling Setup'!$A:$A,0)),"")
A48: 43701 | F48: Shannon | H48: Hardin | I48: Primary | J48: 641 | L48: GENERAL MANAGER | AK48: =IFERROR(INDEX('Scheduling Setup'!$L:$L,MATCH($A48,'Scheduling Setup'!$A:$A,0)),"")
A49: 43701 | F49: Nia | H49: Battles | I49: Primary | J49: 641 | L49: GENERAL MANAGER | AK49: =IFERROR(INDEX('Scheduling Setup'!$L:$L,MATCH($A49,'Scheduling Setup'!$A:$A,0)),"")

Sheet FC-Inv Setup
A1: =TODAY() -> 46266
A2: Location | B2: LocationName | C2: Supervisor | D2: GM | E2: Counting Manager | F2: Time Needed | G2: Date Scheduled | H2: Start Time | I2: RGR Date | J2: Count Day | K2: FOB Risk | L2: Validity | M2: Status
A3: 10422 | B3: ATOKA, OK | C3: =_xlfn.XLOOKUP($A3,Table1[Location Name],Table1[Supervisor]) -> Ashley Podroza | D3: =_xlfn.XLOOKUP($A3,Table1[Location Name],Table1[GM]) -> Ashleyh Hegwer | E3: =IF(_xlfn.XLOOKUP($A3,Table1[Location Name],Table1[Primary Counting Manager])="","",_xlfn.XLOOKUP($A3,Table1[Location Name],Table1[Primary Counting Manager])) -> Ashley | G3: 46095 | I3: =_xlfn.XLOOKUP(Table39[[#This Row],[Location]],Table4[STORE '#],Table4[DATE RGR]) -> 46051 | J3: =_xlfn.XLOOKUP(Table39[[#This Row],[Location]],Table1[Location Name],Table1[Weekly Inventory Count Day]) -> Saturday | K3: =_xlfn.XLOOKUP(Table39[[#This Row],[Location]],Table1[Location Name],Table1[FOB Risk Profile]) -> High | M3: Completed
A4: 6972 | B4: ADA | C4: =_xlfn.XLOOKUP($A4,Table1[Location Name],Table1[Supervisor]) -> Robert Spencer | D4: =_xlfn.XLOOKUP($A4,Table1[Location Name],Table1[GM]) -> Nick Rice | E4: =IF(_xlfn.XLOOKUP($A4,Table1[Location Name],Table1[Primary Counting Manager])="","",_xlfn.XLOOKUP($A4,Table1[Location Name],Table1[Primary Counting Manager])) -> Beth | G4: 46065 | I4: =_xlfn.XLOOKUP(Table39[[#This Row],[Location]],Table4[STORE '#],Table4[DATE RGR]) -> 46063 | J4: =_xlfn.XLOOKUP(Table39[[#This Row],[Location]],Table1[Location Name],Table1[Weekly Inventory Count Day]) -> Thursday | K4: =_xlfn.XLOOKUP(Table39[[#This Row],[Location]],Table1[Location Name],Table1[FOB Risk Profile]) -> Medium | M4: Completed
A5: 10915 | B5: SEMINOLE, OK | C5: =_xlfn.XLOOKUP($A5,Table1[Location Name],Table1[Supervisor]) -> Steven Vaughn | D5: =_xlfn.XLOOKUP($A5,Table1[Location Name],Table1[GM]) -> Caleb Nunnelley | E5: =IF(_xlfn.XLOOKUP($A5,Table1[Location Name],Table1[Primary Counting Manager])="","",_xlfn.XLOOKUP($A5,Table1[Location Name],Table1[Primary Counting Manager])) -> Caitlin | F5: 4-6 Hours | G5: 46148 | H5: 0.33333333 | I5: =_xlfn.XLOOKUP(Table39[[#This Row],[Location]],Table4[STORE '#],Table4[DATE RGR]) -> 46071 | J5: =_xlfn.XLOOKUP(Table39[[#This Row],[Location]],Table1[Location Name],Table1[Weekly Inventory Count Day]) -> Wednesday | K5: =_xlfn.XLOOKUP(Table39[[#This Row],[Location]],Table1[Location Name],Table1[FOB Risk Profile]) -> Medium | L5: Earliest available date | M5: Unchanged
A6: 5985 | B6: DURANT | C6: =_xlfn.XLOOKUP($A6,Table1[Location Name],Table1[Supervisor]) -> Ashley Podroza | D6: =_xlfn.XLOOKUP($A6,Table1[Location Name],Table1[GM]) -> Stacey Hyatt | E6: =IF(_xlfn.XLOOKUP($A6,Table1[Location Name],Table1[Primary Counting Manager])="","",_xlfn.XLOOKUP($A6,Table1[Location Name],Table1[Primary Counting Manager])) -> Scauti/Chas | F6: 4-6 Hours | G6: 46119 | H6: 0.33333333 | I6: =_xlfn.XLOOKUP(Table39[[#This Row],[Location]],Table4[STORE '#],Table4[DATE RGR]) -> 46092 | J6: =_xlfn.XLOOKUP(Table39[[#This Row],[Location]],Table1[Location Name],Table1[Weekly Inventory Count Day]) -> Tuesday | K6: =_xlfn.XLOOKUP(Table39[[#This Row],[Location]],Table1[Location Name],Table1[FOB Risk Profile]) -> Low | L6: Earliest available date | M6: Unchanged
A7: 20475 | B7: OKC | C7: =_xlfn.XLOOKUP($A7,Table1[Location Name],Table1[Supervisor]) -> Amanda Estrada | D7: =_xlfn.XLOOKUP($A7,Table1[Location Name],Table1[GM]) -> Derek McGirt | E7: Susanna | F7: 4-6 Hours | G7: 46121 | H7: 0.33333333 | I7: =_xlfn.XLOOKUP(Table39[[#This Row],[Location]],Table4[STORE '#],Table4[DATE RGR]) -> 46107 | J7: =_xlfn.XLOOKUP(Table39[[#This Row],[Location]],Table1[Location Name],Table1[Weekly Inventory Count Day]) -> Thursday | K7: =_xlfn.XLOOKUP(Table39[[#This Row],[Location]],Table1[Location Name],Table1[FOB Risk Profile]) -> Low | L7: Earliest available date | M7: Unchanged
A8: 33704 | B8: TECUMSEH, OK | C8: =_xlfn.XLOOKUP($A8,Table1[Location Name],Table1[Supervisor]) -> Steven Vaughn | D8: =_xlfn.XLOOKUP($A8,Table1[Location Name],Table1[GM]) -> Candy Barksdale | E8: =IF(_xlfn.XLOOKUP($A8,Table1[Location Name],Table1[Primary Counting Manager])="","",_xlfn.XLOOKUP($A8,Table1[Location Name],Table1[Primary Counting Manager])) -> Marlena | F8: 4-6 Hours | G8: 46157 | H8: 0.33333333 | I8: =_xlfn.XLOOKUP(Table39[[#This Row],[Location]],Table4[STORE '#],Table4[DATE RGR]) -> 46127 | J8: =_xlfn.XLOOKUP(Table39[[#This Row],[Location]],Table1[Location Name],Table1[Weekly Inventory Count Day]) -> Friday | K8: =_xlfn.XLOOKUP(Table39[[#This Row],[Location]],Table1[Location Name],Table1[FOB Risk Profile]) -> Medium | L8: Earliest available date | M8: Unchanged
A9: 11657 | B9: PURCELL | C9: =_xlfn.XLOOKUP($A9,Table1[Location Name],Table1[Supervisor]) -> Amanda Estrada | D9: =_xlfn.XLOOKUP($A9,Table1[Location Name],Table1[GM]) -> Jessie Hiatt | E9: =IF(_xlfn.XLOOKUP($A9,Table1[Location Name],Table1[Primary Counting Manager])="","",_xlfn.XLOOKUP($A9,Table1[Location Name],Table1[Primary Counting Manager])) -> Norma | F9: 4-6 Hours | G9: 46149 | H9: 0.33333333 | I9: =_xlfn.XLOOKUP(Table39[[#This Row],[Location]],Table4[STORE '#],Table4[DATE RGR]) -> 46134 | J9: =_xlfn.XLOOKUP(Table39[[#This Row],[Location]],Table1[Location Name],Table1[Weekly Inventory Count Day]) -> Thursday | K9: =_xlfn.XLOOKUP(Table39[[#This Row],[Location]],Table1[Location Name],Table1[FOB Risk Profile]) -> Medium | L9: Earliest available date | M9: Changed from 06/04/26
A10: 34222 | B10: HARRAH, OK | C10: =_xlfn.XLOOKUP($A10,Table1[Location Name],Table1[Supervisor]) -> Steven Vaughn | D10: =_xlfn.XLOOKUP($A10,Table1[Location Name],Table1[GM]) -> Hunter McKee | E10: =IF(_xlfn.XLOOKUP($A10,Table1[Location Name],Table1[Primary Counting Manager])="","",_xlfn.XLOOKUP($A10,Table1[Location Name],Table1[Primary Counting Manager])) -> Kaylee | F10: 4-6 Hours | G10: 46160 | H10: 0.375 | I10: =_xlfn.XLOOKUP(Table39[[#This Row],[Location]],Table4[STORE '#],Table4[DATE RGR]) -> 46155 | J10: =_xlfn.XLOOKUP(Table39[[#This Row],[Location]],Table1[Location Name],Table1[Weekly Inventory Count Day]) -> Monday | K10: =_xlfn.XLOOKUP(Table39[[#This Row],[Location]],Table1[Location Name],Table1[FOB Risk Profile]) -> Low | L10: Earliest available date | M10: Changed from 05/20/26
A11: 33222 | B11: ELGIN, OK | C11: =_xlfn.XLOOKUP($A11,Table1[Location Name],Table1[Supervisor]) -> Krystiana Langford | D11: =_xlfn.XLOOKUP($A11,Table1[Location Name],Table1[GM]) -> Carol Escusa | E11: =IF(_xlfn.XLOOKUP($A11,Table1[Location Name],Table1[Primary Counting Manager])="","",_xlfn.XLOOKUP($A11,Table1[Location Name],Table1[Primary Counting Manager])) -> Darryl | F11: 4-6 Hours | G11: 46135 | H11: 0.33333333 | I11: =_xlfn.XLOOKUP(Table39[[#This Row],[Location]],Table4[STORE '#],Table4[DATE RGR]) -> 46169 | J11: =_xlfn.XLOOKUP(Table39[[#This Row],[Location]],Table1[Location Name],Table1[Weekly Inventory Count Day]) -> Thursday | K11: =_xlfn.XLOOKUP(Table39[[#This Row],[Location]],Table1[Location Name],Table1[FOB Risk Profile]) -> High | L11: Earliest available date | M11: Changed Fdrom 04/02/26
A12: 13113 | B12: MADILL, HWY. 70 | C12: =_xlfn.XLOOKUP($A12,Table1[Location Name],Table1[Supervisor]) -> Ashley Podroza | D12: =_xlfn.XLOOKUP($A12,Table1[Location Name],Table1[GM]) -> Chris Abbey | E12: =IF(_xlfn.XLOOKUP($A12,Table1[Location Name],Table1[Primary Counting Manager])="","",_xlfn.XLOOKUP($A12,Table1[Location Name],Table1[Primary Counting Manager])) -> Josh | F12: 4-6 Hours | G12: 46126 | H12: 0.33333333 | I12: =_xlfn.XLOOKUP(Table39[[#This Row],[Location]],Table4[STORE '#],Table4[DATE RGR]) -> 46183 | J12: =_xlfn.XLOOKUP(Table39[[#This Row],[Location]],Table1[Location Name],Table1[Weekly Inventory Count Day]) -> Tuesday | K12: =_xlfn.XLOOKUP(Table39[[#This Row],[Location]],Table1[Location Name],Table1[FOB Risk Profile]) -> High | L12: Earliest available date | M12: Unchanged
A13: 31357 | B13: PAULS VALLEY RELO | C13: =_xlfn.XLOOKUP($A13,Table1[Location Name],Table1[Supervisor]) -> Amanda Estrada | D13: =_xlfn.XLOOKUP($A13,Table1[Location Name],Table1[GM]) -> Brady Giambaresi | E13: =IF(_xlfn.XLOOKUP($A13,Table1[Location Name],Table1[Primary Counting Manager])="","",_xlfn.XLOOKUP($A13,Table1[Location Name],Table1[Primary Counting Manager])) -> Angelo | F13: 4-6 Hours | G13: 46156 | H13: 0.33333333 | I13: 46198 | J13: =_xlfn.XLOOKUP(Table39[[#This Row],[Location]],Table1[Location Name],Table1[Weekly Inventory Count Day]) -> Thursday | K13: =_xlfn.XLOOKUP(Table39[[#This Row],[Location]],Table1[Location Name],Table1[FOB Risk Profile]) -> Medium | L13: Earliest available date | M13: Unchanged
A14: 35064 | B14: HOLDENVILLE, OK | C14: =_xlfn.XLOOKUP($A14,Table1[Location Name],Table1[Supervisor]) -> Steven Vaughn | D14: =_xlfn.XLOOKUP($A14,Table1[Location Name],Table1[GM]) -> Lynsey Yahola | E14: =IF(_xlfn.XLOOKUP($A14,Table1[Location Name],Table1[Primary Counting Manager])="","",_xlfn.XLOOKUP($A14,Table1[Location Name],Table1[Primary Counting Manager])) -> Lynsey | G14: 46092 | I14: =_xlfn.XLOOKUP(Table39[[#This Row],[Location]],Table4[STORE '#],Table4[DATE RGR]) -> 46211 | J14: =_xlfn.XLOOKUP(Table39[[#This Row],[Location]],Table1[Location Name],Table1[Weekly Inventory Count Day]) -> Wednesday | K14: =_xlfn.XLOOKUP(Table39[[#This Row],[Location]],Table1[Location Name],Table1[FOB Risk Profile]) -> High | M14: Completed
A15: 43380 | B15: MAIN AND REFUGE | C15: =_xlfn.XLOOKUP($A15,Table1[Location Name],Table1[Supervisor]) -> Ashley Podroza | D15: =_xlfn.XLOOKUP($A15,Table1[Location Name],Table1[GM]) -> Zukarr Eaves | E15: =IF(_xlfn.XLOOKUP($A15,Table1[Location Name],Table1[Primary Counting Manager])="","",_xlfn.XLOOKUP($A15,Table1[Location Name],Table1[Primary Counting Manager])) -> Zukaar | G15: 46088 | I15: =_xlfn.XLOOKUP(Table39[[#This Row],[Location]],Table4[STORE '#],Table4[DATE RGR]) -> 46225 | J15: =_xlfn.XLOOKUP(Table39[[#This Row],[Location]],Table1[Location Name],Table1[Weekly Inventory Count Day]) -> Saturday | K15: =_xlfn.XLOOKUP(Table39[[#This Row],[Location]],Table1[Location Name],Table1[FOB Risk Profile]) -> Medium | M15: Completed
A16: 3708 | B16: ARDMORE | C16: =_xlfn.XLOOKUP($A16,Table1[Location Name],Table1[Supervisor]) -> Robert Spencer | D16: =_xlfn.XLOOKUP($A16,Table1[Location Name],Table1[GM]) -> Cinthya Armedariz | E16: =IF(_xlfn.XLOOKUP($A16,Table1[Location Name],Table1[Primary Counting Manager])="","",_xlfn.XLOOKUP($A16,Table1[Location Name],Table1[Primary Counting Manager])) -> Cinthya | F16: 4-6 Hours | G16: 46133 | H16: 0.33333333 | I16: =_xlfn.XLOOKUP(Table39[[#This Row],[Location]],Table4[STORE '#],Table4[DATE RGR]) -> 46260 | J16: =_xlfn.XLOOKUP(Table39[[#This Row],[Location]],Table1[Location Name],Table1[Weekly Inventory Count Day]) -> Tuesday | K16: =_xlfn.XLOOKUP(Table39[[#This Row],[Location]],Table1[Location Name],Table1[FOB Risk Profile]) -> Medium | L16: Earliest available date | M16: Unchanged
A17: 5183 | B17: CHICKASHA | C17: =_xlfn.XLOOKUP($A17,Table1[Location Name],Table1[Supervisor]) -> Krystiana Langford | D17: =_xlfn.XLOOKUP($A17,Table1[Location Name],Table1[GM]) -> Mukarram Norman | E17: =IF(_xlfn.XLOOKUP($A17,Table1[Location Name],Table1[Primary Counting Manager])="","",_xlfn.XLOOKUP($A17,Table1[Location Name],Table1[Primary Counting Manager])) -> Mukarram | F17: 4-6 Hours | G17: 46163 | H17: 0.33333333 | I17: =_xlfn.XLOOKUP(Table39[[#This Row],[Location]],Table4[STORE '#],Table4[DATE RGR]) -> 46281 | J17: =_xlfn.XLOOKUP(Table39[[#This Row],[Location]],Table1[Location Name],Table1[Weekly Inventory Count Day]) -> Thursday | K17: =_xlfn.XLOOKUP(Table39[[#This Row],[Location]],Table1[Location Name],Table1[FOB Risk Profile]) -> Medium | L17: Earliest available date | M17: Changed from 04/23/26
A18: 33109 | B18: MARIETTA, OK | C18: =_xlfn.XLOOKUP($A18,Table1[Location Name],Table1[Supervisor]) -> Ashley Podroza | D18: =_xlfn.XLOOKUP($A18,Table1[Location Name],Table1[GM]) -> Rey Araiz | E18: =IF(_xlfn.XLOOKUP($A18,Table1[Location Name],Table1[Primary Counting Manager])="","",_xlfn.XLOOKUP($A18,Table1[Location Name],Table1[Primary Counting Manager])) -> Gisselle | F18: 4-6 Hours | G18: 46170 | H18: 0.33333333 | I18: =_xlfn.XLOOKUP(Table39[[#This Row],[Location]],Table4[STORE '#],Table4[DATE RGR]) -> 46295 | J18: =_xlfn.XLOOKUP(Table39[[#This Row],[Location]],Table1[Location Name],Table1[Weekly Inventory Count Day]) -> Tuesday | K18: =_xlfn.XLOOKUP(Table39[[#This Row],[Location]],Table1[Location Name],Table1[FOB Risk Profile]) -> Low | L18: Earliest available date | M18: Changed from 05/21/26
A19: 24471 | B19: ARDMORE, OK | C19: =_xlfn.XLOOKUP($A19,Table1[Location Name],Table1[Supervisor]) -> Robert Spencer | D19: =_xlfn.XLOOKUP($A19,Table1[Location Name],Table1[GM]) -> Mystykal Abbey | E19: =IF(_xlfn.XLOOKUP($A19,Table1[Location Name],Table1[Primary Counting Manager])="","",_xlfn.XLOOKUP($A19,Table1[Location Name],Table1[Primary Counting Manager])) -> Mystikal | G19: 46086 | I19: =_xlfn.XLOOKUP(Table39[[#This Row],[Location]],Table4[STORE '#],Table4[DATE RGR]) -> 46309 | J19: =_xlfn.XLOOKUP(Table39[[#This Row],[Location]],Table1[Location Name],Table1[Weekly Inventory Count Day]) -> Thursday | K19: =_xlfn.XLOOKUP(Table39[[#This Row],[Location]],Table1[Location Name],Table1[FOB Risk Profile]) -> High | M19: Completed
A20: 29760 | B20: DUNCAN, OK | C20: =_xlfn.XLOOKUP($A20,Table1[Location Name],Table1[Supervisor]) -> Krystiana Langford | D20: =_xlfn.XLOOKUP($A20,Table1[Location Name],Table1[GM]) -> Heather Danforth | E20: =IF(_xlfn.XLOOKUP($A20,Table1[Location Name],Table1[Primary Counting Manager])="","",_xlfn.XLOOKUP($A20,Table1[Location Name],Table1[Primary Counting Manager])) -> Magi | G20: 46100 | I20: =_xlfn.XLOOKUP(Table39[[#This Row],[Location]],Table4[STORE '#],Table4[DATE RGR]) -> 46323 | J20: =_xlfn.XLOOKUP(Table39[[#This Row],[Location]],Table1[Location Name],Table1[Weekly Inventory Count Day]) -> Thursday | K20: =_xlfn.XLOOKUP(Table39[[#This Row],[Location]],Table1[Location Name],Table1[FOB Risk Profile]) -> Low | M20: Completed
A21: 32525 | B21: SULPHUR, OK | C21: =_xlfn.XLOOKUP($A21,Table1[Location Name],Table1[Supervisor]) -> Robert Spencer | D21: =_xlfn.XLOOKUP($A21,Table1[Location Name],Table1[GM]) -> Aliyah Richardson | E21: =IF(_xlfn.XLOOKUP($A21,Table1[Location Name],Table1[Primary Counting Manager])="","",_xlfn.XLOOKUP($A21,Table1[Location Name],Table1[Primary Counting Manager])) -> Priscilla | F21: 4-6 Hours | G21: 46121 | H21: 0.54166667 | I21: =_xlfn.XLOOKUP(Table39[[#This Row],[Location]],Table4[STORE '#],Table4[DATE RGR]) -> 46337 | J21: =_xlfn.XLOOKUP(Table39[[#This Row],[Location]],Table1[Location Name],Table1[Weekly Inventory Count Day]) -> Thursday | K21: =_xlfn.XLOOKUP(Table39[[#This Row],[Location]],Table1[Location Name],Table1[FOB Risk Profile]) -> High | L21: Earliest available date | M21: Unchanged
A22: 18213 | B22: LINDSAY, OK | C22: =_xlfn.XLOOKUP($A22,Table1[Location Name],Table1[Supervisor]) -> Krystiana Langford | D22: =_xlfn.XLOOKUP($A22,Table1[Location Name],Table1[GM]) -> Cora Bahling | E22: =IF(_xlfn.XLOOKUP($A22,Table1[Location Name],Table1[Primary Counting Manager])="","",_xlfn.XLOOKUP($A22,Table1[Location Name],Table1[Primary Counting Manager])) -> Crystal | F22: 4-6 Hours | G22: 46191 | H22: 0.33333333 | I22: =_xlfn.XLOOKUP(Table39[[#This Row],[Location]],Table4[STORE '#],Table4[DATE RGR]) -> 46338 | J22: =_xlfn.XLOOKUP(Table39[[#This Row],[Location]],Table1[Location Name],Table1[Weekly Inventory Count Day]) -> Thursday | K22: =_xlfn.XLOOKUP(Table39[[#This Row],[Location]],Table1[Location Name],Table1[FOB Risk Profile]) -> Medium | L22: Earliest available date | M22: Changed from 05/07/26, Changed from 06/04/26

Sheet Scheduling Setup
A1: =TODAY() -> 46266 | O1: Use
A2: Location | B2: LocationName | C2: Supervisor | D2: GM | E2: Scheduling Manager | F2: Time Needed | G2: Date Scheduled | H2: Start Time | I2: RGR Date | J2: Count Day | K2: Sched Risk | L2: 1st Schedule Week | M2: GM Engagement | N2: Sched Mgr Engagement | O2: Execution Confidence | P2: if only 5 of these 20 improve, is this store one of them? | Q2: Notes
A3: 20475 | B3: OKC | C3: =_xlfn.XLOOKUP($A3,Table1[Location Name],Table1[Supervisor]) -> Amanda Estrada | D3: =_xlfn.XLOOKUP($A3,Table1[Location Name],Table1[GM]) -> Derek McGirt | E3: Rebecca | F3: 6-7 Hours | G3: 46239 | H3: 0.33333333 | I3: =_xlfn.XLOOKUP(Table393[[#This Row],[Location]],Table4[STORE '#],Table4[DATE RGR]) -> 46107 | J3: =_xlfn.XLOOKUP(Table393[[#This Row],[Location]],Table1[Location Name],Table1[Weekly Inventory Count Day]) -> Thursday | L3: 46246 | M3: Low | N3: Med | O3: Low | P3: No | Q3: Derek not fully engaged. Appeared asleep a couple times | R3: =S3 -> 46237 | S3: 46237
A4: 34222 | B4: HARRAH, OK | C4: =_xlfn.XLOOKUP($A4,Table1[Location Name],Table1[Supervisor]) -> Steven Vaughn | D4: =_xlfn.XLOOKUP($A4,Table1[Location Name],Table1[GM]) -> Hunter McKee | E4: Lezli | F4: 6-7 Hours | G4: 46239 | H4: 0.33333333 | I4: =_xlfn.XLOOKUP(Table393[[#This Row],[Location]],Table4[STORE '#],Table4[DATE RGR]) -> 46155 | J4: =_xlfn.XLOOKUP(Table393[[#This Row],[Location]],Table1[Location Name],Table1[Weekly Inventory Count Day]) -> Monday | L4: 46246 | M4: High | N4: Low | O4: Med | P4: No | Q4: Hunter volatile | R4: =S4 -> 46238 | S4: 46238
A5: 10422 | B5: ATOKA, OK | C5: =_xlfn.XLOOKUP($A5,Table1[Location Name],Table1[Supervisor]) -> Ashley Podroza | D5: =_xlfn.XLOOKUP($A5,Table1[Location Name],Table1[GM]) -> Ashleyh Hegwer | E5: Peggy May | F5: 6-7 Hours | G5: 46240 | H5: 0.33333333 | I5: =_xlfn.XLOOKUP(Table393[[#This Row],[Location]],Table4[STORE '#],Table4[DATE RGR]) -> 46051 | J5: =_xlfn.XLOOKUP(Table393[[#This Row],[Location]],Table1[Location Name],Table1[Weekly Inventory Count Day]) -> Saturday | L5: 46246 | M5: High | N5: High | O5: Med | P5: No | Q5: Both highly engaged | R5: =S5 -> 46239 | S5: 46239 | T5: Amanda
A6: 43380 | B6: MAIN AND REFUGE | C6: =_xlfn.XLOOKUP($A6,Table1[Location Name],Table1[Supervisor]) -> Ashley Podroza | D6: =_xlfn.XLOOKUP($A6,Table1[Location Name],Table1[GM]) -> Zukarr Eaves | E6: Sabrina Turner | F6: 6-7 Hours | G6: 46240 | H6: 0.33333333 | I6: =_xlfn.XLOOKUP(Table393[[#This Row],[Location]],Table4[STORE '#],Table4[DATE RGR]) -> 46225 | J6: =_xlfn.XLOOKUP(Table393[[#This Row],[Location]],Table1[Location Name],Table1[Weekly Inventory Count Day]) -> Saturday | L6: 46246 | M6: High | N6: Med | O6: High | P6: Yes | Q6: Zukkaar overpowers conversation. Sabrina soaked it in | R6: =S6 -> 46240 | S6: 46240 | T6: Ashley
A7: 33704 | B7: TECUMSEH, OK | C7: =_xlfn.XLOOKUP($A7,Table1[Location Name],Table1[Supervisor]) -> Steven Vaughn | D7: =_xlfn.XLOOKUP($A7,Table1[Location Name],Table1[GM]) -> Candy Barksdale | E7: Bella | F7: 6-7 Hours | G7: 46246 | H7: 0.33333333 | I7: =_xlfn.XLOOKUP(Table393[[#This Row],[Location]],Table4[STORE '#],Table4[DATE RGR]) -> 46127 | J7: =_xlfn.XLOOKUP(Table393[[#This Row],[Location]],Table1[Location Name],Table1[Weekly Inventory Count Day]) -> Friday | L7: 46253 | M7: High | N7: Low | O7: HIgh | P7: Yes | Q7: Candy highly engaged, easily frustrated. Bella not very invovled | R7: =S7 -> 46246 | S7: =S5+7 -> 46246 | T7: Steven
A8: 35064 | B8: HOLDENVILLE, OK | C8: =_xlfn.XLOOKUP($A8,Table1[Location Name],Table1[Supervisor]) -> Steven Vaughn | D8: =_xlfn.XLOOKUP($A8,Table1[Location Name],Table1[GM]) -> Lynsey Yahola | E8: Kevonte | F8: 6-7 Hours | G8: 46246 | H8: 0.33333333 | I8: =_xlfn.XLOOKUP(Table393[[#This Row],[Location]],Table4[STORE '#],Table4[DATE RGR]) -> 46211 | J8: =_xlfn.XLOOKUP(Table393[[#This Row],[Location]],Table1[Location Name],Table1[Weekly Inventory Count Day]) -> Wednesday | L8: 46253 | M8: Med | N8: High | O8: Med | P8: No | Q8: Lynsey distractd easily. Kevonte has heart and should do well | R8: =S8 -> 46247 | S8: =S6+7 -> 46247
A9: 5183 | B9: CHICKASHA | C9: =_xlfn.XLOOKUP($A9,Table1[Location Name],Table1[Supervisor]) -> Krystiana Langford | D9: =_xlfn.XLOOKUP($A9,Table1[Location Name],Table1[GM]) -> Mukarram Norman | E9: Pam | F9: 6-7 Hours | G9: 46247 | H9: 0.33333333 | I9: =_xlfn.XLOOKUP(Table393[[#This Row],[Location]],Table4[STORE '#],Table4[DATE RGR]) -> 46281 | J9: =_xlfn.XLOOKUP(Table393[[#This Row],[Location]],Table1[Location Name],Table1[Weekly Inventory Count Day]) -> Thursday | L9: 46260 | M9: High | N9: Med | O9: Med | P9: No | Q9: Mukarram super involved. Pam may struggle only due to tech. She is highly capableGM yilelds to Pam for actual duties | R9: =S9 -> 46251 | S9: 46251
A10: 18213 | B10: LINDSAY, OK | C10: =_xlfn.XLOOKUP($A10,Table1[Location Name],Table1[Supervisor]) -> Krystiana Langford | D10: =_xlfn.XLOOKUP($A10,Table1[Location Name],Table1[GM]) -> Cora Bahling | E10: Brad | F10: 6-7 Hours | G10: 46247 | H10: 0.33333333 | I10: =_xlfn.XLOOKUP(Table393[[#This Row],[Location]],Table4[STORE '#],Table4[DATE RGR]) -> 46338 | J10: =_xlfn.XLOOKUP(Table393[[#This Row],[Location]],Table1[Location Name],Table1[Weekly Inventory Count Day]) -> Thursday | L10: 46253 | M10: Med | N10: Med | O10: Low | P10: No | Q10: Cora not the numbers person. Very supportive. Brad quiet but soaked up info | R10: =S10 -> 46252 | S10: 46252
A11: 5985 | B11: DURANT | C11: =_xlfn.XLOOKUP($A11,Table1[Location Name],Table1[Supervisor]) -> Ashley Podroza | D11: =_xlfn.XLOOKUP($A11,Table1[Location Name],Table1[GM]) -> Stacey Hyatt | E11: Chasity | F11: 6-7 Hours | G11: 46251 | H11: 0.33333333 | I11: =_xlfn.XLOOKUP(Table393[[#This Row],[Location]],Table4[STORE '#],Table4[DATE RGR]) -> 46092 | J11: =_xlfn.XLOOKUP(Table393[[#This Row],[Location]],Table1[Location Name],Table1[Weekly Inventory Count Day]) -> Tuesday | L11: 46260 | M11: HIgh | N11: High | O11: High | P11: Yes | Q11: Both highly engaged | R11: =S11 -> 46260 | S11: 46260
A12: 32525 | B12: SULPHUR, OK | C12: =_xlfn.XLOOKUP($A12,Table1[Location Name],Table1[Supervisor]) -> Robert Spencer | D12: =_xlfn.XLOOKUP($A12,Table1[Location Name],Table1[GM]) -> Aliyah Richardson | E12: Sarah | F12: 6-7 Hours | G12: 46251 | H12: 0.33333333 | I12: =_xlfn.XLOOKUP(Table393[[#This Row],[Location]],Table4[STORE '#],Table4[DATE RGR]) -> 46337 | J12: =_xlfn.XLOOKUP(Table393[[#This Row],[Location]],Table1[Location Name],Table1[Weekly Inventory Count Day]) -> Thursday | L12: 46267 | M12: High | N12: Low | O12: Med | P12: No | Q12: Aliyah very engaged, Sarah learning schedule new and pay close attentio. She should do well. | R12: =S12 -> 46261 | S12: 46261
A13: 10915 | B13: SEMINOLE, OK | C13: =_xlfn.XLOOKUP($A13,Table1[Location Name],Table1[Supervisor]) -> Steven Vaughn | D13: =_xlfn.XLOOKUP($A13,Table1[Location Name],Table1[GM]) -> Caleb Nunnelley | E13: Tasha | F13: 6-7 Hours | G13: 46252 | H13: 0.33333333 | I13: =_xlfn.XLOOKUP(Table393[[#This Row],[Location]],Table4[STORE '#],Table4[DATE RGR]) -> 46071 | J13: =_xlfn.XLOOKUP(Table393[[#This Row],[Location]],Table1[Location Name],Table1[Weekly Inventory Count Day]) -> Wednesday | L13: 46260 | M13: N/A | N13: Med | O13: Low | P13: No | Q13: Caleb(GM) absent due to Large Order. Will reshedule. Tasha very engaged, but feel like will struggle to implement | R13: =S13 -> 46267 | S13: =S11+7 -> 46267
A14: 33109 | B14: MARIETTA, OK | C14: =_xlfn.XLOOKUP($A14,Table1[Location Name],Table1[Supervisor]) -> Ashley Podroza | D14: =_xlfn.XLOOKUP($A14,Table1[Location Name],Table1[GM]) -> Rey Araiz | E14: Angie | F14: 6-7 Hours | G14: 46252 | H14: 0.33333333 | I14: =_xlfn.XLOOKUP(Table393[[#This Row],[Location]],Table4[STORE '#],Table4[DATE RGR]) -> 46295 | J14: =_xlfn.XLOOKUP(Table393[[#This Row],[Location]],Table1[Location Name],Table1[Weekly Inventory Count Day]) -> Tuesday | L14: 46260 | M14: Med | N14: High | O14: Med | P14: No | Q14: Rey involved but yielded mostly to Angie whom has a deep knowledge for the schedule. Could be one of the five. Borederline | R14: =S14 -> 46268 | S14: =S12+7 -> 46268 | T14: Robert
A15: 11657 | B15: PURCELL | C15: =_xlfn.XLOOKUP($A15,Table1[Location Name],Table1[Supervisor]) -> Amanda Estrada | D15: =_xlfn.XLOOKUP($A15,Table1[Location Name],Table1[GM]) -> Jessie Hiatt | E15: Olivia | F15: 6-7 Hours | G15: 46260 | H15: 0.33333333 | I15: =_xlfn.XLOOKUP(Table393[[#This Row],[Location]],Table4[STORE '#],Table4[DATE RGR]) -> 46134 | J15: =_xlfn.XLOOKUP(Table393[[#This Row],[Location]],Table1[Location Name],Table1[Weekly Inventory Count Day]) -> Thursday | L15: 46267 | M15: High | N15: HIgh | O15: High | P15: Yes | Q15: Jessie amazing, involved and knowledgeable. Olivia is geat as well
A16: 6972 | B16: ADA | C16: =_xlfn.XLOOKUP($A16,Table1[Location Name],Table1[Supervisor]) -> Robert Spencer | D16: =_xlfn.XLOOKUP($A16,Table1[Location Name],Table1[GM]) -> Nick Rice | E16: Bobbi | F16: 6-7 Hours | G16: 46261 | H16: 0.33333333 | I16: =_xlfn.XLOOKUP(Table393[[#This Row],[Location]],Table4[STORE '#],Table4[DATE RGR]) -> 46063 | J16: =_xlfn.XLOOKUP(Table393[[#This Row],[Location]],Table1[Location Name],Table1[Weekly Inventory Count Day]) -> Thursday | L16: 46267 | M16: Med | N16: Med | O16: Low | P16: No | Q16: Both struggled to understand process due to wrong/no training previously
A17: 31357 | B17: PAULS VALLEY RELO | C17: =_xlfn.XLOOKUP($A17,Table1[Location Name],Table1[Supervisor]) -> Amanda Estrada | D17: =_xlfn.XLOOKUP($A17,Table1[Location Name],Table1[GM]) -> Brady Giambaresi | E17: Ashleigh | F17: 6-7 Hours | G17: 46261 | H17: 0.33333333 | I17: 46198 | J17: =_xlfn.XLOOKUP(Table393[[#This Row],[Location]],Table1[Location Name],Table1[Weekly Inventory Count Day]) -> Thursday | L17: 46267 | M17: Med | N17: High | O17: Med | P17: No | Q17: Good engagement from both. Brady left early. Ashleigh extremely sharp | R17: 2 Pre Classes leading up
A18: 29760 | B18: DUNCAN, OK | C18: =_xlfn.XLOOKUP($A18,Table1[Location Name],Table1[Supervisor]) -> Krystiana Langford | D18: =_xlfn.XLOOKUP($A18,Table1[Location Name],Table1[GM]) -> Heather Danforth | E18: Stephanie | F18: 6-7 Hours | G18: 46267 | H18: 0.33333333 | I18: =_xlfn.XLOOKUP(Table393[[#This Row],[Location]],Table4[STORE '#],Table4[DATE RGR]) -> 46323 | J18: =_xlfn.XLOOKUP(Table393[[#This Row],[Location]],Table1[Location Name],Table1[Weekly Inventory Count Day]) -> Thursday | L18: 46267 | R18: Scheduling Training Overview and Pre-work for Restaurants | U18: 2 Weeks Out
A19: 33222 | B19: ELGIN, OK | C19: =_xlfn.XLOOKUP($A19,Table1[Location Name],Table1[Supervisor]) -> Krystiana Langford | D19: =_xlfn.XLOOKUP($A19,Table1[Location Name],Table1[GM]) -> Carol Escusa | E19: Stephanie | F19: 6-7 Hours | G19: 46267 | H19: 0.33333333 | I19: =_xlfn.XLOOKUP(Table393[[#This Row],[Location]],Table4[STORE '#],Table4[DATE RGR]) -> 46169 | J19: =_xlfn.XLOOKUP(Table393[[#This Row],[Location]],Table1[Location Name],Table1[Weekly Inventory Count Day]) -> Thursday | L19: 46274 | R19: Scheduling Setup Class - Verification and Completion of Pre-work in LifeLenz | U19: < 1 Week Out
A20: 13113 | B20: MADILL, HWY. 70 | C20: =_xlfn.XLOOKUP($A20,Table1[Location Name],Table1[Supervisor]) -> Ashley Podroza | D20: =_xlfn.XLOOKUP($A20,Table1[Location Name],Table1[GM]) -> Chris Abbey | E20: Colton Standeraur | F20: 6-7 Hours | G20: 46268 | H20: 0.33333333 | I20: 46252 | J20: =_xlfn.XLOOKUP(Table393[[#This Row],[Location]],Table1[Location Name],Table1[Weekly Inventory Count Day]) -> Tuesday | L20: 46274
A21: 3708 | B21: ARDMORE | C21: =_xlfn.XLOOKUP($A21,Table1[Location Name],Table1[Supervisor]) -> Robert Spencer | D21: =_xlfn.XLOOKUP($A21,Table1[Location Name],Table1[GM]) -> Cinthya Armedariz | E21: Siara | F21: 6-7 Hours | G21: 46268 | H21: 0.33333333 | I21: =_xlfn.XLOOKUP(Table393[[#This Row],[Location]],Table4[STORE '#],Table4[DATE RGR]) -> 46260 | J21: =_xlfn.XLOOKUP(Table393[[#This Row],[Location]],Table1[Location Name],Table1[Weekly Inventory Count Day]) -> Tuesday | L21: 46274
A22: 24471 | B22: ARDMORE, OK | C22: =_xlfn.XLOOKUP($A22,Table1[Location Name],Table1[Supervisor]) -> Robert Spencer | D22: =_xlfn.XLOOKUP($A22,Table1[Location Name],Table1[GM]) -> Mystykal Abbey | E22: Rasheda | F22: 6-7 Hours | G22: 46268 | H22: 0.33333333 | I22: =_xlfn.XLOOKUP(Table393[[#This Row],[Location]],Table4[STORE '#],Table4[DATE RGR]) -> 46309 | J22: =_xlfn.XLOOKUP(Table393[[#This Row],[Location]],Table1[Location Name],Table1[Weekly Inventory Count Day]) -> Thursday | L22: 46274
C25: Store | D25: Store
A26: 46237 | B26: Setup/Mgr Sched
A27: 46238 | B27: Setup/Mgr Sched
A28: 46239 | B28: Crew Schedule
A29: 46240 | B29: Crew Schedule
A30: =A28+7 -> 46246 | B30: Crew Schedule
A31: =A29+7 -> 46247 | B31: Crew Schedule
A32: =A30+7 -> 46253 | B32: Crew Schedule
A33: =A31+7 -> 46254 | B33: Crew Schedule
A34: =A32+7 -> 46260 | B34: Crew Schedule
A35: =A33+7 -> 46261 | B35: Crew Schedule
A36: =A34+7 -> 46267 | B36: Crew Schedule
A37: =A35+7 -> 46268 | B37: Crew Schedule

Sheet IMET
A2: Location Name | B2: GM | C2: IMET Training (MB) | D2: IMET Training (Internal) | E2: Primary Counting Manager | F2: IMET Training (MB) | G2: IMET Training (Internal) | H2: Date Trained
A3: 3708 | B3: Cinthya Armedariz | C3: Yes | E3: Cinthya | F3: Yes | H3: 46128
A4: 5183 | B4: Mukarram Norman | C4: Yes | E4: Mukarram | F4: Yes | H4: 46128
A5: 5985 | B5: Stacey Hyatt | D5: Yes | E5: Scauti/Chas | G5: Yes | H5: 46184
A6: 6972 | B6: Nick Rice | C6: Yes | E6: Beth | F6: Yes | H6: 46128
A7: 10422 | B7: Ashley Hegwer | D7: Yes | E7: Ashley | G7: Yes | H7: 46184
A8: 10915 | B8: Caleb Nunnelley | C8: Yes | E8: Caitlin | F8: Yes | H8: 46128
A9: 11657 | B9: Jessie Hiatt | C9: Yes | E9: Norma | F9: Yes | H9: 46128
A10: 13113 | B10: Chris Abbey | C10: Yes | E10: Josh | F10: Yes | H10: 46128
A11: 18213 | B11: Cora Bahling | C11: Yes | F11: Yes | H11: 46128
A12: 20475 | B12: Derek McGirt | D12: Yes | E12: Susanna | G12: Yes | H12: 46184
A13: 24471 | B13: Mystykal Abbey | C13: Yes | E13: Mystikal | F13: Yes | H13: 46128
A14: 29760 | B14: Heather Danforth | D14: Yes | E14: Magi | G14: Yes | H14: 46184
A15: 31357 | B15: Brady Giambaresi | C15: Yes | E15: Angelo | F15: Yes | H15: 46128
A16: 32525 | B16: Aliyah Richardson | C16: Yes | E16: Priscilla | F16: Yes | H16: 46128
A17: 33109 | B17: Rey Araiz | D17: Yes | G17: Yes | H17: 46184
A18: 33222 | B18: Carol Escusa | C18: Yes | E18: Darryl | F18: Yes | H18: 46128
A19: 33704 | B19: Candy Barksdale | C19: Yes | E19: Marlena | F19: Yes | H19: 46128
A20: 34222 | B20: Hunter McKee | D20: Yes | E20: Kaylee | G20: Yes | H20: 46184
A21: 35064 | B21: Lynsey Yahola | C21: Yes | E21: Lynsey | F21: Yes | H21: 46128
A22: 43380 | B22: Zukarr Eaves | D22: Yes | E22: Zukaar | G22: Yes | H22: 46184
A23: 6178 | B23: Janet Jeter | C23: No | D23: No | F23: No | G23: No
A24: 6838 | B24: Stephanie Harris | C24: No | D24: No | F24: No | G24: No
A25: 10034 | B25: Harlee Yates | C25: No | D25: No | F25: No | G25: No
A26: 35242 | B26: Michele Nixon | C26: No | D26: No | F26: No | G26: No
A27: 37566 | B27: Debra Herndon | C27: No | D27: No | F27: No | G27: No
A28: 38609 | B28: Christina Bencokzy | C28: No | D28: No | F28: No | G28: No
A29: 43701 | B29: Shannon Hardin | C29: No | D29: No | F29: No | G29: No

Sheet 3708
A1: Location | B1: 3708 | C1: RGR Date | D1: =_xlfn.XLOOKUP(B1,'FC-Inv Setup'!A3:A22,'FC-Inv Setup'!I3:I22) -> 46260 | F1: Date Scheduled | G1: Start Time | K1: Validity | L1: Status
A2: Supervisor | B2: =_xlfn.XLOOKUP(B1,'FC-Inv Setup'!A3:A22,'FC-Inv Setup'!C3:C22) -> Robert Spencer | C2: FOB Risk | D2: =_xlfn.XLOOKUP(B1,'FC-Inv Setup'!A3:A22,'FC-Inv Setup'!K3:K22) -> Medium
A3: GM | B3: =_xlfn.XLOOKUP(B1,'FC-Inv Setup'!A3:A22,'FC-Inv Setup'!D3:D22) -> Cinthya Armedariz
A4: Counting Manager | B4: =_xlfn.XLOOKUP(B1,'FC-Inv Setup'!A3:A22,'FC-Inv Setup'!E3:E22) -> Cinthya
A5: Count Day | B5: =_xlfn.XLOOKUP(B1,'FC-Inv Setup'!A3:A22,'FC-Inv Setup'!J3:J22) -> Tuesday
C6: Data N/A | D6: Data N/A
A7: Date | B7: Dec EOM | C7: 46028 | D7: 46035 | E7: 46042 | F7: 46049 | G7: 01/31/26% | H7: 46056 | I7: 46063 | J7: 46070 | K7: 46077 | L7: 2/28/26 | M7: 46084 | N7: 46091 | O7: 46098 | P7: 46105 | Q7: 3/31/26 | R7: 4/7/26 | S7: 4/14/26 | T7: 4/21/26 | U7: 4/28/26 | V7: 4/30/26
A8: Cycle | B8: EOM | E8: Count Day | F8: Count Day | G8: EOM | H8: Count Day | I8: Count Day | J8: Count Day | K8: Count Day | L8: EOM | M8: Count Day | N8: Count Day | O8: Count Day | P8: Count Day | Q8: EOM | R8: Count Day | S8: Count Day | T8: Count Day | U8: Count Day | V8: EOM
A9: Product Net Sales | B9: 354316.7 | E9: 81427.39 | F9: 65262.07 | G9: 306572.29 | H9: 31584.29 | I9: 84327.35 | J9: 81369.78 | K9: 87050.44 | L9: 303713.4 | M9: 32757.7 | N9: 86003.9 | O9: 87353.68 | P9: 89351.12
A10: Total Paper Cost (%) | B10: 3.88 | E10: 4.04 | F10: 3.9 | G10: 3.61 | H10: 3.25 | I10: 4.13 | J10: 3.54 | K10: 3.65 | L10: 3.78 | M10: 3.2 | N10: 4.12 | O10: 4.2 | P10: 3.52
A11: Total Paper Cost ($) | B11: 13743.68 | E11: 3291.54 | F11: 2542.03 | G11: 11064.99 | H11: 1025.02 | I11: 3480.74 | J11: 2881.61 | K11: 3176.24 | L11: 11492.28 | M11: 1047.04 | N11: 3450.35 | O11: 3672.73 | P11: 3141.67
A12: Completed Waste | B12: 0.38 | E12: 0.48 | F12: 0.43 | G12: 0.46 | H12: 0.24 | I12: 0.43 | J12: 0.36 | K12: 0.32 | L12: 0.34 | M12: 0.27 | N12: 0.41 | O12: 0.42 | P12: 0.45
A13: Raw Waste | B13: 0.37 | E13: 0.54 | F13: 0.64 | G13: 0.61 | H13: 0.52 | I13: 0.53 | J13: 0.52 | K13: 0.47 | L13: 0.51 | M13: 0.41 | N13: 0.56 | O13: 0.42 | P13: 0.33
A14: Condiments | B14: 1.95 | E14: 2.28 | F14: 2.44 | G14: 2.11 | H14: 2.12 | I14: 2.36 | J14: 2.48 | K14: 2.11 | L14: 2.16 | M14: 2.16 | N14: 1.92 | O14: 2.02 | P14: 1.93
A15: Emp Mgr Meals | B15: 0.18 | E15: 0.21 | F15: 0.23 | G15: 0.22 | H15: 0.2 | I15: 0.19 | J15: 0.21 | K15: 0.2 | L15: 0.2 | M15: 0.22 | N15: 0.19 | O15: 0.16 | P15: 0.17
A16: Variance Stat | B16: 1.31 | E16: 1.49 | F16: 1.48 | G16: 0.8 | H16: -0.07 | I16: 1.28 | J16: 0.49 | K16: 1.44 | L16: 1.15 | M16: -0.08 | N16: 1.99 | O16: 2.18 | P16: 1.58
A17: Unexplained | B17: -0.02 | E17: -0.05 | F17: 0 | G17: -0.05 | H17: 0.07 | I17: 0.01 | J17: -0.03 | K17: -0.02 | L17: 0.01 | M17: -0.03 | N17: -0.05 | O17: -0.08 | P17: -0.06
A18: Food Over Base | B18: 4.17 | E18: 4.95 | F18: 5.22 | G18: 4.15 | H18: 3.08 | I18: 4.8 | J18: 4.03 | K18: 4.52 | L18: 4.37 | M18: 2.95 | N18: 5.02 | O18: 5.12 | P18: 4.4
A19: Base Food | B19: 22.746048 | E19: 23.065832 | F19: 23.154795 | G19: 23.032121 | H19: 23.133749 | I19: 23.19685 | J19: 23.203236 | K19: 22.992445 | L19: 23.094649 | M19: 22.741087 | N19: 23.239369 | O19: 23.243149 | P19: 23.103799
A20: Discounts/Coupons | B20: 1.29 | E20: 1.26 | F20: 1.3 | G20: 1.32 | H20: 1.26 | I20: 1.29 | J20: 1.24 | K20: 1.33 | L20: 1.3 | M20: 1.39 | N20: 1.43 | O20: 1.65 | P20: 1.65
A21: Total Food Cost | B21: 28.2 | E21: 29.28 | F21: 29.68 | G21: 28.49 | H21: 27.47 | I21: 29.29 | J21: 28.48 | K21: 28.85 | L21: 28.77 | M21: 27.08 | N21: 29.69 | O21: 30.01 | P21: 29.16
A22: Food
A23: Beginning Inventory (+) | B23: 19294.02 | E23: 19873.09 | F23: 18240.15 | G23: 21625.48 | H23: 14869.96 | I23: 18962.27 | J23: 19754.81 | K23: 21673.91 | L23: 14869.96 | M23: 13345.31 | N23: 21719.95 | O23: 23701.18 | P23: 21074
A24: Purchases | B24: 105040.97 | E24: 19214.43 | F24: 22680 | G24: 84008.65 | H24: 9966.48 | I24: 24250.71 | J24: 23251.07 | K24: 22484.18 | L24: 89874.66 | M24: 15454.11 | N24: 24751.14 | O24: 21794.02 | P24: 22142.46
A25: Adjustments (+/-) | B25: -100.42 | E25: -131.56 | F25: 0 | G25: -171.69 | H25: 0 | I25: 0 | J25: -45.13 | K25: 0 | L25: -45.13 | M25: 0 | N25: -200.43 | O25: 0 | P25: 0
A26: Transfers | B26: 60.89 | E26: -41.68 | F26: -50.98 | G26: -150.77 | H26: -64.73 | I26: -1111.08 | J26: 7.38 | K26: -34.8 | L26: -1185.51 | M26: -41.74 | N26: -886.16 | O26: -1235.55 | P26: -496.59
A27: Promotions (-) | B27: 2745.11 | E27: 792.74 | F27: 661.02 | G27: 3092.01 | H27: 307.93 | I27: 914.81 | J27: 775.46 | K27: 755.5 | L27: 2794.97 | M27: 286.84 | N27: 733.49 | O27: 532.58 | P27: 473.83
A28: Ending Inventory (-) | B28: 21625.48 | E28: 14276.52 | F28: 20840.09 | G28: 14869.96 | H28: 15788.86 | I28: 16491.25 | J28: 19019.89 | K28: 18257.72 | L28: 13345.31 | M28: 19599.13 | N28: 19120.43 | O28: 17510.47 | P28: 16193.05
A29: Total | B29: 99924.86 | E29: 23845.02 | F29: 19368.07 | G29: 87349.69 | H29: 8674.92 | I29: 24695.85 | J29: 23172.77 | K29: 25110.07 | L29: 87373.72 | M29: 8871.72 | N29: 25530.59 | O29: 26216.59 | P29: 26053
A30: Paper
A31: Beginning Inventory (+) | B31: 7037.65 | E31: 5995.84 | F31: 5799.07 | G31: 6211.72 | H31: 5353.25 | I31: 5778.77 | J31: 6095.33 | K31: 6701.62 | L31: 20223.21 | M31: 5175.66 | N31: 6503.15 | O31: 6594.51 | P31: 6641.09
A32: Purchases | B32: 13102.98 | E32: 2562.18 | F32: 2588.27 | G32: 10387.21 | H32: 1111.87 | I32: 3373.19 | J32: 3219.21 | K32: 2676.18 | L32: 101436.04 | M32: 2049.1 | N32: 2779.92 | O32: 3148.53 | P32: 2495.76
A33: Adjustments (+/-) | B33: 0 | E33: 0 | F33: 0 | G33: 0 | H33: 0 | I33: 0 | J33: 0 | K33: 0 | L33: -45.13 | M33: 0 | N33: 0 | O33: 0 | P33: 0
A34: Transfers | B34: 23.53 | E34: 0 | F34: 0 | G34: 35.58 | H34: 0 | I34: -38.67 | J34: 0 | K34: -5.64 | L34: -1238.47 | M34: -7.95 | N34: -12.17 | O34: -25.79 | P34: -19.52
A35: Promotions (-) | B35: 208.76 | E35: 55.24 | F35: 46.1 | G35: 216.28 | H35: 21.94 | I35: 63.79 | J35: 52.49 | K35: 51.93 | L35: 2988.69 | M35: 19.43 | N35: 50.48 | O35: 40.77 | P35: 36.34
A36: Ending Inventory (-) | B36: 6211.72 | E36: 5211.25 | F36: 5799.21 | G36: 5353.25 | H36: 5418.16 | I36: 5568.76 | J36: 6380.44 | K36: 6143.99 | L36: 18520.97 | M36: 6150.34 | N36: 5680.07 | O36: 6003.74 | P36: 5939.31
A37: Total | B37: 13743.68 | E37: 3291.54 | F37: 2542.03 | G37: 11064.99 | H37: 1025.02 | I37: 3480.74 | J37: 2881.61 | K37: 3176.24 | L37: 98866 | M37: 1047.04 | N37: 3540.35 | O37: 3672.73 | P37: 3141.67
A40: Notes
A41: 46123
W65: View Activity

Sheet 5183
A1: Location | B1: 5183 | C1: RGR Date | D1: =_xlfn.XLOOKUP(B1,'FC-Inv Setup'!A3:A22,'FC-Inv Setup'!I3:I22) -> 46281 | F1: Date Scheduled | G1: Start Time | K1: Validity | L1: Status
A2: Supervisor | B2: =_xlfn.XLOOKUP(B1,'FC-Inv Setup'!A3:A22,'FC-Inv Setup'!C3:C22) -> Krystiana Langford | C2: FOB Risk | D2: =_xlfn.XLOOKUP(B1,'FC-Inv Setup'!A3:A22,'FC-Inv Setup'!K3:K22) -> Medium
A3: GM | B3: =_xlfn.XLOOKUP(B1,'FC-Inv Setup'!A3:A22,'FC-Inv Setup'!D3:D22) -> Mukarram Norman
A4: Counting Manager | B4: =_xlfn.XLOOKUP(B1,'FC-Inv Setup'!A3:A22,'FC-Inv Setup'!E3:E22) -> Mukarram
A5: Count Day | B5: =_xlfn.XLOOKUP(B1,'FC-Inv Setup'!A3:A22,'FC-Inv Setup'!J3:J22) -> Thursday
C6: Data N/A | D6: Data N/A
A7: Date | B7: Dec EOM | C7: 46030 | D7: 46249 | E7: 46044 | F7: 46051 | G7: 01/31/26% | H7: 46058 | I7: 46065 | J7: 46072 | K7: 46079 | L7: 2/28/26 | M7: 46086 | N7: 46093 | O7: 46100 | P7: 46107 | Q7: 3/31/26 | R7: 46114 | S7: 46121 | T7: 46128 | U7: 46135 | V7: 4/30/26
A8: Cycle | B8: EOM | E8: Count Day | F8: Count Day | G8: EOM | H8: Count Day | I8: Count Day | J8: Count Day | K8: Count Day | L8: EOM | M8: Count Day | N8: Count Day | O8: Count Day | P8: Count Day | Q8: EOM | R8: Count Day | S8: Count Day | T8: Count Day | U8: Count Day | V8: EOM
A9: Product Net Sales | B9: 539331.58 | E9: 119326.26 | F9: 94795.47 | G9: 441804.76 | H9: 73701.4 | I9: 121675.19 | J9: 119569.19 | K9: 132452.83 | L9: 440065.81 | M9: 80692.49 | N9: 132660.74 | O9: 126427.74
A10: Total Paper Cost (%) | B10: 4.03 | E10: 3.38 | F10: 3.41 | G10: 3.85 | H10: 3.43 | I10: 3.45 | J10: 3.44 | K10: 3.47 | L10: 4.02 | M10: 3.31 | N10: 3.27 | O10: 3.13
A11: Total Paper Cost ($) | B11: 21729.64 | E11: 4027.38 | F11: 3234.29 | G11: 16989.37 | H11: 2530.01 | I11: 4193.21 | J11: 4113.42 | K11: 4589.62 | L11: 17698.96 | M11: 2669.47 | N11: 4332.37 | O11: 3961.23
A12: Completed Waste | B12: 0.08 | E12: 0.1 | F12: 0.1 | G12: 0.1 | H12: 0.12 | I12: 0.12 | J12: 0.07 | K12: 0.06 | L12: 0.09 | M12: 0.05 | N12: 0.05 | O12: 0.08
A13: Raw Waste | B13: 0.26 | E13: 0.22 | F13: 0.38 | G13: 0.26 | H13: 0.18 | I13: 0.25 | J13: 0.26 | K13: 0.26 | L13: 0.27 | M13: 0.17 | N13: 0.17 | O13: 0.25
A14: Condiments | B14: 2.03 | E14: 2.16 | F14: 1.99 | G14: 2.18 | H14: 2.16 | I14: 1.86 | J14: 1.87 | K14: 2.04 | L14: 2.04 | M14: 2.05 | N14: 1.91 | O14: 1.82
A15: Emp Mgr Meals | B15: 0.27 | E15: 0.3 | F15: 0.32 | G15: 0.3 | H15: 0.25 | I15: 0.26 | J15: 0.29 | K15: 0.27 | L15: 0.27 | M15: 0.3 | N15: 0.31 | O15: 0.34
A16: Variance Stat | B16: 1.83 | E16: 4.41 | F16: 1.14 | G16: 1.88 | H16: 0 | I16: 2.51 | J16: 2.69 | K16: 2.32 | L16: 1.65 | M16: -0.03 | N16: 3.16 | O16: 5.1
A17: Unexplained | B17: -0.24 | E17: -0.24 | F17: -0.25 | G17: -0.23 | H17: -0.22 | I17: -0.25 | J17: -0.24 | K17: -0.22 | L17: -0.23 | M17: -0.23 | N17: -0.24 | O17: -0.22
A18: Food Over Base | B18: 4.23 | E18: 6.95 | F18: 3.68 | G18: 4.49 | H18: 2.49 | I18: 4.75 | J18: 4.94 | K18: 4.73 | L18: 4.09 | M18: 2.31 | N18: 5.36 | O18: 7.37
A19: Base Food | B19: 22.956067 | E19: 23.129581 | F19: 23.450413 | G19: 23.216953 | H19: 23.399272 | I19: 23.322407 | J19: 23.180057 | K19: 23.017637 | L19: 23.145682 | M19: 23.272651 | N19: 23.459175 | O19: 23.2546
A20: Discounts/Coupons | B20: 1.49 | E20: 1.54 | F20: 1.58 | G20: 1.57 | H20: 1.55 | I20: 1.54 | J20: 1.54 | K20: 1.52 | L20: 1.54 | M20: 1.67 | N20: 1.6 | O20: 1.81
A21: Total Food Cost | B21: 28.67 | E21: 31.62 | F21: 28.71 | G21: 29.27 | H21: 27.44 | I21: 29.61 | J21: 29.66 | K21: 29.27 | L21: 28.78 | M21: 27.25 | N21: 30.42 | O21: 32.44
A22: Food
A23: Beginning Inventory (+) | B23: 22662.78 | E23: 27593.71 | F23: 26191.76 | G23: 26815.65 | H23: 24934.54 | I23: 24344.37 | J23: 26820.6 | K23: 26916.61 | L23: 24934.54 | M23: 25806.34 | N23: 25177.26 | O23: 28672.63
A24: Purchases | B24: 163423.52 | E24: 32210.33 | F24: 26113.29 | G24: 131438.11 | H24: 16024.19 | I24: 32983.34 | J24: 32005.51 | K24: 31420.82 | L24: 131528.07 | M24: 17160.92 | N24: 37282.84 | O24: 32293.46
A25: Adjustments (+/-) | B25: -299.15 | E25: -111.32 | F25: 0 | G25: -145.28 | H25: 0 | I25: -523.84 | J25: -1.47 | K25: 0 | L25: -525.31 | M25: 0 | N25: -10.75 | O25: 0
A26: Transfers | B26: -678.57 | E26: -268.19 | F26: 0 | G26: -268.19 | H26: -214.56 | I26: -214.56 | J26: 0 | K26: -162.3 | L26: -343.68 | M26: -31.38 | N26: -143.41 | O26: 0
A27: Promotions (-) | B27: 3655.64 | E27: 955.76 | F27: 792.16 | G27: 3581.09 | H27: 595.41 | I27: 871.67 | J27: 838.19 | K27: 925.03 | L27: 3155.26 | M27: 563.88 | N27: 817.9 | O27: 711.82
A28: Ending Inventory (-) | B28: 26815.65 | E28: 20739.99 | F28: 24295.67 | G28: 24934.54 | H28: 19923.55 | I28: 19685.91 | J28: 22523.46 | K28: 18481.43 | L28: 25806.34 | M28: 20383.53 | N28: 21128.28 | O28: 19246.18
A29: Total | B29: 154637.28 | E29: 37728.78 | F29: 27217.23 | G29: 129324.65 | H29: 20225.22 | I29: 36031.74 | J29: 35462.99 | K29: 38768.67 | L29: 126632.02 | M29: 21988.48 | N29: 40359.76 | O29: 41008.09
A30: Paper
A31: Beginning Inventory (+) | B31: 7378.24 | E31: 7184.17 | F31: 7441.79 | G31: 6463.26 | H31: 6271.11 | I31: 6207 | J31: 6903.44 | K31: 7986.08 | L31: 6271.11 | M31: 6295.61 | N31: 6549.41 | O31: 7149.62
A32: Purchases | B32: 21116.02 | E32: 3797.79 | F32: 3601.84 | G32: 17048.5 | H32: 1983.08 | I32: 4428.38 | J32: 4722.2 | K32: 4282.01 | L32: 17959.12 | M32: 2372.72 | N32: 4675.1 | O32: 4205.31
A33: Adjustments (+/-) | B33: 0 | E33: 0 | F33: 0 | G33: 0 | H33: 0 | I33: 0 | J33: 0 | K33: 0 | L33: 0 | M33: 0 | N33: 0 | O33: 0
A34: Transfers | B34: -26.26 | E34: 0 | F34: 0 | G34: 0 | H34: 0 | I34: -8.52 | J34: 0 | K34: 0 | L34: -8.52 | M34: 0 | N34: -17.09 | O34: 0
A35: Promotions (-) | B35: 275.11 | E35: 67.7 | F35: 55.99 | G35: 251.28 | H35: 42.26 | I35: 61.78 | J35: 61.61 | K35: 66.57 | L35: 227.14 | M35: 40.57 | N35: 58.44 | O35: 56.05
A36: Ending Inventory (-) | B36: 6463.26 | E36: 6886.88 | F36: 7753.36 | G36: 6271.11 | H36: 5681.92 | I36: 6371.86 | J36: 7450.6 | K36: 7611.9 | L36: 6295.61 | M36: 5958.3 | N36: 6816.61 | O36: 7337.66
A37: Total | B37: 21729.64 | E37: 4027.38 | F37: 3234.29 | G37: 16989.37 | H37: 2530.01 | I37: 4193.21 | J37: 4113.42 | K37: 4589.62 | L37: 17698.96 | M37: 2669.47 | N37: 4332.37 | O37: 3961.23
A40: Notes

Sheet 5985
A1: Location | B1: 5985 | C1: RGR Date | D1: =_xlfn.XLOOKUP(B1,'FC-Inv Setup'!A3:A22,'FC-Inv Setup'!I3:I22) -> 46092 | F1: Date Scheduled | G1: Start Time | K1: Validity | L1: Status
A2: Supervisor | B2: =_xlfn.XLOOKUP(B1,'FC-Inv Setup'!A3:A22,'FC-Inv Setup'!C3:C22) -> Ashley Podroza | C2: FOB Risk | D2: =_xlfn.XLOOKUP(B1,'FC-Inv Setup'!A3:A22,'FC-Inv Setup'!K3:K22) -> Low
A3: GM | B3: =_xlfn.XLOOKUP(B1,'FC-Inv Setup'!A3:A22,'FC-Inv Setup'!D3:D22) -> Stacey Hyatt
A4: Counting Manager | B4: =_xlfn.XLOOKUP(B1,'FC-Inv Setup'!A3:A22,'FC-Inv Setup'!E3:E22) -> Scauti/Chas
A5: Count Day | B5: =_xlfn.XLOOKUP(B1,'FC-Inv Setup'!A3:A22,'FC-Inv Setup'!J3:J22) -> Tuesday
C6: Data N/A | D6: Data N/A
A7: Date | B7: 46028 | C7: 46035 | D7: 46042 | E7: 46049 | F7: 01/31/26% | G7: 46056 | H7: 46063 | I7: 46070 | J7: 46077 | K7: 2/28/26 | L7: 46084 | M7: 46091 | N7: 46098 | O7: 46105 | P7: 3/31/26 | Q7: 4/7/26 | R7: 4/14/26 | S7: 4/21/26 | T7: 4/28/26 | U7: 4/30/26 | V7: 4/30/26
A8: Cycle | B8: EOM | D8: Count Day | E8: Count Day | F8: EOM | G8: Count Day | H8: Count Day | I8: Count Day | J8: Count Day | K8: EOM | L8: Count Day | M8: Count Day | N8: Count Day | O8: Count Day | P8: Count Day | Q8: EOM | R8: Count Day | S8: Count Day | T8: Count Day | U8: Count Day | V8: EOM
A9: Product Net Sales | B9: 685205.85 | D9: 157775.99 | E9: 116072.71 | F9: 583890.47 | G9: 57025.52 | H9: 163915.2 | I9: 161461.66 | J9: 168899.57 | K9: 588965.17 | L9: 64600.21 | M9: 167456.27 | N9: 170727.12 | O9: 164917.45
A10: Total Paper Cost (%) | B10: 3.78 | D10: 3.41 | E10: 3.38 | F10: 3.87 | G10: 3.4 | H10: 3.37 | I10: 3.35 | J10: 3.46 | K10: 3.91 | L10: 3.19 | M10: 3.3 | N10: 5.22 | O10: 3.39
A11: Total Paper Cost ($) | B11: 25892.1 | D11: 5381.72 | E11: 3922.02 | F11: 22604.46 | G11: 1937.02 | H11: 5522.94 | I11: 5411.79 | J11: 5840.02 | K11: 23021.26 | L11: 2062 | M11: 5528.16 | N11: 8909.67 | O11: 5580.4
A12: Completed Waste | B12: 0.1 | D12: 0.12 | E12: 0.08 | F12: 0.09 | G12: 0.03 | H12: 0.08 | I12: 0.16 | J12: 0.17 | K12: 0.13 | L12: 0.12 | M12: 0.13 | N12: 0.16 | O12: 0.13
A13: Raw Waste | B13: 0.12 | D13: 0.14 | E13: 0.16 | F13: 0.17 | G13: 0.14 | H13: 0.14 | I13: 0.18 | J13: 0.14 | K13: 0.14 | L13: 0.33 | M13: 0.15 | N13: 0.21 | O13: 0.19
A14: Condiments | B14: 1.75 | D14: 1.77 | E14: 1.77 | F14: 1.84 | G14: 1.84 | H14: 2.33 | I14: 2.14 | J14: 2.68 | K14: 2.36 | L14: 2.31 | M14: 2.25 | N14: 1.69 | O14: 1.73
A15: Emp Mgr Meals | B15: 0.17 | D15: 0.22 | E15: 0.24 | F15: 0.2 | G15: 0.22 | H15: 0.23 | I15: 0.27 | J15: 0.23 | K15: 0.21 | L15: 0.27 | M15: 0.25 | N15: 0.23 | O15: 0.23
A16: Variance Stat | B16: 1.71 | D16: 3.25 | E16: 0.93 | F16: 2.05 | G16: -0.01 | H16: 2.05 | I16: 1.12 | J16: 1.39 | K16: 1.53 | L16: 0 | M16: 1.52 | N16: 2.45 | O16: 2.75
A17: Unexplained | B17: -0.14 | D17: -0.2 | E17: 0.19 | F17: -0.17 | G17: -0.12 | H17: -0.11 | I17: -0.17 | J17: -0.16 | K17: -0.15 | L17: -0.16 | M17: -0.16 | N17: -0.15 | O17: -0.13
A18: Food Over Base | B18: 3.71 | D18: 5.3 | E18: 3.37 | F18: 4.18 | G18: 2.1 | H18: 4.72 | I18: 3.7 | J18: 4.45 | K18: 4.22 | L18: 2.87 | M18: 4.14 | N18: 4.59 | O18: 4.9
A19: Base Food | B19: 22.427055 | D19: 22.822266 | E19: 23.268538 | F19: 22.927329 | G19: 23.14007 | H19: 22.917337 | I19: 22.889147 | J19: 22.928433 | K19: 22.868198 | L19: 22.825142 | M19: 23.203099 | N19: 23.168185 | O19: 23.073277
A20: Discounts/Coupons | B20: 1.36 | D20: 1.42 | E20: 1.37 | F20: 1.38 | G20: 1.37 | H20: 1.35 | I20: 1.36 | J20: 1.43 | K20: 1.4 | L20: 1.61 | M20: 1.54 | N20: 1.73 | O20: 1.72
A21: Total Food Cost | B21: 27.5 | D21: 29.54 | E21: 28 | F21: 28.49 | G21: 26.62 | H21: 28.98 | I21: 27.95 | J21: 28.8 | K21: 28.49 | L21: 27.3 | M21: 28.89 | N21: 29.49 | O21: 29.7
A22: Food
A23: Beginning Inventory (+) | B23: 37688.65 | D23: 37485.31 | E23: 35483.56 | F23: 41313.01 | G23: 26807.94 | H23: 34670.31 | I23: 28925.83 | J23: 31616.56 | K23: 26807.94 | L23: 21694.52 | M23: 31126.39 | N23: 34139.71 | O23: 33008.13
A24: Purchases | B24: 195860.03 | D24: 41596.75 | E24: 39813.72 | F24: 157711.12 | G24: 18078.03 | H24: 39459.94 | I24: 43765.17 | J24: 43252.15 | K24: 169403.84 | L24: 21840.17 | M24: 47402.36 | N24: 43779.83 | O24: 43411.54
A25: Adjustments (+/-) | B25: -527.81 | D25: -615.64 | E25: 0 | F25: -615.64 | G25: 0 | H25: 0 | I25: -9.4 | J25: 0 | K25: -15.29 | L25: -2.35 | M25: -248.45 | N25: 0 | O25: 0
A26: Transfers | B26: 1445.72 | D26: 0 | E26: 0 | F26: -29.35 | G26: -73.85 | H26: -2160.04 | I26: 144.83 | J26: 118.71 | K26: -1911.57 | L26: 0 | M26: 208.32 | N26: 726.2 | O26: -214.9
A27: Promotions (-) | B27: 4752.7 | D27: 1455.46 | E27: 1046.84 | F27: 5197.15 | G27: 540.83 | H27: 1623.76 | I27: 1164.63 | J27: 1374.22 | K27: 4816.29 | L27: 418.19 | M27: 1126.85 | N27: 1072.19 | O27: 1022.15
A28: Ending Inventory (-) | B28: 41313.01 | D28: 30398.09 | E28: 41744.55 | F28: 26807.94 | G28: 29093.89 | H28: 22838.91 | I28: 26539.62 | J28: 24966.05 | K28: 21694.52 | L28: 25478.89 | M28: 28991.13 | N28: 27224.78 | O28: 26207.01
A29: Total | B29: 188400.88 | D29: 46612.86 | E29: 32505.88 | F29: 166374.04 | G29: 15177.41 | H29: 47507.54 | I29: 45122.17 | J29: 48647.15 | K29: 167774.11 | L29: 17635.26 | M29: 48370.64 | N29: 50348.78 | O29: 48975.61
A30: Paper
A31: Beginning Inventory (+) | B31: 9283.8 | D31: 10827.4 | E31: 11046.25 | F31: 11887.84 | G31: 8660.56 | H31: 9154.6 | I31: 8936.35 | J31: 9421.47 | K31: 8660.56 | L31: 6926.53 | M31: 8401.2 | N31: 9835.84 | O31: 6889.41
A32: Purchases | B32: 28505.49 | D32: 5039.63 | E32: 4616.15 | F32: 19786.61 | G32: 1775.17 | H32: 4775.45 | I32: 5343.93 | J32: 6388.59 | K32: 21659.64 | L32: 2914.37 | M32: 6431.05 | N32: 5323.4 | O32: 7011.96
A33: Adjustments (+/-) | B33: 0 | D33: 0 | E33: 0 | F33: 0 | G33: 0 | H33: 0 | I33: 0 | J33: 0 | K33: 0 | L33: 0 | M33: 0 | N33: 0 | O33: 0
A34: Transfers | B34: 320.53 | D34: 0 | E34: 0 | F34: -54.36 | G34: -43.93 | H34: -26.19 | I34: 9.4 | J34: -39.57 | K34: -56.35 | L34: 0 | M34: 4.17 | N34: 0 | O34: -22.03
A35: Promotions (-) | B35: 329.89 | D35: 100.65 | E35: 71.09 | F35: 355.07 | G35: 38.39 | H35: 105.51 | I35: 78.33 | J35: 86.8 | K35: 316.06 | L35: 27.78 | M35: 78.95 | N35: 76.97 | O35: 73.64
A36: Ending Inventory (-) | B36: 11887.84 | D36: 10384.66 | E36: 11669.29 | F36: 8660.56 | G36: 8416.4 | H36: 8275.41 | I36: 8799.56 | J36: 9843.67 | K36: 6926.53 | L36: 7751.12 | M36: 9229.31 | N36: 6172.6 | O36: 8221.31
A37: Total | B37: 25892.1 | D37: 5381.72 | E37: 3922.02 | G37: 1937.02 | H37: 5522.94 | I37: 5411.79 | J37: 5840.02 | L37: 2062 | M37: 5528.16 | N37: 8909.67 | O37: 5584.4
A40: Notes
L41: 2/28/26 | M41: 46088 | N41: 46095 | O41: 46102
L42: EOM | M42: Count Day | N42: Count Day | O42: Count Day
L43: 588965.17 | M43: 155307.49 | N43: 171161.79 | O43: 172406.38
L44: 3.91 | M44: 3.25 | N44: 5.15 | O44: 5.23
L45: 23021.26 | M45: 5047.29 | N45: 8811.75 | O45: 9015.19
L46: 0.13 | M46: 0.13 | N46: 0.14 | O46: 0.14
L47: 0.14 | M47: 0.21 | N47: 0.21 | O47: 0.19
L48: 2.36 | M48: 2.23 | N48: 1.71 | O48: 1.64
L49: 0.21 | M49: 0.22 | N49: 0.2 | O49: 0.18
L50: 1.53 | M50: 1.57 | N50: 2.42 | O50: 2.36
L51: -0.15 | M51: -0.15 | N51: -0.15 | O51: -0.13
L52: 4.22 | M52: 4.21 | N52: 4.53 | O52: 4.38
L53: 22.868198 | M53: 22.979641 | N53: 23.23893 | O53: 23.059393
L54: 1.4 | M54: 1.5 | N54: 1.68 | O54: 1.69
... L70: 6926.53 | M70: 7567.17 | N70: 5451.53 | O70: 7484.35

Sheet 6972
A1: Location | B1: 6972 | C1: RGR Date | D1: =_xlfn.XLOOKUP(B1,'FC-Inv Setup'!A3:A22,'FC-Inv Setup'!I3:I22) -> 46063 | F1: Date Scheduled | H1: Start Time | L1: Validity | M1: Status
A2: Supervisor | B2: =_xlfn.XLOOKUP(B1,'FC-Inv Setup'!A3:A22,'FC-Inv Setup'!C3:C22) -> Robert Spencer | C2: FOB Risk | D2: =_xlfn.XLOOKUP(B1,'FC-Inv Setup'!A3:A22,'FC-Inv Setup'!K3:K22) -> Medium
A3: GM | B3: =_xlfn.XLOOKUP(B1,'FC-Inv Setup'!A3:A22,'FC-Inv Setup'!D3:D22) -> Nick Rice
A4: Counting Manager | B4: =_xlfn.XLOOKUP(B1,'FC-Inv Setup'!A3:A22,'FC-Inv Setup'!E3:E22) -> Beth
A5: Count Day | B5: =_xlfn.XLOOKUP(B1,'FC-Inv Setup'!A3:A22,'FC-Inv Setup'!J3:J22) -> Thursday
C6: Data N/A | D6: Data N/A
A7: Date | B7: Dec EOM | C7: 46023 | D7: 46030 | E7: 46037 | F7: 46044 | G7: 46051 | H7: 01/31/26% | I7: 46058 | J7: 46065 | K7: 46072 | L7: 46079 | M7: 2/28/26 | N7: 46086 | O7: 46093 | P7: 46100 | Q7: 46107 | R7: 3/31/26 | S7: 46114 | T7: 46121 | U7: 46128 | V7: 46135 | W7: 46142 | X7: 4/30/26
A8: Cycle | B8: EOM | F8: Count Day | G8: Count Day | H8: EOM | I8: Count Day | J8: Count Day | K8: Count Day | L8: Count Day | M8: EOM | N8: Count Day | O8: Count Day | P8: Count Day | Q8: Count Day | R8: EOM | S8: Count Day | T8: Count Day | U8: Count Day | V8: Count Day | W8: Count Day | X8: EOM
A9: Product Net Sales | B9: 610699.99 | F9: 140433.35 | G9: 113098.58 | H9: 498161.97 | I9: 86537.26 | J9: 146863.41 | K9: 146245.03 | L9: 153012.59 | M9: 520258.68 | N9: 95351.62 | O9: 152391.33 | P9: 153452.98
A10: Total Paper Cost (%) | B10: 4.2 | F10: 3.34 | G10: 3.35 | H10: 3.91 | I10: 3.1 | J10: 3.35 | K10: 4.33 | L10: 3.22 | M10: 3.86 | N10: 3.42 | O10: 3.45 | P10: 3.41
A11: Total Paper Cost ($) | B11: 25680.71 | F11: 4692.68 | G11: 3790.32 | H11: 19460.17 | I11: 2686.87 | J11: 4917.62 | K11: 6337.63 | L11: 4927.89 | M11: 20096.56 | N11: 3259.4 | O11: 5254.31 | P11: 5227.44
A12: Completed Waste | B12: 0.19 | F12: 0.16 | G12: 0.19 | H12: 0.18 | I12: 0.16 | J12: 0.66 | K12: 0.16 | L12: 0.16 | M12: 0.19 | N12: 0.34 | O12: 0.26 | P12: 0.18
A13: Raw Waste | B13: 0.78 | F13: 0.76 | G13: 0.58 | H13: 0.81 | I13: 0.35 | J13: 5.61 | K13: 0.61 | L13: 0.51 | M13: 0.59 | N13: 0.7 | O13: 0.83 | P13: 0.66
A14: Condiments | B14: 1.82 | F14: 1.85 | G14: 1.66 | H14: 1.93 | I14: 1.96 | J14: 0.34 | K14: 2.36 | L14: 1.98 | M14: 3.18 | N14: 1.84 | O14: 1.28 | P14: 1.41
A15: Emp Mgr Meals | B15: 0.32 | F15: 0.4 | G15: 0.4 | H15: 0.4 | I15: 0.4 | J15: 11.42 | K15: 0.36 | L15: 0.4 | M15: 0.37 | N15: 0.36 | O15: 0.37 | P15: 0.36
A16: Variance Stat | B16: 1.78 | F16: 2.32 | G16: 1.97 | H16: 2.33 | I16: -0.39 | J16: 0.26 | K16: 2.17 | L16: 2 | M16: 4.42 | N16: 1.38 | O16: 0.64 | P16: 1.55
A17: Unexplained | B17: -0.06 | F17: -0.01 | G17: 0.06 | H17: -0.04 | I17: -0.64 | J17: 18.49 | K17: -0.02 | L17: -0.05 | M17: -0.02 | N17: 0.06 | O17: -0.05 | P17: 0.02
A18: Food Over Base | B18: 4.83 | F18: 5.48 | G18: 4.86 | H18: 5.61 | I18: 1.84 | J18: 22.869907 | K18: 5.64 | L18: 5 | M18: 8.73 | N18: 4.68 | O18: 3.33 | P18: 4.18
A19: Base Food | B19: 22.258831 | F19: 22.629538 | G19: 23.047351 | H19: 22.645419 | I19: 22.704551 | J19: 1 | K19: 22.665279 | L19: 22.634521 | M19: 22.701665 | N19: 22.662941 | O19: 22.86012 | P19: 22.786398
A20: Discounts/Coupons | B20: 1.18 | F20: 1.27 | G20: 1.24 | H20: 1.23 | I20: 1.21 | J20: 42.36 | K20: 1.17 | L20: 1.26 | M20: 1.17 | N20: 1.39 | O20: 1.41 | P20: 1.54
A21: Total Food Cost | B21: 28.27 | F21: 29.38 | G21: 29.14 | H21: 29.49 | I21: 25.76 | K21: 29.47 | L21: 28.9 | M21: 32.6 | N21: 28.73 | O21: 27.6 | P21: 28.5
A22: Food
A23: Beginning Inventory (+) | B23: 47190.12 | F23: 54587.6 | G23: 44139.63 | H23: 49486.59 | I23: 48777.12 | J23: 32573.4 | K23: 24108.96 | L23: 27759.68 | M23: 48777.12 | N23: 35101.86 | O23: 29286.17 | P23: 26838.13
A24: Purchases | B24: 176637.17 | F24: 26542.42 | G24: 36861.97 | H24: 150205.83 | I24: 0 | J24: 42258.33 | K24: 42195.39 | L24: 39504.76 | M24: 149439.3 | N24: 16924.21 | O24: 35289.81 | P24: 36750.97
A25: Adjustments (+/-) | B25: -16.76 | F25: 0 | G25: -536.52 | H25: -536.52 | I25: 0 | J25: -102.71 | K25: -22.07 | L25: 0 | M25: -136.56 | N25: 0 | O25: -9.54 | P25: -134.89
A26: Transfers | B26: 2091.03 | F26: 337.71 | G26: 403.38 | H26: 656.11 | I26: 6615.84 | J26: 7261.03 | K26: 393.62 | L26: 93.59 | M26: 10231.96 | N26: -255.21 | O26: 565.04 | P26: 454.53
A27: Promotions (-) | B27: 3713.79 | F27: 1214.62 | G27: 899.45 | H27: 4138.97 | I27: 707.2 | J27: 936.13 | K27: 1007.91 | L27: 1076.25 | M27: 3628.75 | N27: 699.83 | O27: 962.81 | P27: 766.93
A28: Ending Inventory (-) | B28: 49486.59 | F28: 38986.98 | G28: 47008.24 | H28: 48777.12 | I28: 32397.33 | J28: 18841.01 | K28: 22565.55 | L28: 22060.92 | M28: 35101.86 | N28: 23680.52 | O28: 22112.2 | P28: 19400.18
A29: Total | B29: 172701.18 | F29: 41266.14 | G29: 32960.77 | H29: 146895.92 | I29: 22288.43 | J29: 62212.91 | K29: 43102.44 | L29: 44220.86 | M29: 169581.2 | N29: 27390.51 | O29: 42056.47 | P29: 43741.63
A30: Paper
A31: Beginning Inventory (+) | B31: 6923.06 | F31: 7015.63 | G31: 7917.45 | H31: 6163.19 | I31: 6836.94 | J31: 4771.17 | K31: 6295.69 | L31: 5756.9 | M31: 6836.94 | N31: 5864.64 | O31: 6341.88 | P31: 6678.56
A32: Purchases | B32: 25031.64 | F32: 5043.07 | G32: 5021.3 | H32: 20779.69 | I32: 0 | J32: 5460.37 | K32: 5218.7 | L32: 5387.93 | M32: 18831.55 | N32: 3057.48 | O32: 4866.33 | P32: 5087.77
A33: Adjustments (+/-) | B33: 0 | F33: 0 | G33: -51.09 | H33: -51.09 | I33: 0 | J33: 0 | K33: 0 | L33: 0 | M33: 0 | N33: 0 | O33: 0 | P33: 0
A34: Transfers | B34: 160.81 | F34: -287.91 | G34: -296.64 | H34: -313.64 | I34: 197.06 | J34: 369.59 | K34: 0 | L34: 0 | M34: 542.36 | N34: -11.62 | O34: 57.51 | P34: 0
A35: Promotions (-) | B35: 271.6 | F35: 82.66 | G35: 61.22 | H35: 281.05 | I35: 49.86 | J35: 66.34 | K35: 68.31 | L35: 72.86 | M35: 249.64 | N35: 44.17 | O35: 64.92 | P35: 56.47
A36: Ending Inventory (-) | B36: 6163.19 | F36: 6995.44 | G36: 8739.49 | H36: 6836.94 | I36: 4297.27 | J36: 5617.17 | K36: 5108.46 | L36: 6144.09 | M36: 5864.64 | N36: 5606.94 | O36: 5946.5 | P36: 6482.42
A37: Total | B37: 25680.71 | F37: 4692.68 | G37: 3790.32 | H37: 19460.17 | I37: 2686.87 | J37: 4917.62 | K37: 6337.63 | L37: 4927.89 | M37: 20096.56 | N37: 3259.4 | O37: 5254.31 | P37: 5227.44
A40: Notes

Sheet 10422
A1: Location | B1: 10422 | C1: RGR Date | D1: =_xlfn.XLOOKUP(B1,'FC-Inv Setup'!A3:A22,'FC-Inv Setup'!I3:I22) -> 46051 | F1: Date Scheduled | I1: Start Time | M1: Validity | N1: Status
A2: Supervisor | B2: =_xlfn.XLOOKUP(B1,'FC-Inv Setup'!A3:A22,'FC-Inv Setup'!C3:C22) -> Ashley Podroza | C2: FOB Risk | D2: =_xlfn.XLOOKUP(B1,'FC-Inv Setup'!A3:A22,'FC-Inv Setup'!K3:K22) -> High
A3: GM | B3: =_xlfn.XLOOKUP(B1,'FC-Inv Setup'!A3:A22,'FC-Inv Setup'!D3:D22) -> Ashleyh Hegwer
A4: Counting Manager | B4: =_xlfn.XLOOKUP(B1,'FC-Inv Setup'!A3:A22,'FC-Inv Setup'!E3:E22) -> Ashley
A5: Count Day | B5: =_xlfn.XLOOKUP(B1,'FC-Inv Setup'!A3:A22,'FC-Inv Setup'!J3:J22) -> Saturday
C6: Data N/A | D6: Data N/A
A7: Date | B7: Dec EOM | C7: 46025 | D7: 46032 | E7: 46039 | F7: 46046 | G7: 46053 | H7: 46053 | I7: 46060 | J7: 46067 | K7: 46074 | L7: 46081 | M7: 2/28/26 | N7: 46088 | O7: 46095 | P7: 46102 | Q7: 46109 | R7: 3/31/26 | S7: 46116 | T7: 46123 | U7: 46130 | V7: 46137 | W7: 4/30/26
A8: Cycle | B8: EOM | E8: Count Day | F8: Count Day | G8: Count Day | H8: EOM | I8: Count Day | J8: Count Day | K8: Count Day | L8: Count Day | M8: EOM | N8: Count Day | O8: Count Day | P8: Count Day | Q8: Count Day | R8: Count Day | S8: EOM | T8: Count Day | U8: Count Day | V8: Count Day | W8: EOM
A9: Product Net Sales | B9: 404646.58 | E9: 88847.94 | F9: 76371.55 | G9: 62172.89 | H9: 326528.93 | I9: 81699.74 | J9: 93483.49 | K9: 98883.53 | L9: 101436.11 | M9: 337651.74 | N9: 88666.72 | O9: 104333.98 | P9: 117772.86
A10: Total Paper Cost (%) | B10: 3.49 | E10: 2.64 | F10: 3.11 | G10: 7.35 | H10: 3.96 | I10: 3.21 | J10: 3.17 | K10: 3.189 | L10: 4.27 | M10: 3.52 | N10: 3.05 | O10: 3.18 | P10: 3.21
A11: Total Paper Cost ($) | B11: 14118.28 | E11: 2342.13 | F11: 2377.5 | G11: 4572.36 | H11: 12930.41 | I11: 2621.04 | J11: 2966.64 | K11: 3141.14 | L11: 4332.2 | M11: 11871.7 | N11: 2703.24 | O11: 33156.73 | P11: 3782.14
A12: Completed Waste | B12: 0.25 | E12: 0.18 | F12: 0.36 | G12: 0.3 | H12: 0.3 | I12: 0.21 | J12: 0.23 | K12: 0.32 | L12: 0.2 | M12: 0.25 | N12: 0.31 | O12: 0.21 | P12: 0.21
A13: Raw Waste | B13: 0.13 | E13: 0.13 | F13: 0.09 | G13: 0.13 | H13: 0.11 | I13: 0.26 | J13: 0.16 | K13: 0.18 | L13: 0.13 | M13: 0.18 | N13: 0.35 | O13: 0.25 | P13: 0.27
A14: Condiments | B14: 1.88 | E14: 1.62 | F14: 1.99 | G14: 2.3 | H14: 1.96 | I14: 1.96 | J14: 2 | K14: 1.95 | L14: 1.83 | M14: 1.94 | N14: 1.97 | O14: 1.76 | P14: 1.67
A15: Emp Mgr Meals | B15: 0.14 | E15: 0.23 | F15: 0.16 | G15: 0.23 | H15: 0.19 | I15: 0.13 | J15: 0.15 | K15: 0.14 | L15: 0.12 | M15: 0.13 | N15: 0.15 | O15: 0.13 | P15: 0.12
A16: Variance Stat | B16: 1.77 | E16: 1.84 | F16: 3.42 | G16: 5.4 | H16: 2.72 | I16: 1.51 | J16: 3.63 | K16: 3.13 | L16: 2.19 | M16: 1.82 | N16: 3.28 | O16: 3.27 | P16: 2.96
A17: Unexplained | B17: -0.04 | E17: -3.54 | F17: -0.01 | G17: -0.02 | H17: -0.06 | I17: 0.09 | J17: -0.06 | K17: 0.01 | L17: -0.04 | M17: 0 | N17: -0.03 | O17: -0.03 | P17: -0.02
A18: Food Over Base | B18: 4.13 | E18: 0.46 | F18: 6.01 | G18: 8.34 | H18: 5.22 | I18: 4.16 | J18: 6.11 | K18: 5.73 | L18: 4.43 | M18: 4.32 | N18: 6.03 | O18: 5.59 | P18: 5.21
A19: Base Food | B19: 22.806186 | E19: 23.269135 | F19: 23.21359 | G19: 23.843993 | H19: 23.350791 | I19: 23.306814 | J19: 23.134514 | K19: 23.092778 | L19: 23.00912 | M19: 23.141136 | N19: 23.299204 | O19: 23.342215 | P19: 23.197683
A20: Discounts/Coupons | B20: 1.18 | E20: 1.22 | F20: 1.26 | G20: 1.36 | H20: 1.25 | I20: 1.18 | J20: 1.19 | K20: 1.23 | L20: 1.33 | M20: 1.24 | N20: 1.36 | O20: 1.42 | P20: 1.35
A21: Total Food Cost | B21: 28.11 | E21: 24.95 | F21: 30.48 | G21: 33.55 | H21: 29.82 | I21: 28.65 | J21: 30.43 | K21: 30.05 | L21: 28.77 | M21: 28.71 | N21: 30.68 | O21: 30.35 | P21: 29.75
A22: Food
A23: Beginning Inventory (+) | B23: 23615.85 | E23: 18596 | F23: 22363.08 | G23: 26552.28 | H23: 29533.52 | I23: 21668.8 | J23: 20756.26 | K23: 20207.3 | L23: 22869.64 | M23: 21668.8 | N23: 20307.15 | O23: 22789.78 | P23: 21570.96
A24: Purchases | B24: 124119.79 | E24: 22739.59 | F24: 25756.55 | G24: 16890.06 | H24: 92958.96 | I24: 18832.28 | J24: 25099.76 | K24: 28247.05 | L24: 27618.67 | M24: 99797.76 | N24: 24892.88 | O24: 26467.56 | P24: 28540.27
A25: Adjustments (+/-) | B25: 0 | E25: 0 | F25: 0 | G25: 0 | H25: 0 | I25: 0 | J25: 0 | K25: 0 | L25: 0 | M25: 0 | N25: 0 | O25: 0 | P25: 0
A26: Transfers | B26: -1008.03 | E26: 164.45 | F26: 0 | G26: -313.26 | H26: -160.88 | I26: 68.13 | J26: -1143.21 | K26: -121.81 | L26: -16.16 | M26: -1105.9 | N26: -191.31 | O26: -150.04 | P26: 445.51
A27: Promotions (-) | B27: 3462.12 | E27: 861.55 | F27: 899.88 | G27: 599.83 | H27: 3283.97 | I27: 681.05 | J27: 824.36 | K27: 955.21 | L27: 979.29 | M27: 3127.41 | N27: 770.77 | O27: 779.46 | P27: 942.48
A28: Ending Inventory (-) | B28: 29533.52 | E28: 18471.9 | F28: 23939.68 | G28: 21668.8 | H28: 21668.8 | I28: 16483.46 | J28: 15437.22 | K28: 17658.32 | L28: 20307.15 | M28: 20307.15 | N28: 17031.65 | O28: 16663.06 | P28: 14572.22
A29: Total | B29: 113731.97 | E29: 22166.59 | F29: 23280.06 | G29: 20860.45 | H29: 97378.84 | I29: 23404.7 | J29: 28451.24 | K29: 29719 | L29: 29185.72 | M29: 96926.1 | N29: 27206.3 | O29: 31664.79 | P29: 35042.04
A30: Paper
A31: Beginning Inventory (+) | B31: 5432.63 | E31: 5437.25 | F31: 5944.58 | G31: 7783.86 | H31: 6127.64 | I31: 5592.36 | J31: 4720.09 | K31: 5119 | L31: 5508.73 | M31: 5592.36 | N31: 4308.26 | O31: 4871.77 | P31: 5668.16
A32: Purchases | B32: 15273.97 | E32: 2449.97 | F32: 3799.8 | G32: 2420.14 | H32: 12025.19 | I32: 1466.22 | J32: 3327.34 | K32: 3118.55 | L32: 3183.58 | M32: 11095.69 | N32: 2922.2 | O32: 3622.28 | P32: 4222.9
A33: Adjustments (+/-) | B33: 0 | E33: 0 | F33: 0 | G33: 0 | H33: 0 | I33: 0 | J33: 0 | K33: 0 | L33: 0 | M33: 0 | N33: 0 | O33: 0 | P33: 0
A34: Transfers | B34: -229.91 | E34: 121.93 | F34: 395.52 | G34: 0 | H34: 585.97 | I34: -43.93 | J34: -263.29 | K34: 6.44 | L34: 14.36 | M34: -292.86 | N34: 0.04 | O34: 17.96 | P34: 12.61
A35: Promotions (-) | B35: 230.77 | E35: 55.83 | F35: 61.01 | G35: 39.28 | H35: 216.04 | I35: 47.85 | J35: 57.23 | K35: 65.84 | L35: 66.21 | M35: 215.24 | N35: 51.75 | O35: 56.23 | P35: 68.99
A36: Ending Inventory (-) | B36: 6127.64 | E36: 5611.19 | F36: 7701.39 | G36: 5592.36 | H36: 5592.36 | I36: 4345.77 | J36: 4760.27 | K36: 5037.01 | L36: 4308.26 | M36: 4308.26 | N36: 4475.51 | O36: 5140.06 | P36: 6052.53
A37: Total | B37: 14118.28 | E37: 2342.13 | F37: 2377.5 | G37: 4572.36 | H37: 12930.41 | I37: 2621.04 | J37: 2966.64 | K37: 3141.14 | L37: 4332.2 | M37: 11871.7 | N37: 2703.24 | O37: 3315.73 | P37: 3782.14
A40: Notes

Sheet 10915
A1: Location | B1: 10915 | C1: RGR Date | D1: =_xlfn.XLOOKUP(B1,'FC-Inv Setup'!A3:A22,'FC-Inv Setup'!I3:I22) -> 46071 | F1: Date Scheduled | H1: Start Time | L1: Validity | M1: Status
A2: Supervisor | B2: =_xlfn.XLOOKUP(B1,'FC-Inv Setup'!A3:A22,'FC-Inv Setup'!C3:C22) -> Steven Vaughn | C2: FOB Risk | D2: =_xlfn.XLOOKUP(B1,'FC-Inv Setup'!A3:A22,'FC-Inv Setup'!K3:K22) -> Medium
A3: GM | B3: =_xlfn.XLOOKUP(B1,'FC-Inv Setup'!A3:A22,'FC-Inv Setup'!D3:D22) -> Caleb Nunnelley
A4: Counting Manager | B4: =_xlfn.XLOOKUP(B1,'FC-Inv Setup'!A3:A22,'FC-Inv Setup'!E3:E22) -> Caitlin
A5: Count Day | B5: =_xlfn.XLOOKUP(B1,'FC-Inv Setup'!A3:A22,'FC-Inv Setup'!J3:J22) -> Wednesday
C6: Data N/A | D6: Data N/A
A7: Date | B7: Dec EOM | C7: 46029 | D7: 46036 | E7: 46043 | F7: 46050 | G7: 46053 | H7: 46057 | I7: 46064 | J7: 46071 | K7: 46078 | L7: 2/28/26 | M7: 46085 | N7: 46092 | O7: 46099 | P7: 46106 | Q7: 3/31/26 | R7: 46113 | S7: 46120 | T7: 46127 | U7: 46134 | V7: 46141 | W7: 4/30/26
A8: Cycle | B8: EOM | E8: Count Day | F8: Count Day | G8: EOM | H8: Count Day | I8: Count Day | J8: Count Day | K8: Count Day | L8: EOM | M8: Count Day | N8: Count Day | O8: Count Day | P8: Count Day | Q8: EOM | R8: Count Day | S8: Count Day | T8: Count Day | U8: Count Day | V8: Count Day | W8: EOM
A9: Product Net Sales | B9: 393680.36 | E9: 89759.88 | F9: 69761.65 | G9: 330061.12 | H9: 46830.58 | I9: 95149.29 | J9: 92824.41 | K9: 101926.92 | L9: 348339.26 | M9: 52090.71 | N9: 105609.13 | O9: 102967.21 | P9: 100821.25
A10: Total Paper Cost (%) | B10: 5.96 | E10: 3.53 | F10: 5.57 | G10: 4.01 | H10: 3.64 | I10: 3.61 | J10: 3.58 | K10: 5.45 | L10: 4.14 | M10: 3.35 | N10: 3.44 | O10: 3.49 | P10: 3.49
A11: Total Paper Cost ($) | B11: 23444.88 | E11: 3166.79 | F11: 3884.64 | G11: 13250.66 | H11: 1706.73 | I11: 3430.28 | J11: 3326.33 | K11: 5558.5 | L11: 14410.4 | M11: 1744.27 | N11: 3634.15 | O11: 3588.85 | P11: 3516.21
A12: Completed Waste | B12: 0.31 | E12: 0.3 | F12: 0.34 | G12: 0.29 | H12: 0.36 | I12: 0.2 | J12: 0.25 | K12: 0.26 | L12: 0.26 | M12: 0.3 | N12: 0.31 | O12: 0.31 | P12: 0.3
A13: Raw Waste | B13: 0.74 | E13: 0.86 | F13: 0.98 | G13: 0.87 | H13: 0.83 | I13: 0.83 | J13: 0.89 | K13: 0.74 | L13: 0.76 | M13: 0.76 | N13: 0.75 | O13: 0.64 | P13: 0.78
A14: Condiments | B14: 2.15 | E14: 1.86 | F14: 2.12 | G14: 2.07 | H14: 2.04 | I14: 2.04 | J14: 1.91 | K14: 2.66 | L14: 2.13 | M14: 2.13 | N14: 1.6 | O14: 1.72 | P14: 1.92
A15: Emp Mgr Meals | B15: 0.56 | E15: 0.55 | F15: 0.6 | G15: 0.57 | H15: 0.5 | I15: 0.45 | J15: 0.61 | K15: 0.4 | L15: 0.47 | M15: 0.37 | N15: 0.39 | O15: 0.43 | P15: 0.44
A16: Variance Stat | B16: 0.3 | E16: 0.88 | F16: 0.06 | G16: 0.75 | H16: -0.01 | I16: -0.03 | J16: 0.67 | K16: 0.7 | L16: 0.53 | M16: -0.05 | N16: 1.16 | O16: 1.28 | P16: 0.87
A17: Unexplained | B17: -0.01 | E17: -0.02 | F17: 0.01 | G17: -0.02 | H17: -0.04 | I17: -0.02 | J17: 0.13 | K17: -0.02 | L17: -0.04 | M17: -0.05 | N17: -0.04 | O17: -0.02 | P17: 0.02
A18: Food Over Base | B18: 4.05 | E18: 4.43 | F18: 4.11 | G18: 4.53 | H18: 3.68 | I18: 3.47 | J18: 4.46 | K18: 4.74 | L18: 4.11 | M18: 3.46 | N18: 4.17 | O18: 4.36 | P18: 4.33
A19: Base Food | B19: 23.431864 | E19: 23.736005 | F19: 24.158944 | G19: 23.811547 | H19: 23.892621 | I19: 23.789787 | J19: 23.688692 | K19: 23.607717 | L19: 23.653208 | M19: 23.600144 | N19: 23.807819 | O19: 23.472676 | P19: 23.463611
A20: Discounts/Coupons | B20: 1.44 | E20: 1.55 | F20: 1.69 | G20: 1.59 | H20: 1.54 | I20: 1.52 | J20: 1.46 | K20: 1.57 | L20: 1.54 | M20: 1.69 | N20: 1.68 | O20: 1.84 | P20: 1.77
A21: Total Food Cost | B21: 28.92 | E21: 29.71 | F21: 29.96 | G21: 29.94 | H21: 29.11 | I21: 28.78 | J21: 29.61 | K21: 29.91 | L21: 29.31 | M21: 28.75 | N21: 29.66 | O21: 29.67 | P21: 29.56
A22: Food
A23: Beginning Inventory (+) | B23: 29007.79 | E23: 22338.7 | F23: 18704.95 | G23: 19972.37 | H23: 18139.64 | I23: 19411.87 | J23: 16111.55 | K23: 23876.56 | L23: 18139.64 | M23: 17951.23 | N23: 20094.72 | O23: 22716.2 | P23: 24186.19
A24: Purchases | B24: 112263.8 | E24: 20842.95 | F24: 25858.36 | G24: 102997.94 | H24: 12218.9 | I24: 27634.32 | J24: 31029.66 | K24: 26559.04 | L24: 110404.46 | M24: 13687.68 | N24: 30587.38 | O24: 29836.74 | P24: 23483.11
A25: Adjustments (+/-) | B25: -9.1 | E25: 0 | F25: 0 | G25: 0 | H25: 0 | I25: 0 | J25: 0 | K25: 0 | L25: 0 | M25: 0 | N25: 0 | O25: -35.98 | P25: 0
A26: Transfers | B26: -3534.5 | E26: -493.42 | F26: 46.95 | G26: -2190.33 | H26: -1853.71 | I26: -4074.59 | J26: 1625.2 | K26: -429.56 | L26: -5043.21 | M26: -268.3 | N26: -429.89 | O26: -997.96 | P26: -215.25
A27: Promotions (-) | B27: 3901.99 | E27: 1049.55 | F27: 771.08 | G27: 3830.48 | H27: 583.62 | I27: 952.39 | J27: 896.52 | K27: 1009.79 | L27: 3451.21 | M27: 446.07 | N27: 896.47 | O27: 760.26 | P27: 851.4
A28: Ending Inventory (-) | B28: 19972.37 | E28: 14966.85 | F28: 22937.2 | G28: 18139.64 | H28: 14287.22 | I28: 14638.49 | J28: 20384.25 | K28: 18508.36 | L28: 17951.23 | M28: 15946.43 | N28: 18034.72 | O28: 20208.17 | P28: 16799.52
A29: Total | B29: 113853.62 | E29: 26671.83 | F29: 20901.98 | G29: 98809.87 | H29: 13633.98 | I29: 27380.71 | J29: 27485.63 | K29: 30487.9 | L29: 102098.44 | M29: 14978.11 | N29: 31321.01 | O29: 30550.57 | P29: 29803.13
A30: Paper
A31: Beginning Inventory (+) | B31: 14970.12 | E31: 7580.51 | F31: 7821.49 | G31: 6114.2 | H31: 7652.93 | I31: 7979.08 | J31: 8009.41 | K31: 9013.41 | L31: 7652.93 | M31: 7474.29 | N31: 8100.6 | O31: 8257.33 | P31: 9332.46
A32: Purchases | B32: 15087.3 | E32: 3258.39 | F32: 3861.83 | G32: 15524.41 | H32: 1612 | I32: 3383.73 | J32: 3946.95 | K32: 3572.03 | L32: 14802.69 | M32: 1961.26 | N32: 3492.57 | O32: 4279.23 | P32: 3061.42
A33: Adjustments (+/-) | B33: 0 | E33: 0 | F33: 0 | G33: 0 | H33: 0 | I33: 0 | J33: 0 | K33: 0 | L33: 0 | M33: 0 | N33: 0 | O33: 0 | P33: 0
A34: Transfers | B34: -202.02 | E34: -216.99 | F34: -69.59 | G34: -450.79 | H34: -1885.5 | I34: -198.76 | J34: 35.7 | K34: -64.53 | L34: -316.88 | M34: -30.15 | N34: -91.79 | O34: -3.36 | P34: -41.88
A35: Promotions (-) | B35: 296.32 | E35: 76.11 | F35: 58.13 | G35: 284.24 | H35: 40.75 | I35: 70.2 | J35: 67.24 | K35: 76.29 | L35: 254.05 | M35: 31.6 | N35: 66.97 | O35: 56.03 | P35: 67.36
A36: Ending Inventory (-) | B36: 6114.2 | E36: 7379.01 | F36: 7670.96 | G36: 7652.93 | H36: 7485.66 | I36: 7663.57 | J36: 8598.48 | K36: 6886.12 | L36: 7474.29 | M36: 7629.51 | N36: 7800.27 | O36: 8888.32 | P36: 8768.43
A37: Total | B37: 23444.88 | E37: 3166.79 | F37: 3884.64 | G37: 13250.66 | H37: 1706.73 | I37: 3430.28 | J37: 3326.33 | K37: 5558.5 | L37: 14410.4 | M37: 1744.27 | N37: 3634.15 | O37: 3588.85 | P37: 3516.21
A40: Notes

Sheet 11657
A1: Location | B1: 11657 | C1: RGR Date | D1: =_xlfn.XLOOKUP(B1,'FC-Inv Setup'!A3:A22,'FC-Inv Setup'!I3:I22) -> 46134 | F1: Date Scheduled | H1: Start Time | L1: Validity | M1: Status
A2: Supervisor | B2: =_xlfn.XLOOKUP(B1,'FC-Inv Setup'!A3:A22,'FC-Inv Setup'!C3:C22) -> Amanda Estrada | C2: FOB Risk | D2: =_xlfn.XLOOKUP(B1,'FC-Inv Setup'!A3:A22,'FC-Inv Setup'!K3:K22) -> Medium
A3: GM | B3: =_xlfn.XLOOKUP(B1,'FC-Inv Setup'!A3:A22,'FC-Inv Setup'!D3:D22) -> Jessie Hiatt
A4: Counting Manager | B4: =_xlfn.XLOOKUP(B1,'FC-Inv Setup'!A3:A22,'FC-Inv Setup'!E3:E22) -> Norma
A5: Count Day | B5: =_xlfn.XLOOKUP(B1,'FC-Inv Setup'!A3:A22,'FC-Inv Setup'!J3:J22) -> Thursday
C6: Data N/A | D6: Data N/A
A7: Date | B7: Dec EOM | C7: 46030 | D7: 46249 | E7: 46044 | F7: 46051 | G7: 01/31/26% | H7: 46058 | I7: 46065 | J7: 46072 | K7: 46079 | L7: 2/28/26 | M7: 46086 | N7: 46093 | O7: 46100 | P7: 46107 | Q7: 3/31/26 | R7: 46114 | S7: 46121 | T7: 46128 | U7: 46135 | V7: 4/30/26 | W7: 4/30/26
A8: Cycle | B8: EOM | E8: Count Day | F8: Count Day | G8: EOM | H8: Count Day | I8: Count Day | J8: Count Day | K8: Count Day | L8: EOM | M8: Count Day | N8: Count Day | O8: Count Day | P8: Count Day | Q8: EOM | R8: Count Day | S8: Count Day | T8: Count Day | U8: Count Day | V8: Count Day | W8: EOM
A9: Product Net Sales | E9: 85636.45 | F9: 58894.94
A10: Total Paper Cost (%) | E10: 3.33 | F10: 5.69
A11: Total Paper Cost ($) | E11: 2851.13 | F11: 3350.32
A12: Completed Waste | E12: 0.47 | F12: 0.67
A13: Raw Waste | E13: 0.67 | F13: 1.02
A14: Condiments | E14: 3.92 | F14: 2.29
A15: Emp Mgr Meals | E15: 0.25 | F15: 0.2
A16: Variance Stat | E16: 3.66 | F16: 3.31
A17: Unexplained | E17: -0.13 | F17: -0.2
A18: Food Over Base | E18: 8.84 | F18: 7.29
A19: Base Food | E19: 23.065992 | F19: 23.392501
A20: Discounts/Coupons | E20: 1.28 | F20: 1.28
A21: Total Food Cost | E21: 33.19 | F21: 31.97
A22: Food
A23: Beginning Inventory (+) | E23: 24224.57 | F23: 22034.16
A24: Purchases | E24: 22165 | F24: 20946.81
A25: Adjustments (+/-) | E25: 0 | F25: 0
A26: Transfers | E26: -11.74 | F26: 30.89
A27: Promotions (-) | E27: 576.12 | F27: 368.4
A28: Ending Inventory (-) | E28: 17382.37 | F28: 23816.29
A29: Total | E29: 28419.34 | F29: 18827.17
A30: Paper
A31: Beginning Inventory (+) | E31: 12664.92 | F31: 12201.75
A32: Purchases | E32: 2007.63 | F32: 2378
A33: Adjustments (+/-) | E33: 0 | F33: 0
A34: Transfers | E34: 0 | F34: 87.92
A35: Promotions (-) | E35: 48.61 | F35: 29.97
A36: Ending Inventory (-) | E36: 11772.82 | F36: 11287.37
A37: Total | E37: 2851.13 | F37: 3350.32
A40: Notes

Sheet 13113
A1: Location | B1: 13113 | C1: RGR Date | D1: =_xlfn.XLOOKUP(B1,'FC-Inv Setup'!A3:A22,'FC-Inv Setup'!I3:I22) -> 46183 | F1: Date Scheduled | H1: Start Time | L1: Validity | M1: Status
A2: Supervisor | B2: =_xlfn.XLOOKUP(B1,'FC-Inv Setup'!A3:A22,'FC-Inv Setup'!C3:C22) -> Ashley Podroza | C2: FOB Risk | D2: =_xlfn.XLOOKUP(B1,'FC-Inv Setup'!A3:A22,'FC-Inv Setup'!K3:K22) -> High
A3: GM | B3: =_xlfn.XLOOKUP(B1,'FC-Inv Setup'!A3:A22,'FC-Inv Setup'!D3:D22) -> Chris Abbey
A4: Counting Manager | B4: =_xlfn.XLOOKUP(B1,'FC-Inv Setup'!A3:A22,'FC-Inv Setup'!E3:E22) -> Josh
A5: Count Day | B5: =_xlfn.XLOOKUP(B1,'FC-Inv Setup'!A3:A22,'FC-Inv Setup'!J3:J22) -> Tuesday
C6: Data N/A | D6: Data N/A
A7: Date | B7: Dec EOM | C7: 46028 | D7: 46035 | E7: 46042 | F7: 46049 | G7: 01/31/26% | H7: 46056 | I7: 46063 | J7: 46070 | K7: 46077 | L7: 2/28/26 | M7: 46084 | N7: 46091 | O7: 46098 | P7: 46105 | Q7: 3/31/26 | R7: 4/7/26 | S7: 4/14/26 | T7: 4/21/26 | U7: 4/28/26 | V7: 4/30/26 | W7: 4/30/26
A8: Cycle | B8: EOM | E8: Count Day | F8: Count Day | G8: EOM | H8: Count Day | I8: Count Day | J8: Count Day | K8: Count Day | L8: EOM | M8: Count Day | N8: Count Day | O8: Count Day | P8: Count Day | Q8: EOM | R8: Count Day | S8: Count Day | T8: Count Day | U8: Count Day | V8: Count Day | W8: EOM
A9: Product Net Sales | E9: 71491.7 | F9: 48328.37
A10: Total Paper Cost (%) | E10: 3.07 | F10: 3.18
A11: Total Paper Cost ($) | E11: 2194.83 | F11: 1537.64
A12: Completed Waste | E12: 0.3 | F12: 0.33
A13: Raw Waste | E13: 0.53 | F13: 0.57
A14: Condiments | E14: 1.85 | F14: 2.44
A15: Emp Mgr Meals | E15: 0.21 | F15: 0.24
A16: Variance Stat | E16: 0.7 | F16: 6.3
A17: Unexplained | E17: -0.03 | F17: 0
A18: Food Over Base | E18: 3.56 | F18: 9.88
A19: Base Food | E19: 23.292412 | F19: 23.693876
A20: Discounts/Coupons | E20: 1.26 | F20: 1.36
A21: Total Food Cost | E21: 28.12 | F21: 34.93
A22: Food
A23: Beginning Inventory (+) | E23: 25213.23 | F23: 26085.01
A24: Purchases | E24: 19804.54 | F24: 21372.98
A25: Adjustments (+/-) | E25: 0 | F25: 0
A26: Transfers | E26: 0 | F26: 477.53
A27: Promotions (-) | E27: 465.74 | F27: 301.35
A28: Ending Inventory (-) | E28: 24447.53 | F28: 30753.29
A29: Total | E29: 20104.5 | F29: 16880.89
A30: Paper
A31: Beginning Inventory (+) | E31: 9403.84 | F31: 9804.83
A32: Purchases | E32: 2357.39 | F32: 2082.27
A33: Adjustments (+/-) | E33: 0 | F33: 0
A34: Transfers | E34: 0 | F34: 0
A35: Promotions (-) | E35: 32.49 | F35: 22.41
A36: Ending Inventory (-) | E36: 9533.91 | F36: 10327.05
A37: Total | E37: 2194.83 | F37: 1537.64
A40: Notes

Sheet 18213
A1: Location | B1: 18213 | C1: RGR Date | D1: =_xlfn.XLOOKUP(B1,'FC-Inv Setup'!A3:A22,'FC-Inv Setup'!I3:I22) -> 46338 | F1: Date Scheduled | H1: Start Time | L1: Validity | M1: Status
A2: Supervisor | B2: =_xlfn.XLOOKUP(B1,'FC-Inv Setup'!A3:A22,'FC-Inv Setup'!C3:C22) -> Krystiana Langford | C2: FOB Risk | D2: =_xlfn.XLOOKUP(B1,'FC-Inv Setup'!A3:A22,'FC-Inv Setup'!K3:K22) -> Medium
A3: GM | B3: =_xlfn.XLOOKUP(B1,'FC-Inv Setup'!A3:A22,'FC-Inv Setup'!D3:D22) -> Cora Bahling
A4: Counting Manager | B4: =_xlfn.XLOOKUP(B1,'FC-Inv Setup'!A3:A22,'FC-Inv Setup'!E3:E22) -> Crystal
A5: Count Day | B5: =_xlfn.XLOOKUP(B1,'FC-Inv Setup'!A3:A22,'FC-Inv Setup'!J3:J22) -> Thursday
C6: Data N/A | D6: Data N/A
A7: Date | B7: Dec EOM | C7: 46030 | D7: 46249 | E7: 46044 | F7: 46051 | G7: 01/31/26% | H7: 46058 | I7: 46065 | J7: 46072 | K7: 46079 | L7: 2/28/26 | M7: 46086 | N7: 46093 | O7: 46100 | P7: 46107 | Q7: 3/31/26 | R7: 46114 | S7: 46121 | T7: 46128 | U7: 46135 | V7: 4/30/26 | W7: 4/30/26
A8: Cycle | B8: EOM | E8: Count Day | F8: Count Day | G8: EOM | H8: Count Day | I8: Count Day | J8: Count Day | K8: Count Day | L8: EOM | M8: Count Day | N8: Count Day | O8: Count Day | P8: Count Day | Q8: EOM | R8: Count Day | S8: Count Day | T8: Count Day | U8: Count Day | V8: Count Day | W8: EOM
A9: Product Net Sales | E9: 43317.38 | F9: 31712.97
A10: Total Paper Cost (%) | E10: 3.38 | F10: 3.36
A11: Total Paper Cost ($) | E11: 1464.63 | F11: 1066.16
A12: Completed Waste | E12: 0.19 | F12: 0.19
A13: Raw Waste | E13: 0.99 | F13: 1.26
A14: Condiments | E14: 1.42 | F14: 1.19
A15: Emp Mgr Meals | E15: 0.38 | F15: 0.47
A16: Variance Stat | E16: 2.61 | F16: -12.11
A17: Unexplained | E17: -0.08 | F17: -0.16
A18: Food Over Base | E18: 5.51 | F18: -9.16
A19: Base Food | E19: 23.167452 | F19: 23.890527
A20: Discounts/Coupons | E20: 1.39 | F20: 1.49
A21: Total Food Cost | E21: 30.06 | F21: 16.22
A22: Food
A23: Beginning Inventory (+) | E23: 14375.36 | F23: 14994.59
A24: Purchases | E24: 11832.31 | F24: 5377.92
A25: Adjustments (+/-) | E25: 0 | F25: 0
A26: Transfers | E26: 11.74 | F26: -30.89
A27: Promotions (-) | E27: 255.65 | F27: 140.72
A28: Ending Inventory (-) | E28: 12941 | F28: 15058.18
A29: Total | E29: 13022.76 | F29: 5142.71
A30: Paper
A31: Beginning Inventory (+) | E31: 6349.4 | F31: 6655.21
A32: Purchases | E32: 1582.65 | F32: 692.98
A33: Adjustments (+/-) | E33: 0 | F33: 0
A34: Transfers | E34: 0 | F34: 0
A35: Promotions (-) | E35: 18.2 | F35: 11.05
A36: Ending Inventory (-) | E36: 6449.22 | F36: 6270.98
A37: Total | E37: 1464.63 | F37: 1066.16
A40: Notes

Sheet 20475
A1: Location | B1: 20475 | C1: RGR Date | D1: =_xlfn.XLOOKUP(B1,'FC-Inv Setup'!A3:A22,'FC-Inv Setup'!I3:I22) -> 46107 | F1: Date Scheduled | H1: Start Time | L1: Validity | M1: Status
A2: Supervisor | B2: =_xlfn.XLOOKUP(B1,'FC-Inv Setup'!A3:A22,'FC-Inv Setup'!C3:C22) -> Amanda Estrada | C2: FOB Risk | D2: =_xlfn.XLOOKUP(B1,'FC-Inv Setup'!A3:A22,'FC-Inv Setup'!K3:K22) -> Low
A3: GM | B3: =_xlfn.XLOOKUP(B1,'FC-Inv Setup'!A3:A22,'FC-Inv Setup'!D3:D22) -> Derek McGirt
A4: Counting Manager | B4: =_xlfn.XLOOKUP(B1,'FC-Inv Setup'!A3:A22,'FC-Inv Setup'!E3:E22) -> Susanna
A5: Count Day | B5: =_xlfn.XLOOKUP(B1,'FC-Inv Setup'!A3:A22,'FC-Inv Setup'!J3:J22) -> Thursday
C6: Data N/A | D6: Data N/A
A7: Date | B7: Dec EOM | C7: 46030 | D7: 46249 | E7: 46044 | F7: 46051 | G7: 01/31/26% | H7: 46058 | I7: 46065 | J7: 46072 | K7: 46079 | L7: 2/28/26 | M7: 46086 | N7: 46093 | O7: 46100 | P7: 46107 | Q7: 3/31/26 | R7: 46114 | S7: 46121 | T7: 46128 | U7: 46135 | V7: 4/30/26 | W7: 4/30/26
A8: Cycle | B8: EOM | E8: Count Day | F8: Count Day | G8: EOM | H8: Count Day | I8: Count Day | J8: Count Day | K8: Count Day | L8: EOM | M8: Count Day | N8: Count Day | O8: Count Day | P8: Count Day | Q8: EOM | R8: Count Day | S8: Count Day | T8: Count Day | U8: Count Day | V8: Count Day | W8: EOM
A9: Product Net Sales | E9: 78125.23 | F9: 61228.57
A10: Total Paper Cost (%) | E10: 3.4 | F10: 5.65
A11: Total Paper Cost ($) | E11: 2652.52 | F11: 3457.2
A12: Completed Waste | E12: 0.26 | F12: 0.28
A13: Raw Waste | E13: 0.25 | F13: 0.46
A14: Condiments | E14: 2.12 | F14: 2.31
A15: Emp Mgr Meals | E15: 0.3 | F15: 0.32
A16: Variance Stat | E16: 1.93 | F16: 5.21
A17: Unexplained | E17: -0.05 | F17: -0.12
A18: Food Over Base | E18: 4.81 | F18: 8.46
A19: Base Food | E19: 23.381987 | F19: 23.683004
A20: Discounts/Coupons | E20: 1.65 | F20: 1.68
A21: Total Food Cost | E21: 29.84 | F21: 33.82
A22: Food
A23: Beginning Inventory (+) | E23: 18623.2 | F23: 19445.19
A24: Purchases | E24: 18930.61 | F24: 21704.51
A25: Adjustments (+/-) | E25: 0 | F25: -42.25
A26: Transfers | E26: 130.57 | F26: -6.37
A27: Promotions (-) | E27: 712.66 | F27: 554.53
A28: Ending Inventory (-) | E28: 13658.23 | F28: 19837.93
A29: Total | E29: 23313.48 | F29: 20708.62
A30: Paper
A31: Beginning Inventory (+) | E31: 7203.53 | F31: 7892.54
A32: Purchases | E32: 2990.64 | F32: 2366.86
A33: Adjustments (+/-) | E33: 0 | F33: 0
A34: Transfers | E34: 0 | F34: 0
A35: Promotions (-) | E35: 46.75 | F35: 37.23
A36: Ending Inventory (-) | E36: 7494.9 | F36: 6764.97
A37: Total | E37: 2652.52 | F37: 3457.2
A40: Notes

Sheet 24471
A1: Location | B1: 24471 | C1: RGR Date | D1: =_xlfn.XLOOKUP(B1,'FC-Inv Setup'!A3:A22,'FC-Inv Setup'!I3:I22) -> 46309 | F1: Date Scheduled | H1: Start Time | L1: Validity | M1: Status
A2: Supervisor | B2: =_xlfn.XLOOKUP(B1,'FC-Inv Setup'!A3:A22,'FC-Inv Setup'!C3:C22) -> Robert Spencer | C2: FOB Risk | D2: =_xlfn.XLOOKUP(B1,'FC-Inv Setup'!A3:A22,'FC-Inv Setup'!K3:K22) -> High
A3: GM | B3: =_xlfn.XLOOKUP(B1,'FC-Inv Setup'!A3:A22,'FC-Inv Setup'!D3:D22) -> Mystykal Abbey
A4: Counting Manager | B4: =_xlfn.XLOOKUP(B1,'FC-Inv Setup'!A3:A22,'FC-Inv Setup'!E3:E22) -> Mystikal
A5: Count Day | B5: =_xlfn.XLOOKUP(B1,'FC-Inv Setup'!A3:A22,'FC-Inv Setup'!J3:J22) -> Thursday
C6: Data N/A | D6: Data N/A
A7: Date | B7: Dec EOM | C7: 46030 | D7: 46249 | E7: 46044 | F7: 46051 | G7: 01/31/26% | H7: 46058 | I7: 46065 | J7: 46072 | K7: 46079 | L7: 2/28/26 | M7: 46086 | N7: 46093 | O7: 46100 | P7: 46107 | Q7: 3/31/26 | R7: 46114 | S7: 46121 | T7: 46128 | U7: 46135 | V7: 4/30/26 | W7: 4/30/26
A8: Cycle | B8: EOM | E8: Count Day | F8: Count Day | G8: EOM | H8: Count Day | I8: Count Day | J8: Count Day | K8: Count Day | L8: EOM | M8: Count Day | N8: Count Day | O8: Count Day | P8: Count Day | Q8: EOM | R8: Count Day | S8: Count Day | T8: Count Day | U8: Count Day | V8: Count Day | W8: EOM
A9: Product Net Sales | E9: 80045.43 | F9: 51026.77
A10: Total Paper Cost (%) | E10: 3.24 | F10: 5.59
A11: Total Paper Cost ($) | E11: 2593.85 | F11: 2851.98
A12: Completed Waste | E12: 0.59 | F12: 0.61
A13: Raw Waste | E13: 0.54 | F13: 0.5
A14: Condiments | E14: 1.52 | F14: 3.7
A15: Emp Mgr Meals | E15: 0.38 | F15: 0.49
A16: Variance Stat | E16: 2.47 | F16: 3.56
A17: Unexplained | E17: 0 | F17: -0.01
A18: Food Over Base | E18: 5.5 | F18: 8.85
A19: Base Food | E19: 23.317099 | F19: 23.5069
A20: Discounts/Coupons | E20: 1.32 | F20: 1.35
A21: Total Food Cost | E21: 30.14 | F21: 33.71
A22: Food
A23: Beginning Inventory (+) | E23: 23424.05 | F23: 23880.78
A24: Purchases | E24: 22275.93 | F24: 20467.5
A25: Adjustments (+/-) | E25: 0 | F25: 0
A26: Transfers | E26: 114.61 | F26: 0
A27: Promotions (-) | E27: 628.11 | F27: 373.56
A28: Ending Inventory (-) | E28: 21064.55 | F28: 26772.72
A29: Total | E29: 24121.94 | F29: 17202
A30: Paper
A31: Beginning Inventory (+) | E31: 6378.19 | F31: 7054.74
A32: Purchases | E32: 2999.43 | F32: 2200.96
A33: Adjustments (+/-) | E33: 0 | F33: 0
A34: Transfers | E34: 0 | F34: 0
A35: Promotions (-) | E35: 44.82 | F35: 24.95
A36: Ending Inventory (-) | E36: 6738.95 | F36: 6378.78
A37: Total | E37: 2593.85 | F37: 2851.98
A40: Notes

Sheet 29760
A1: Location | B1: 29760 | C1: RGR Date | D1: =_xlfn.XLOOKUP(B1,'FC-Inv Setup'!A3:A22,'FC-Inv Setup'!I3:I22) -> 46323 | F1: Date Scheduled | H1: Start Time | L1: Validity | M1: Status
A2: Supervisor | B2: =_xlfn.XLOOKUP(B1,'FC-Inv Setup'!A3:A22,'FC-Inv Setup'!C3:C22) -> Krystiana Langford | C2: FOB Risk | D2: =_xlfn.XLOOKUP(B1,'FC-Inv Setup'!A3:A22,'FC-Inv Setup'!K3:K22) -> Low
A3: GM | B3: =_xlfn.XLOOKUP(B1,'FC-Inv Setup'!A3:A22,'FC-Inv Setup'!D3:D22) -> Heather Danforth
A4: Counting Manager | B4: =_xlfn.XLOOKUP(B1,'FC-Inv Setup'!A3:A22,'FC-Inv Setup'!E3:E22) -> Magi
A5: Count Day | B5: =_xlfn.XLOOKUP(B1,'FC-Inv Setup'!A3:A22,'FC-Inv Setup'!J3:J22) -> Thursday
C6: Data N/A | D6: Data N/A
A7: Date | B7: Dec EOM | C7: 46030 | D7: 46249 | E7: 46044 | F7: 46051 | G7: 01/31/26% | H7: 46058 | I7: 46065 | J7: 46072 | K7: 46079 | L7: 2/28/26 | M7: 46086 | N7: 46093 | O7: 46100 | P7: 46107 | Q7: 3/31/26 | R7: 46114 | S7: 46121 | T7: 46128 | U7: 46135 | V7: 4/30/26 | W7: 4/30/26
A8: Cycle | B8: EOM | E8: Count Day | F8: Count Day | G8: EOM | H8: Count Day | I8: Count Day | J8: Count Day | K8: Count Day | L8: EOM | M8: Count Day | N8: Count Day | O8: Count Day | P8: Count Day | Q8: EOM | R8: Count Day | S8: Count Day | T8: Count Day | U8: Count Day | V8: Count Day | W8: EOM
A9: Product Net Sales | E9: 112254.39 | F9: 101656.28
A10: Total Paper Cost (%) | E10: 3.2 | F10: 7.86
A11: Total Paper Cost ($) | E11: 3588.36 | F11: 7987.48
A12: Completed Waste | E12: 0.21 | F12: 0.22
A13: Raw Waste | E13: 0.39 | F13: 0.4
A14: Condiments | E14: 2.08 | F14: 2.3
A15: Emp Mgr Meals | E15: 0.34 | F15: 0.35
A16: Variance Stat | E16: 1.24 | F16: 2.15
A17: Unexplained | E17: -0.03 | F17: -0.07
A18: Food Over Base | E18: 4.23 | F18: 5.35
A19: Base Food | E19: 23.163269 | F19: 23.532933
A20: Discounts/Coupons | E20: 1.2 | F20: 1.3
A21: Total Food Cost | E21: 28.58 | F21: 30.18
A22: Food
A23: Beginning Inventory (+) | E23: 28296.33 | F23: 30717.03
A24: Purchases | E24: 29200.93 | F24: 28221.02
A25: Adjustments (+/-) | E25: 0 | F25: 0
A26: Transfers | E26: -30.98 | F26: 0
A27: Promotions (-) | E27: 931.55 | F27: 876.76
A28: Ending Inventory (-) | E28: 24447.89 | F28: 27376.85
A29: Total | E29: 32086.83 | F29: 30684.45
A30: Paper
A31: Beginning Inventory (+) | E31: 7830.66 | F31: 8728.83
A32: Purchases | E32: 3951.71 | F32: 3860.72
A33: Adjustments (+/-) | E33: 0 | F33: 0
A34: Transfers | E34: 32.4 | F34: 0
A35: Promotions (-) | E35: 63.86 | F35: 58.07
A36: Ending Inventory (-) | E36: 8162.56 | F36: 4544
A37: Total | E37: 3588.36 | F37: 7987.48
A40: Notes

Sheet 31357
A1: Location | B1: 31357 | C1: RGR Date | D1: =_xlfn.XLOOKUP(B1,'FC-Inv Setup'!A3:A22,'FC-Inv Setup'!I3:I22) -> 46198 | F1: Date Scheduled | H1: Start Time | L1: Validity | M1: Status
A2: Supervisor | B2: =_xlfn.XLOOKUP(B1,'FC-Inv Setup'!A3:A22,'FC-Inv Setup'!C3:C22) -> Amanda Estrada | C2: FOB Risk | D2: =_xlfn.XLOOKUP(B1,'FC-Inv Setup'!A3:A22,'FC-Inv Setup'!K3:K22) -> Medium
A3: GM | B3: =_xlfn.XLOOKUP(B1,'FC-Inv Setup'!A3:A22,'FC-Inv Setup'!D3:D22) -> Brady Giambaresi
A4: Counting Manager | B4: =_xlfn.XLOOKUP(B1,'FC-Inv Setup'!A3:A22,'FC-Inv Setup'!E3:E22) -> Angelo
A5: Count Day | B5: =_xlfn.XLOOKUP(B1,'FC-Inv Setup'!A3:A22,'FC-Inv Setup'!J3:J22) -> Thursday
C6: Data N/A | D6: Data N/A
A7: Date | B7: Dec EOM | C7: 46030 | D7: 46249 | E7: 46044 | F7: 46051 | G7: 01/31/26% | H7: 46058 | I7: 46065 | J7: 46072 | K7: 46079 | L7: 2/28/26 | M7: 46086 | N7: 46093 | O7: 46100 | P7: 46107 | Q7: 3/31/26 | R7: 46114 | S7: 46121 | T7: 46128 | U7: 46135 | V7: 4/30/26 | W7: 4/30/26
A8: Cycle | B8: EOM | E8: Count Day | F8: Count Day | G8: EOM | H8: Count Day | I8: Count Day | J8: Count Day | K8: Count Day | L8: EOM | M8: Count Day | N8: Count Day | O8: Count Day | P8: Count Day | Q8: EOM | R8: Count Day | S8: Count Day | T8: Count Day | U8: Count Day | V8: Count Day | W8: EOM
A9: Product Net Sales | E9: 76738.62 | F9: 56499.69
A10: Total Paper Cost (%) | E10: 3.3 | F10: 3.32
A11: Total Paper Cost ($) | E11: 2532.07 | F11: 1878.3
A12: Completed Waste | E12: 0.1 | F12: 0.39
A13: Raw Waste | E13: 0.57 | F13: 0.71
A14: Condiments | E14: 2.59 | F14: 2.78
A15: Emp Mgr Meals | E15: 0.21 | F15: 0.3
A16: Variance Stat | E16: 3.12 | F16: 3.7
A17: Unexplained | E17: 0.02 | F17: -0.011
A18: Food Over Base | E18: 6.61 | F18: 7.87
A19: Base Food | E19: 23.077301 | F19: 23.586345
A20: Discounts/Coupons | E20: 1.27 | F20: 1.3
A21: Total Food Cost | E21: 30.95 | F21: 32.76
A22: Food
A23: Beginning Inventory (+) | E23: 23284.92 | F23: 24239.74
A24: Purchases | E24: 22173.32 | F24: 19203.91
A25: Adjustments (+/-) | E25: 0 | F25: -45.13
A26: Transfers | E26: -98.78 | F26: 0
A27: Promotions (-) | E27: 641.47 | F27: 547.92
A28: Ending Inventory (-) | E28: 20950.71 | F28: 24341.91
A29: Total | E29: 23767.28 | F29: 18508.69
A30: Paper
A31: Beginning Inventory (+) | E31: 15919.41 | F31: 15587.46
A32: Purchases | E32: 1901.14 | F32: 2674.01
A33: Adjustments (+/-) | E33: 0 | F33: 0
A34: Transfers | E34: 0 | F34: -87.92
A35: Promotions (-) | E35: 46.69 | F35: 41.72
A36: Ending Inventory (-) | E36: 15241.8 | F36: 16253.53
A37: Total | E37: 2532.07 | F37: 1878.3
A40: Notes

Sheet 32525
A1: Location | B1: 32525 | C1: RGR Date | D1: =_xlfn.XLOOKUP(B1,'FC-Inv Setup'!A3:A22,'FC-Inv Setup'!I3:I22) -> 46337 | F1: Date Scheduled | H1: Start Time | L1: Validity | M1: Status
A2: Supervisor | B2: =_xlfn.XLOOKUP(B1,'FC-Inv Setup'!A3:A22,'FC-Inv Setup'!C3:C22) -> Robert Spencer | C2: FOB Risk | D2: =_xlfn.XLOOKUP(B1,'FC-Inv Setup'!A3:A22,'FC-Inv Setup'!K3:K22) -> High
A3: GM | B3: =_xlfn.XLOOKUP(B1,'FC-Inv Setup'!A3:A22,'FC-Inv Setup'!D3:D22) -> Aliyah Richardson
A4: Counting Manager | B4: =_xlfn.XLOOKUP(B1,'FC-Inv Setup'!A3:A22,'FC-Inv Setup'!E3:E22) -> Priscilla
A5: Count Day | B5: =_xlfn.XLOOKUP(B1,'FC-Inv Setup'!A3:A22,'FC-Inv Setup'!J3:J22) -> Thursday
C6: Data N/A | D6: Data N/A
A7: Date | B7: Dec EOM | C7: 46030 | D7: 46249 | E7: 46044 | F7: 46051 | G7: 01/31/26% | H7: 46058 | I7: 46065 | J7: 46072 | K7: 46079 | L7: 2/28/26 | M7: 46086 | N7: 46093 | O7: 46100 | P7: 46107 | Q7: 3/31/26 | R7: 46114 | S7: 46121 | T7: 46128 | U7: 46135 | V7: 4/30/26 | W7: 4/30/26
A8: Cycle | B8: EOM | E8: Count Day | F8: Count Day | G8: EOM | H8: Count Day | I8: Count Day | J8: Count Day | K8: Count Day | L8: EOM | M8: Count Day | N8: Count Day | O8: Count Day | P8: Count Day | Q8: EOM | R8: Count Day | S8: Count Day | T8: Count Day | U8: Count Day | V8: Count Day | W8: EOM
A9: Product Net Sales | E9: 59050.96 | F9: 40405.79
A10: Total Paper Cost (%) | E10: 3.34 | F10: 6.07
A11: Total Paper Cost ($) | E11: 1970.42 | F11: 2453.6
A12: Completed Waste | E12: 0.46 | F12: 0.33
A13: Raw Waste | E13: 1.72 | F13: 1.58
A14: Condiments | E14: 2.26 | F14: 2.51
A15: Emp Mgr Meals | E15: 0.29 | F15: 0.24
A16: Variance Stat | E16: 0.79 | F16: 1.96
A17: Unexplained | E17: -0.03 | F17: -0.03
A18: Food Over Base | E18: 5.49 | F18: 6.59
A19: Base Food | E19: 23.701091 | F19: 24.130862
A20: Discounts/Coupons | E20: 1.27 | F20: 1.21
A21: Total Food Cost | E21: 30.45 | F21: 31.93
A22: Food
A23: Beginning Inventory (+) | E23: 23339.56 | F23: 23898.51
A24: Purchases | E24: 16693.11 | F24: 13077.52
A25: Adjustments (+/-) | E25: 0 | F25: 0
A26: Transfers | E26: 0 | F26: 19.15
A27: Promotions (-) | E27: 413.41 | F27: 293.17
A28: Ending Inventory (-) | E28: 21636.91 | F28: 23800.62
A29: Total | E29: 17982.35 | F29: 12901.39
A30: Paper
A31: Beginning Inventory (+) | E31: 6018.21 | F31: 6168.67
A32: Purchases | E32: 1885.72 | F32: 1874.93
A33: Adjustments (+/-) | E33: 0 | F33: 0
A34: Transfers | E34: 0 | F34: 0
A35: Promotions (-) | E35: 28.38 | F35: 20.75
A36: Ending Inventory (-) | E36: 5905.13 | F36: 5569.25
A37: Total | E37: 1970.42 | F37: 2453.6
A40: Notes

Sheet 33109
A1: Location | B1: 33109 | C1: RGR Date | D1: =_xlfn.XLOOKUP(B1,'FC-Inv Setup'!A3:A22,'FC-Inv Setup'!I3:I22) -> 46295 | F1: Date Scheduled | H1: Start Time | L1: Validity | M1: Status
A2: Supervisor | B2: =_xlfn.XLOOKUP(B1,'FC-Inv Setup'!A3:A22,'FC-Inv Setup'!C3:C22) -> Ashley Podroza | C2: FOB Risk | D2: =_xlfn.XLOOKUP(B1,'FC-Inv Setup'!A3:A22,'FC-Inv Setup'!K3:K22) -> Low
A3: GM | B3: =_xlfn.XLOOKUP(B1,'FC-Inv Setup'!A3:A22,'FC-Inv Setup'!D3:D22) -> Rey Araiz
A4: Counting Manager | B4: =_xlfn.XLOOKUP(B1,'FC-Inv Setup'!A3:A22,'FC-Inv Setup'!E3:E22) -> Gisselle
A5: Count Day | B5: =_xlfn.XLOOKUP(B1,'FC-Inv Setup'!A3:A22,'FC-Inv Setup'!J3:J22) -> Tuesday
C6: Data N/A | D6: Data N/A
A7: Date | B7: Dec EOM | C7: 46030 | D7: 46249 | E7: 46044 | F7: 46051 | G7: 01/31/26% | H7: 46058 | I7: 46065 | J7: 46072 | K7: 46079 | L7: 2/28/26 | M7: 46086 | N7: 46093 | O7: 46100 | P7: 46107 | Q7: 3/31/26 | R7: 46114 | S7: 46121 | T7: 46128 | U7: 46135 | V7: 4/30/26 | W7: 4/30/26
A8: Cycle | B8: EOM | E8: Count Day | F8: Count Day | G8: EOM | H8: Count Day | I8: Count Day | J8: Count Day | K8: Count Day | L8: EOM | M8: Count Day | N8: Count Day | O8: Count Day | P8: Count Day | Q8: EOM | R8: Count Day | S8: Count Day | T8: Count Day | U8: Count Day | V8: Count Day | W8: EOM
A9: Product Net Sales | E9: 71546.23 | F9: 46108.73
A10: Total Paper Cost (%) | E10: 3.36 | F10: 3.28
A11: Total Paper Cost ($) | E11: 2404.04 | F11: 1514.46
A12: Completed Waste | E12: 0.12 | F12: 0.15
A13: Raw Waste | E13: 0.47 | F13: 0.74
A14: Condiments | E14: 1.96 | F14: 1.99
A15: Emp Mgr Meals | E15: 0.16 | F15: 0.15
A16: Variance Stat | E16: 1.14 | F16: 0.05
A17: Unexplained | E17: -0.04 | F17: -0.01
A18: Food Over Base | E18: 3.81 | F18: 3.07
A19: Base Food | E19: 23.722064 | F19: 24.137003
A20: Discounts/Coupons | E20: 1.24 | F20: 1.25
A21: Total Food Cost | E21: 28.78 | F21: 28.46
A22: Food
A23: Beginning Inventory (+) | E23: 20551.31 | F23: 18042.97
A24: Purchases | E24: 15947.85 | F24: 11681.46
A25: Adjustments (+/-) | E25: 0 | F25: 0
A26: Transfers | E26: 0 | F26: 0
A27: Promotions (-) | E27: 356.65 | F27: 239.1
A28: Ending Inventory (-) | E28: 15553.62 | F28: 16363.13
A29: Total | E29: 20588.89 | F29: 13122.2
A30: Paper
A31: Beginning Inventory (+) | E31: 5901.32 | F31: 5724.45
A32: Purchases | E32: 1951.89 | F32: 1541
A33: Adjustments (+/-) | E33: 0 | F33: 0
A34: Transfers | E34: 0 | F34: 0
A35: Promotions (-) | E35: 23.4 | F35: 16.02
A36: Ending Inventory (-) | E36: 5425.78 | F36: 5734.96
A37: Total | E37: 2404.04 | F37: 1514.46
A40: Notes

Sheet 33222
A1: Location | B1: 33222 | C1: RGR Date | D1: =_xlfn.XLOOKUP(B1,'FC-Inv Setup'!A3:A22,'FC-Inv Setup'!I3:I22) -> 46169 | F1: Date Scheduled | H1: Start Time | L1: Validity | M1: Status
A2: Supervisor | B2: =_xlfn.XLOOKUP(B1,'FC-Inv Setup'!A3:A22,'FC-Inv Setup'!C3:C22) -> Krystiana Langford | C2: FOB Risk | D2: =_xlfn.XLOOKUP(B1,'FC-Inv Setup'!A3:A22,'FC-Inv Setup'!K3:K22) -> High
A3: GM | B3: =_xlfn.XLOOKUP(B1,'FC-Inv Setup'!A3:A22,'FC-Inv Setup'!D3:D22) -> Carol Escusa
A4: Counting Manager | B4: =_xlfn.XLOOKUP(B1,'FC-Inv Setup'!A3:A22,'FC-Inv Setup'!E3:E22) -> Darryl
A5: Count Day | B5: =_xlfn.XLOOKUP(B1,'FC-Inv Setup'!A3:A22,'FC-Inv Setup'!J3:J22) -> Thursday
C6: Data N/A | D6: Data N/A
A7: Date | B7: Dec EOM | C7: 46030 | D7: 46249 | E7: 46044 | F7: 46051 | G7: 01/31/26% | H7: 46058 | I7: 46065 | J7: 46072 | K7: 46079 | L7: 2/28/26 | M7: 46086 | N7: 46093 | O7: 46100 | P7: 46107 | Q7: 3/31/26 | R7: 46114 | S7: 46121 | T7: 46128 | U7: 46135 | V7: 4/30/26 | W7: 4/30/26
A8: Cycle | B8: EOM | E8: Count Day | F8: Count Day | G8: EOM | H8: Count Day | I8: Count Day | J8: Count Day | K8: Count Day | L8: EOM | M8: Count Day | N8: Count Day | O8: Count Day | P8: Count Day | Q8: EOM | R8: Count Day | S8: Count Day | T8: Count Day | U8: Count Day | V8: Count Day | W8: EOM
A9: Product Net Sales | E9: 60445.05 | F9: 43354.19
A10: Total Paper Cost (%) | E10: 3.03 | F10: 6.19
A11: Total Paper Cost ($) | E11: 1828.88 | F11: 2682.06
A12: Completed Waste | E12: 0.36 | F12: 0.33
A13: Raw Waste | E13: 1.15 | F13: 1.22
A14: Condiments | E14: 2.92 | F14: 6
A15: Emp Mgr Meals | E15: 0.16 | F15: 0.19
A16: Variance Stat | E16: 1.97 | F16: 5.17
A17: Unexplained | E17: -0.16 | F17: -0.16
A18: Food Over Base | E18: 6.4 | F18: 12.75
A19: Base Food | E19: 23.39591 | F19: 23.806802
A20: Discounts/Coupons | E20: 1.24 | F20: 1.23
A21: Total Food Cost | E21: 31.03 | F21: 37.79
A22: Food
A23: Beginning Inventory (+) | E23: 19610.83 | F23: 21784.44
A24: Purchases | E24: 16753.12 | F24: 14314.2
A25: Adjustments (+/-) | E25: 0 | F25: 0
A26: Transfers | E26: 299.17 | F26: 0
A27: Promotions (-) | E27: 424 | F27: 294.13
A28: Ending Inventory (-) | E28: 17482.55 | F28: 19420.5
A29: Total | E29: 18756.57 | F29: 16384.01
A30: Paper
A31: Beginning Inventory (+) | E31: 7240.04 | F31: 7082.66
A32: Purchases | E32: 1488.68 | F32: 2728.88
A33: Adjustments (+/-) | E33: 0 | F33: 0
A34: Transfers | E34: -32.4 | F34: 0
A35: Promotions (-) | E35: 29.47 | F35: 20.2
A36: Ending Inventory (-) | E36: 6837.97 | F36: 7109.28
A37: Total | E37: 1828.88 | F37: 2682.06
A40: Notes

Sheet 33704
A1: Location | B1: 33704 | C1: RGR Date | D1: =_xlfn.XLOOKUP(B1,'FC-Inv Setup'!A3:A22,'FC-Inv Setup'!I3:I22) -> 46127 | F1: Date Scheduled | H1: Start Time | L1: Validity | M1: Status
A2: Supervisor | B2: =_xlfn.XLOOKUP(B1,'FC-Inv Setup'!A3:A22,'FC-Inv Setup'!C3:C22) -> Steven Vaughn | C2: FOB Risk | D2: =_xlfn.XLOOKUP(B1,'FC-Inv Setup'!A3:A22,'FC-Inv Setup'!K3:K22) -> Medium
A3: GM | B3: =_xlfn.XLOOKUP(B1,'FC-Inv Setup'!A3:A22,'FC-Inv Setup'!D3:D22) -> Candy Barksdale
A4: Counting Manager | B4: =_xlfn.XLOOKUP(B1,'FC-Inv Setup'!A3:A22,'FC-Inv Setup'!E3:E22) -> Marlena
A5: Count Day | B5: =_xlfn.XLOOKUP(B1,'FC-Inv Setup'!A3:A22,'FC-Inv Setup'!J3:J22) -> Friday
C6: Data N/A | D6: Data N/A
A7: Date | B7: Dec EOM | C7: 46031 | D7: 46038 | E7: 46045 | F7: 46052 | G7: 46053 | H7: 46059 | I7: 46066 | J7: 46073 | K7: 46080 | L7: 2/28/26 | M7: 46087 | N7: 46094 | O7: 46101 | P7: 46108 | Q7: 3/31/26 | R7: 46115 | S7: 46122 | T7: 46129 | U7: 46136 | V7: 4/30/26
A8: Cycle | B8: EOM | E8: Count Day | F8: Count Day | G8: EOM | H8: Count Day | I8: Count Day | J8: Count Day | K8: Count Day | L8: EOM | M8: Count Day | N8: Count Day | O8: Count Day | P8: Count Day | Q8: EOM | R8: Count Day | S8: Count Day | T8: Count Day | U8: Count Day | V8: EOM
A9: Product Net Sales | E9: 71459.09 | F9: 50655.59
A10: Total Paper Cost (%) | E10: 3.31 | F10: 3.32
A11: Total Paper Cost ($) | E11: 2366.68 | F11: 1679.89
A12: Completed Waste | E12: 0.16 | F12: 0.2
A13: Raw Waste | E13: 0.83 | F13: 1.21
A14: Condiments | E14: 1.53 | F14: 1.72
A15: Emp Mgr Meals | E15: 0.38 | F15: 0.49
A16: Variance Stat | E16: 0.8 | F16: 1.16
A17: Unexplained | E17: -0.04 | F17: -0.02
A18: Food Over Base | E18: 3.66 | F18: 4.76
A19: Base Food | E19: 23.28387 | F19: 23.566689
A20: Discounts/Coupons | E20: 1.65 | F20: 1.74
A21: Total Food Cost | E21: 28.6 | F21: 30.06
A22: Food
A23: Beginning Inventory (+) | E23: 27110.65 | F23: 25620.24
A24: Purchases | E24: 16333.34 | F24: 14064.75
A25: Adjustments (+/-) | E25: 0 | F25: -34.13
A26: Transfers | E26: -34.17 | F26: 0
A27: Promotions (-) | E27: 514.16 | F27: 373.63
A28: Ending Inventory (-) | E28: 22458.93 | F28: 24048.09
A29: Total | E29: 20436.72 | F29: 15229.13
A30: Paper
A31: Beginning Inventory (+) | E31: 9968.4 | F31: 10203.09
A32: Purchases | E32: 2189.92 | F32: 1097.81
A33: Adjustments (+/-) | E33: 0 | F33: 0
A34: Transfers | E34: 167.63 | F34: 0
A35: Promotions (-) | E35: 40.53 | F35: 28.75
A36: Ending Inventory (-) | E36: 9918.73 | F36: 9592.26
A37: Total | E37: 2366.68 | F37: 1679.89
A40: Notes

Sheet 34222
A1: Location | B1: 34222 | C1: RGR Date | D1: =_xlfn.XLOOKUP(B1,'FC-Inv Setup'!A3:A22,'FC-Inv Setup'!I3:I22) -> 46155 | F1: Date Scheduled | H1: Start Time | L1: Validity | M1: Status
A2: Supervisor | B2: =_xlfn.XLOOKUP(B1,'FC-Inv Setup'!A3:A22,'FC-Inv Setup'!C3:C22) -> Steven Vaughn | C2: FOB Risk | D2: =_xlfn.XLOOKUP(B1,'FC-Inv Setup'!A3:A22,'FC-Inv Setup'!K3:K22) -> Low
A3: GM | B3: =_xlfn.XLOOKUP(B1,'FC-Inv Setup'!A3:A22,'FC-Inv Setup'!D3:D22) -> Hunter McKee
A4: Counting Manager | B4: =_xlfn.XLOOKUP(B1,'FC-Inv Setup'!A3:A22,'FC-Inv Setup'!E3:E22) -> Kaylee
A5: Count Day | B5: =_xlfn.XLOOKUP(B1,'FC-Inv Setup'!A3:A22,'FC-Inv Setup'!J3:J22) -> Monday
C6: Data N/A | D6: Data N/A
A7: Date | B7: Dec EOM | C7: 46029 | D7: 46036 | E7: 46043 | F7: 46050 | G7: 46053 | H7: 46057 | I7: 46064 | J7: 46071 | K7: 46078 | L7: 2/28/26 | M7: 46085 | N7: 46092 | O7: 46099 | P7: 46106 | Q7: 3/31/26 | R7: 46113 | S7: 46120 | T7: 46127 | U7: 46134 | V7: 46141 | W7: 4/30/26
A8: Cycle | B8: EOM | E8: Count Day | F8: Count Day | G8: EOM | H8: Count Day | I8: Count Day | J8: Count Day | K8: Count Day | L8: EOM | M8: Count Day | N8: Count Day | O8: Count Day | P8: Count Day | Q8: EOM | R8: Count Day | S8: Count Day | T8: Count Day | U8: Count Day | V8: Count Day | W8: EOM
A9: Product Net Sales | E9: 67380.6 | F9: 49812.54
A10: Total Paper Cost (%) | E10: 3.1 | F10: 3.08
A11: Total Paper Cost ($) | E11: 2091.1 | F11: 1536.52
A12: Completed Waste | E12: 0.17 | F12: 0.2
A13: Raw Waste | E13: 0.56 | F13: 0.76
A14: Condiments | E14: 1.89 | F14: 2.1
A15: Emp Mgr Meals | E15: 0.52 | F15: 0.57
A16: Variance Stat | E16: 1.08 | F16: 1.39
A17: Unexplained | E17: -0.03 | F17: -0.05
A18: Food Over Base | E18: 4.19 | F18: 4.97
A19: Base Food | E19: 23.271646 | F19: 23.49306
A20: Discounts/Coupons | E20: 1.44 | F20: 1.48
A21: Total Food Cost | E21: 28.91 | F21: 29.93
A22: Food
A23: Beginning Inventory (+) | E23: 17170.88 | F23: 19299.37
A24: Purchases | E24: 19463.99 | F24: 14384.9
A25: Adjustments (+/-) | E25: -34.51 | F25: 0
A26: Transfers | E26: -32.52 | F26: -17.1
A27: Promotions (-) | E27: 534.11 | F27: 371.02
A28: Ending Inventory (-) | E28: 16555.77 | F28: 18384.89
A29: Total | E29: 19477.96 | F29: 14911.26
A30: Paper
A31: Beginning Inventory (+) | E31: 5685.24 | F31: 5720.86
A32: Purchases | E32: 1916.47 | F32: 2992.13
A33: Adjustments (+/-) | E33: 0 | F33: 0
A34: Transfers | E34: 0 | F34: 0
A35: Promotions (-) | E35: 38.67 | F35: 25.97
A36: Ending Inventory (-) | E36: 5471.93 | F36: 7150.51
A37: Total | E37: 2091.1 | F37: 1536.52
A40: Notes

Sheet 35064
A1: Location | B1: 35064 | C1: RGR Date | D1: =_xlfn.XLOOKUP(B1,'FC-Inv Setup'!A3:A22,'FC-Inv Setup'!I3:I22) -> 46211 | F1: Date Scheduled | H1: Start Time | L1: Validity | M1: Status
A2: Supervisor | B2: =_xlfn.XLOOKUP(B1,'FC-Inv Setup'!A3:A22,'FC-Inv Setup'!C3:C22) -> Steven Vaughn | C2: FOB Risk | D2: =_xlfn.XLOOKUP(B1,'FC-Inv Setup'!A3:A22,'FC-Inv Setup'!K3:K22) -> High
A3: GM | B3: =_xlfn.XLOOKUP(B1,'FC-Inv Setup'!A3:A22,'FC-Inv Setup'!D3:D22) -> Lynsey Yahola
A4: Counting Manager | B4: =_xlfn.XLOOKUP(B1,'FC-Inv Setup'!A3:A22,'FC-Inv Setup'!E3:E22) -> Lynsey
A5: Count Day | B5: =_xlfn.XLOOKUP(B1,'FC-Inv Setup'!A3:A22,'FC-Inv Setup'!J3:J22) -> Wednesday
C6: Data N/A | D6: Data N/A
A7: Date | B7: Dec EOM | C7: 46029 | D7: 46036 | E7: 46043 | F7: 46050 | G7: 46053 | H7: 46057 | I7: 46064 | J7: 46071 | K7: 46078 | L7: 2/28/26 | M7: 46085 | N7: 46092 | O7: 46099 | P7: 46106 | Q7: 3/31/26 | R7: 46113 | S7: 46120 | T7: 46127 | U7: 46134 | V7: 46141 | W7: 4/30/26
A8: Cycle | B8: EOM | E8: Count Day | F8: Count Day | G8: EOM | H8: Count Day | I8: Count Day | J8: Count Day | K8: Count Day | L8: EOM | M8: Count Day | N8: Count Day | O8: Count Day | P8: Count Day | Q8: EOM | R8: Count Day | S8: Count Day | T8: Count Day | U8: Count Day | V8: Count Day | W8: EOM
A9: Product Net Sales | E9: 50346.98 | F9: 39976.98
A10: Total Paper Cost (%) | E10: 3.46 | F10: 3.39
A11: Total Paper Cost ($) | E11: 1747.01 | F11: 1355.69
A12: Completed Waste | E12: 0.55 | F12: 0.4
A13: Raw Waste | E13: 1.25 | F13: 1.17
A14: Condiments | E14: 1.96 | F14: 2.39
A15: Emp Mgr Meals | E15: 0.24 | F15: 0.35
A16: Variance Stat | E16: -0.04 | F16: 6.5
A17: Unexplained | E17: 0.01 | F17: -0.04
A18: Food Over Base | E18: 3.97 | F18: 10.77
A19: Base Food | E19: 23.988088 | F19: 24.548249
A20: Discounts/Coupons | E20: 1.35 | F20: 1.46
A21: Total Food Cost | E21: 29.31 | F21: 36.77
A22: Food
A23: Beginning Inventory (+) | E23: 19019.64 | F23: 20179.59
A24: Purchases | E24: 14639.6 | F24: 15252.66
A25: Adjustments (+/-) | E25: 0 | F25: 0
A26: Transfers | E26: 81.38 | F26: -257.24
A27: Promotions (-) | E27: 727 | F27: 482.41
A28: Ending Inventory (-) | E28: 18255.93 | F28: 19991.48
A29: Total | E29: 14757.7 | F29: 14701.13
A30: Paper
A31: Beginning Inventory (+) | E31: 7112.74 | F31: 7356.8
A32: Purchases | E32: 1770.18 | F32: 2051.84
A33: Adjustments (+/-) | E33: 0 | F33: 0
A34: Transfers | E34: 40.64 | F34: -29.29
A35: Promotions (-) | E35: 47.57 | F35: 31.74
A36: Ending Inventory (-) | E36: 7134.98 | F36: 7991.92
A37: Total | E37: 1741.01 | F37: 1355.69
A40: Notes

Sheet 43380
A1: Location | B1: 43380 | C1: RGR Date | D1: =_xlfn.XLOOKUP(B1,'FC-Inv Setup'!A3:A22,'FC-Inv Setup'!I3:I22) -> 46225 | F1: Date Scheduled | H1: Start Time | L1: Validity | M1: Status
A2: Supervisor | B2: =_xlfn.XLOOKUP(B1,'FC-Inv Setup'!A3:A22,'FC-Inv Setup'!C3:C22) -> Ashley Podroza | C2: FOB Risk | D2: =_xlfn.XLOOKUP(B1,'FC-Inv Setup'!A3:A22,'FC-Inv Setup'!K3:K22) -> Medium
A3: GM | B3: =_xlfn.XLOOKUP(B1,'FC-Inv Setup'!A3:A22,'FC-Inv Setup'!D3:D22) -> Zukarr Eaves
A4: Counting Manager | B4: =_xlfn.XLOOKUP(B1,'FC-Inv Setup'!A3:A22,'FC-Inv Setup'!E3:E22) -> Zukaar
A5: Count Day | B5: =_xlfn.XLOOKUP(B1,'FC-Inv Setup'!A3:A22,'FC-Inv Setup'!J3:J22) -> Saturday
C6: Data N/A | D6: Data N/A
A7: Date | B7: Dec EOM | C7: 46025 | D7: 46032 | E7: 46039 | F7: 46046 | G7: 46053 | H7: 46053 | I7: 46060 | J7: 46067 | K7: 46074 | L7: 46081 | M7: 2/28/26 | N7: 46088 | O7: 46095 | P7: 46102 | Q7: 46109 | R7: 3/31/26 | S7: 46116 | T7: 46123 | U7: 46130 | V7: 46137 | W7: 4/30/26
A8: Cycle | B8: EOM | F8: Count Day | G8: EOM | H8: Count Day | I8: Count Day | J8: Count Day | K8: Count Day | L8: EOM | M8: Count Day | N8: Count Day | O8: Count Day | P8: Count Day | Q8: EOM | R8: Count Day | S8: Count Day | T8: Count Day | U8: Count Day | V8: Count Day | W8: EOM
A9: Product Net Sales | F9: 37086.76 | G9: 30735.72
A10: Total Paper Cost (%) | F10: 3.06 | G10: 5.93
A11: Total Paper Cost ($) | F11: 1133.27 | G11: 1821.96
A12: Completed Waste | F12: 0.07 | G12: 0.07
A13: Raw Waste | F13: 0.83 | G13: 0.64
A14: Condiments | F14: 2.14 | G14: 1.73
A15: Emp Mgr Meals | F15: 0.16 | G15: 0.2
A16: Variance Stat | F16: 2.58 | G16: 0.62
A17: Unexplained | F17: -0.07 | G17: -0.11
A18: Food Over Base | F18: 5.71 | G18: 3.15
A19: Base Food | F19: 24.210873 | G19: 24.773424
A20: Discounts/Coupons | F20: 1.32 | G20: 1.36
A21: Total Food Cost | F21: 31.24 | G21: 29.28
A22: Food
A23: Beginning Inventory (+) | F23: 17446.45 | G23: 17192.25
A24: Purchases | F24: 12044.78 | G24: 8835.83
A25: Adjustments (+/-) | F25: 0 | G25: -4639.98
A26: Transfers | F26: -477.53 | G26: 190.23
A27: Promotions (-) | F27: 464.37 | G27: 387.49
A28: Ending Inventory (-) | F28: 16961.6 | G28: 12190.62
A29: Total | F29: 11587.73 | G29: 9000.23
A30: Paper
A31: Beginning Inventory (+) | F31: 4651.18 | G31: 4767.28
A32: Purchases | F32: 1258.91 | G32: 814.25
A33: Adjustments (+/-) | F33: 0 | G33: -484.12
A34: Transfers | F34: 0 | G34: 0
A35: Promotions (-) | F35: 31.24 | G35: 24.34
A36: Ending Inventory (-) | F36: 4745.58 | G36: 3251.12
A37: Total | F37: 1133.27 | G37: 1821.96
A40: Notes

Sheet Risk Profiles
A1: 12/01/25 - 03/22/26
A2: FOB Risk Profile Summary
A3: Food, Paper, and Beverage (FOB) risk evaluates inventory control, statistical variance (missing product), and waste management.
A4: Risk Level | B4: Locations | C4: Primary Risk Drivers
A5: High | B5: 35064, 13113, 24471, 32525, 6972 | C5: High Statistical Variance ($>2.0\%$) and high overall FOB % ($>5.5\%$). Location 35064 is the highest risk with excessive waste ($1.40\%$).
A6: Medium | B6: 10422, 10915, 11657, 18213, 31357, 33222, 33704, 3708, 43380, 5183 | C6: Moderate waste or minor inventory variance.
A7: Low | B7: 20475, 29760, 33109, 34222, 5985 | C7: Excellent inventory control and low waste levels.
A9: Controls Risk Profile Summary
A10: Controls risk evaluates transaction security, including T-Red (refunds/voids), cash handling (Over/Short), and discounting practices.
A11: Risk Level | B11: Locations | C11: Primary Risk Drivers
A12: High | B12: 3708 | C12: High T-Red activity ($0.29\%$), significant POS Overrings ($0.58\%$), and higher-than-average Cash Over/Short.
A13: Medium | B13: Most Locations (16) | C13: Generally driven by high discounting (e.g., 20475 at $7.40\%$) or sporadic cash handling issues.
A14: Low | B14: 32525, 33222, 5985 | C14: Very tight transaction controls and minimal cash variance.
A16: Detailed Risk Analysis by Location
A17: Loc | B17: FOB Risk Profile | C17: FOB Key Driver(s) | D17: Controls Risk Profile | E17: Controls Key Driver(s)
A18: 35064 | B18: High | C18: High FOB% (6.12%), Stat Var (2.73%), Waste (1.40%) | D18: HIgh | E18: T-Red After (0.42%), Cash O/S (0.05%)
A19: 13113 | B19: High | C19: High FOB% (5.58%), High Stat Var (2.40%) | D19: Medium | E19: POS Overrings (0.47%)
A20: 24471 | B20: High | C20: High FOB% (5.55%), High Stat Var (2.04%) | D20: Medium | E20: Within Normal range
A21: 32525 | B21: High | C21: High FOB% (5.27%), High Waste (1.51%) | D21: Low | E21: Within Normal range
A22: 6972 | B22: Medium | C22: Within Normal Range | D22: Medium | E22: POS Overrings (0.38%)/Excessively High T-Reds
A23: 3708 | B23: Medium | C23: Within Normal range | D23: High | E23: T-Red After (0.29%), Cash O/S (0.04%), Overrings (0.58%)
A24: 10422 | B24: High | C24: High Stat Var (2.16%)/Coordinated Register Theft | D24: High | E24: POS Overrings (0.47%)
A25: 10915 | B25: Medium | C25: High Waste (1.06%) | D25: High | E25: T-Red After (0.45%), Discounts (6.55%)
A26: 11657 | B26: Medium | C26: High Waste (1.29%) | D26: Medium | E26: Within Normal range
A27: 18213 | B27: Medium | C27: High Waste (1.16%) | D27: Medium | E27: Within Normal range
A28: 31357 | B28: Medium | C28: Within Normal range | D28: Medium | E28: Within Normal range
A29: 33222 | B29: High | C29: Bulk Theft/Untracked Waste | D29: Low | E29: Within Normal range
... A37: 5985 | B37: Low | C37: Within Normal range | D37: Low | E37: Within Normal range
A39: Key Recommendations:
A41: FOB Audit (High Risk): Locations 35064 and 13113 should undergo immediate physical inventory audits to address Statistical Variances exceeding $2.3\%$.
A43: Transactional Review (Control Risk): Location 3708 requires a review of T-Red (refund/void) logs, as the high volume of after-total reductions and POS overrings may indicate "phantom" transactions or training gaps.
A45: Discount Monitoring: Locations 20475 and 33704 should review their discounting policies, as their discount percentages are significantly higher ($>7.0\%$) than the network average.
A47: Risk Criteria Breakdown
A49: High Risk (FOB): Assigned to locations with Statistical Variance (product loss) $>2.0\%$ or combined FOB costs $>5.5\%$ of sales.
A51: High Risk (Controls): Assigned to locations with significantly elevated transaction corrections (T-Red after total) or large cash handling discrepancies.
A53: Low Risk: Assigned to locations that performed in the best 25th percentile across all indicators.
A55: Within Normal Range: Indicates the location's metrics fall within the average/expected bounds compared to the rest of the group.

Sheet RGR Dates
A1: STORE # | B1: STORE NAME | C1: DATE RGR | D1: Confirmed (X) | E1: By Whom | F1: Score
A2: 10422 | B2: Atoka | C2: 46051 | D2: Yes | E2: GG | F2: 0.91
A3: 6972 | B3: Ada | C3: 46063 | D3: Yes | E3: GG
A4: 10915 | B4: Seminole | C4: 46071 | D4: Yes | E4: GG
A5: 5985 | B5: Durant | C5: 46092 | D5: Yes | E5: Sia
A6: 20475 | B6: Sooner | C6: 46107 | D6: Yes | E6: Debra
A7: 33704 | B7: Tecumseh | C7: 46127 | D7: Yes | E7: Lisa
A8: 11657 | B8: Purcell | C8: 46134
A9: 34222 | B9: Harrah | C9: 46155
A10: 33222 | B10: Elgin | C10: 46169 | D10: Yes | E10: GG
A11: 13113 | B11: Madill | C11: 46183 | D11: Yes | E11: Lisa
A12: 31357 | B12: Pauls Valley | C12: 46197
A13: 35064 | B13: Holdenville | C13: 46211 | D13: Yes | E13: GG
A14: 43380 | B14: Tishomingo | C14: 46225 | D14: Yes | E14: Lisa
A15: 3708 | B15: Armore - Broadway | C15: 46260
A16: 5183 | B16: Chickasha | C16: 46281
A17: 33109 | B17: Marietta | C17: 46295 | D17: Yes | E17: Lisa
A18: 24471 | B18: Ardmore Cooper | C18: 46309
A19: 29760 | B19: Duncan | C19: 46323 | D19: Yes | E19: Lisa
A20: 32525 | B20: Sulphur | C20: 46337 | D20: Yes | E20: GG
A21: 18213 | B21: Lindsay | C21: 46338 | D21: ? DO ? GG | E21: DO/GG

Sheet Other Locations
A1: Location Name | B1: Supervisor | C1: Users | D1: Address | E1: Inventory D/W/M Setup Verified | F1: eRestaurant Settings Updated and Verified | G1: Weekly Inventory Count Day | H1: Primary Counting Manager | I1: Mobile Inventory App Training Occurred | J1: Mobile App and 1st Count Training Date | K1: Mobile App Training Scheduled | L1: Martin Brower Delivery Day 1 | M1: Martin Brower Delivery Day 2 | N1: Martin Brower Delivery Day 3
A2: 6178 | C2: 449 | D2: 1291 Main St, Chipley, FL, 32428, USA | E2: No | F2: No | I2: No | K2: =_xlfn.XLOOKUP(A2, $R$2:$R$14, $U$2:$U$14, _xlfn.XLOOKUP(A2, $W$2:$W$14, $Z$2:$Z$14, ""))
A3: 6838 | C3: 468 | D3: 2370 US Highway 331 S, Defuniak Springs, FL, 32435, USA | E3: No | F3: No | I3: No | K3: =_xlfn.XLOOKUP(A3, $R$2:$R$14, $U$2:$U$14, _xlfn.XLOOKUP(A3, $W$2:$W$14, $Z$2:$Z$14, ""))
A4: 10034 | C4: 454 | D4: 2010 S Waukesha St, Bonifay, FL, 32425, USA | E4: No | F4: No | I4: No | K4: =_xlfn.XLOOKUP(A4, $R$2:$R$14, $U$2:$U$14, _xlfn.XLOOKUP(A4, $W$2:$W$14, $Z$2:$Z$14, ""))
A5: 23021 | C5: 390 | D5: 2700 NE 10th St, Oklahoma City, OK, 73117, USA | E5: No | F5: No | I5: No | K5: =_xlfn.XLOOKUP(A5, $R$2:$R$14, $U$2:$U$14, _xlfn.XLOOKUP(A5, $W$2:$W$14, $Z$2:$Z$14, ""))
A6: 28819 | C6: 391 | D6: 196 Shawnee Mall Dr, Shawnee, OK, 74804, USA | E6: No | F6: No | I6: No | K6: =_xlfn.XLOOKUP(A6, $R$2:$R$14, $U$2:$U$14, _xlfn.XLOOKUP(A6, $W$2:$W$14, $Z$2:$Z$14, ""))
A7: 35242 | C7: 452 | D7: 2510 US-231, Cottondale, FL, 32431, USA | E7: No | F7: No | I7: No | K7: =_xlfn.XLOOKUP(A7, $R$2:$R$14, $U$2:$U$14, _xlfn.XLOOKUP(A7, $W$2:$W$14, $Z$2:$Z$14, ""))
A8: 37566 | C8: 457 | D8: 17750 State Highway 285 Dr S, Defuniak Springs, FL, 32435, USA | E8: No | F8: No | I8: No | K8: =_xlfn.XLOOKUP(A8, $R$2:$R$14, $U$2:$U$14, _xlfn.XLOOKUP(A8, $W$2:$W$14, $Z$2:$Z$14, ""))
A9: 38609 | C9: 452 | D9: 16392 US Highway 331 S, Freeport, FL, 32439, USA | E9: No | F9: No | I9: No | K9: =_xlfn.XLOOKUP(A9, $R$2:$R$14, $U$2:$U$14, _xlfn.XLOOKUP(A9, $W$2:$W$14, $Z$2:$Z$14, ""))
A10: 43701 | C10: 24 | D10: 2920 FL-81, Ponce de Leon, FL, 32455, USA | E10: No | F10: No | I10: No
